Workbook
Name lu_CoName: LookupIdx!$B$3:$C$35
Name lu_GEOID: LookupIdx!$A$3:$C$35
Name lu_WrkType: LookupIdx!$F$3:$G$73
Name lu_WrkTypeID_Est: LookupIdx!$H$3:$I$73
Name lu_WrkTypeID_MOE: LookupIdx!$J$3:$K$73

Sheet Forecast
A1: Forecast Share of Work At Home, Telecommute & Home-Based Workers
B3: 0.56 | C3: share of employment eligible to telecommute
B4: 5-Year ACS (2010-2019 Trend) | H4: 1-Year ACS (2010-2019 Trend) | N4: 5-Year ACS (2010-2014 Trend) | T4: Post Covid - Upper | Z4: Post Covid - Lower | AF4: Final
B5: Home-Based | C5: Telecommute | D5: Work At Home | E5: % of Workers Who Can Work At Home | H5: Home-Based | I5: Telecommute | J5: Work At Home | K5: % of Workers Who Can Work At Home | N5: Home-Based | O5: Telecommute | P5: Work At Home | Q5: % of Workers Who Can Work At Home | T5: Home-Based | U5: Telecommute | V5: Work At Home | W5: % of Workers Who Can Work At Home | Z5: Home-Based | AA5: Telecommute | AB5: Work At Home | AC5: % of Workers Who Can Work At Home | AF5: Home-Based | AG5: Telecommute | AH5: Work At Home | AI5: % of Workers Who Can Work At Home
A6: 2010 | B6: =HLOOKUP($A6, WAH_byCounty!$AZ$6:$BI$9, 2, FALSE) -> 0.024156393 | C6: =HLOOKUP($A6, WAH_byCounty!$AZ$6:$BI$9, 3, FALSE) -> 0.02188431 | D6: =SUM(B6:C6) -> 0.046040703 | H6: =B6/D6 * J6 -> 0.022378086 | I6: =C6/D6 * J6 -> 0.020273265 | J6: 0.042651351 | AF6: =$B6 -> 0.024156393 | AG6: =$C6 -> 0.02188431 | AH6: =SUM(AF6:AG6) -> 0.046040703 | AI6: =AF6/$B$3 -> 0.043136416 | AJ6: =AG6/$B$3 -> 0.039079125 | AK6: =AH6/$B$3 -> 0.082215541
A7: 2011 | B7: =HLOOKUP($A7, WAH_byCounty!$AZ$6:$BI$9, 2, FALSE) -> 0.023616541 | C7: =HLOOKUP($A7, WAH_byCounty!$AZ$6:$BI$9, 3, FALSE) -> 0.023317437 | D7: =SUM(B7:C7) -> 0.046933978 | E7: =B7/$B$3 -> 0.042172394 | F7: =C7/$B$3 -> 0.041638281 | G7: =D7/$B$3 -> 0.083810675 | H7: =B7/D7 * J7 -> 0.023758557 | I7: =C7/D7 * J7 -> 0.023457655 | J7: 0.047216212 | AF7: =$B7 -> 0.023616541 | AG7: =$C7 -> 0.023317437 | AH7: =SUM(AF7:AG7) -> 0.046933978 | AI7: =AF7/$B$3 -> 0.042172394 | AJ7: =AG7/$B$3 -> 0.041638281 | AK7: =AH7/$B$3 -> 0.083810675
A8: 2012 | B8: =HLOOKUP($A8, WAH_byCounty!$AZ$6:$BI$9, 2, FALSE) -> 0.022667213 | C8: =HLOOKUP($A8, WAH_byCounty!$AZ$6:$BI$9, 3, FALSE) -> 0.023317753 | D8: =SUM(B8:C8) -> 0.045984966 | E8: =B8/$B$3 -> 0.040477166 | F8: =C8/$B$3 -> 0.041638844 | G8: =D8/$B$3 -> 0.082116011 | H8: =B8/D8 * J8 -> 0.023339433 | I8: =C8/D8 * J8 -> 0.024009265 | J8: 0.047348698 | AF8: =$B8 -> 0.022667213 | AG8: =$C8 -> 0.023317753 | AH8: =SUM(AF8:AG8) -> 0.045984966 | AI8: =AF8/$B$3 -> 0.040477166 | AJ8: =AG8/$B$3 -> 0.041638844 | AK8: =AH8/$B$3 -> 0.082116011
A9: 2013 | B9: =HLOOKUP($A9, WAH_byCounty!$AZ$6:$BI$9, 2, FALSE) -> 0.022171769 | C9: =HLOOKUP($A9, WAH_byCounty!$AZ$6:$BI$9, 3, FALSE) -> 0.02528403 | D9: =SUM(B9:C9) -> 0.047455799 | E9: =B9/$B$3 -> 0.039592445 | F9: =C9/$B$3 -> 0.045150053 | G9: =D9/$B$3 -> 0.084742498 | H9: =B9/D9 * J9 -> 0.023907051 | I9: =C9/D9 * J9 -> 0.027262894 | J9: 0.051169945 | AF9: =$B9 -> 0.022171769 | AG9: =$C9 -> 0.02528403 | AH9: =SUM(AF9:AG9) -> 0.047455799 | AI9: =AF9/$B$3 -> 0.039592445 | AJ9: =AG9/$B$3 -> 0.045150053 | AK9: =AH9/$B$3 -> 0.084742498
A10: 2014 | B10: =HLOOKUP($A10, WAH_byCounty!$AZ$6:$BI$9, 2, FALSE) -> 0.022228968 | C10: =HLOOKUP($A10, WAH_byCounty!$AZ$6:$BI$9, 3, FALSE) -> 0.0266197 | D10: =SUM(B10:C10) -> 0.048848668 | E10: =B10/$B$3 -> 0.039694585 | F10: =C10/$B$3 -> 0.047535179 | G10: =D10/$B$3 -> 0.087229764 | H10: =B10/D10 * J10 -> 0.025486223 | I10: =C10/D10 * J10 -> 0.030520339 | J10: 0.056006562 | AF10: =$B10 -> 0.022228968 | AG10: =$C10 -> 0.0266197 | AH10: =SUM(AF10:AG10) -> 0.048848668 | AI10: =AF10/$B$3 -> 0.039694585 | AJ10: =AG10/$B$3 -> 0.047535179 | AK10: =AH10/$B$3 -> 0.087229764
A11: 2015 | B11: =HLOOKUP($A11, WAH_byCounty!$AZ$6:$BI$9, 2, FALSE) -> 0.022692701 | C11: =HLOOKUP($A11, WAH_byCounty!$AZ$6:$BI$9, 3, FALSE) -> 0.028966157 | D11: =SUM(B11:C11) -> 0.051658859 | E11: =B11/$B$3 -> 0.040522681 | F11: =C11/$B$3 -> 0.051725281 | G11: =D11/$B$3 -> 0.092247962 | H11: =B11/D11 * J11 -> 0.024860784 | I11: =C11/D11 * J11 -> 0.031733612 | J11: 0.056594397 | AF11: =$B11 -> 0.022692701 | AG11: =$C11 -> 0.028966157 | AH11: =SUM(AF11:AG11) -> 0.051658859 | AI11: =AF11/$B$3 -> 0.040522681 | AJ11: =AG11/$B$3 -> 0.051725281 | AK11: =AH11/$B$3 -> 0.092247962
A12: 2016 | B12: =HLOOKUP($A12, WAH_byCounty!$AZ$6:$BI$9, 2, FALSE) -> 0.023436385 | C12: =HLOOKUP($A12, WAH_byCounty!$AZ$6:$BI$9, 3, FALSE) -> 0.029703592 | D12: =SUM(B12:C12) -> 0.053139977 | E12: =B12/$B$3 -> 0.041850688 | F12: =C12/$B$3 -> 0.053042128 | G12: =D12/$B$3 -> 0.094892816 | H12: =B12/D12 * J12 -> 0.025492764 | I12: =C12/D12 * J12 -> 0.032309874 | J12: 0.057802638 | AF12: =$B12 -> 0.023436385 | AG12: =$C12 -> 0.029703592 | AH12: =SUM(AF12:AG12) -> 0.053139977 | AI12: =AF12/$B$3 -> 0.041850688 | AJ12: =AG12/$B$3 -> 0.053042128 | AK12: =AH12/$B$3 -> 0.094892816
A13: 2017 | B13: =HLOOKUP($A13, WAH_byCounty!$AZ$6:$BI$9, 2, FALSE) -> 0.025113206 | C13: =HLOOKUP($A13, WAH_byCounty!$AZ$6:$BI$9, 3, FALSE) -> 0.032081021 | D13: =SUM(B13:C13) -> 0.057194228 | E13: =B13/$B$3 -> 0.044845011 | F13: =C13/$B$3 -> 0.057287538 | G13: =D13/$B$3 -> 0.10213255 | H13: =B13/D13 * J13 -> 0.029327256 | I13: =C13/D13 * J13 -> 0.037464286 | J13: 0.066791542 | AF13: =$B13 -> 0.025113206 | AG13: =$C13 -> 0.032081021 | AH13: =SUM(AF13:AG13) -> 0.057194228 | AI13: =AF13/$B$3 -> 0.044845011 | AJ13: =AG13/$B$3 -> 0.057287538 | AK13: =AH13/$B$3 -> 0.10213255
A14: 2018 | B14: =HLOOKUP($A14, WAH_byCounty!$AZ$6:$BI$9, 2, FALSE) -> 0.026391708 | C14: =HLOOKUP($A14, WAH_byCounty!$AZ$6:$BI$9, 3, FALSE) -> 0.033935668 | D14: =SUM(B14:C14) -> 0.060327376 | E14: =B14/$B$3 -> 0.04712805 | F14: =C14/$B$3 -> 0.060599407 | G14: =D14/$B$3 -> 0.10772746 | H14: =B14/D14 * J14 -> 0.028318982 | I14: =C14/D14 * J14 -> 0.036413845 | J14: 0.064732827 | AF14: =$B14 -> 0.026391708 | AG14: =$C14 -> 0.033935668 | AH14: =SUM(AF14:AG14) -> 0.060327376 | AI14: =AF14/$B$3 -> 0.04712805 | AJ14: =AG14/$B$3 -> 0.060599407 | AK14: =AH14/$B$3 -> 0.10772746
A15: 2019 | B15: =HLOOKUP($A15, WAH_byCounty!$AZ$6:$BI$9, 2, FALSE) -> 0.026666597 | C15: =HLOOKUP($A15, WAH_byCounty!$AZ$6:$BI$9, 3, FALSE) -> 0.036494763 | D15: =SUM(B15:C15) -> 0.06316136 | E15: =B15/$B$3 -> 0.047618923 | F15: =C15/$B$3 -> 0.06516922 | G15: =D15/$B$3 -> 0.11278814 | H15: =B15/D15 * J15 -> 0.029748085 | I15: =C15/D15 * J15 -> 0.040711957 | J15: 0.070460042 | K15: =H15/$B$3 -> 0.053121581 | L15: =I15/$B$3 -> 0.072699923 | M15: =J15/$B$3 -> 0.1258215 | Q15: =N15/$B$3 -> 0 | R15: =O15/$B$3 -> 0 | S15: =P15/$B$3 -> 0 | T15: =B15 -> 0.026666597 | U15: =C15 -> 0.036494763 | V15: =SUM(T15:U15) -> 0.06316136 | W15: =T15/$B$3 -> 0.047618923 | X15: =U15/$B$3 -> 0.06516922 | Y15: =V15/$B$3 -> 0.11278814 | Z15: =B15 -> 0.026666597 | AA15: =C15 -> 0.036494763 | AB15: =SUM(Z15:AA15) -> 0.06316136 | AC15: =Z15/$B$3 -> 0.047618923 | AD15: =AA15/$B$3 -> 0.06516922 | AE15: =AB15/$B$3 -> 0.11278814 | AF15: =$B15 -> 0.026666597 | AG15: =$C15 -> 0.036494763 | AH15: =SUM(AF15:AG15) -> 0.06316136 | AI15: =AF15/$B$3 -> 0.047618923 | AJ15: =AG15/$B$3 -> 0.06516922 | AK15: =AH15/$B$3 -> 0.11278814 | AL15: =1/AD15 -> 15.344667 | AM15: =1/AE15 -> 8.8661802
A16: 2020 | B16: =FORECAST($A16, $B$6:$B$15, $A$6:$A$15) + 0.002 -> 0.027864333 | C16: =FORECAST($A16, $C$6:$C$15, $A$6:$A$15) + 0.001 -> 0.038001883 | D16: =SUM(B16:C16) -> 0.065866216 | E16: =B16/$B$3 -> 0.049757738 | F16: =C16/$B$3 -> 0.067860505 | G16: =D16/$B$3 -> 0.11761824 | H16: =FORECAST($A16, $H$6:$H$15, $A$6:$A$15) + 0.002 -> 0.032072515 | I16: =FORECAST($A16, $I$6:$I$15, $A$6:$A$15) + 0.001 -> 0.043358062 | J16: =SUM(H16:I16) -> 0.075430577 | K16: =H16/$B$3 -> 0.057272348 | L16: =I16/$B$3 -> 0.07742511 | M16: =J16/$B$3 -> 0.13469746 | N16: =$B$15 -> 0.026666597 | O16: =FORECAST($A16, $C$10:$C$15, $A$10:$A$15) + 0.001 -> 0.038966278 | P16: =SUM(N16:O16) -> 0.065632875 | Q16: =N16/$B$3 -> 0.047618923 | R16: =O16/$B$3 -> 0.069582639 | S16: =P16/$B$3 -> 0.11720156 | T16: 0.08 | U16: 0.35 | V16: =SUM(T16:U16) -> 0.43 | W16: =T16/$B$3 -> 0.14285714 | X16: =U16/$B$3 -> 0.625 | Y16: =V16/$B$3 -> 0.76785714 | Z16: 0.06 | AA16: 0.35 | AB16: =SUM(Z16:AA16) -> 0.41 | AC16: =Z16/$B$3 -> 0.10714286 | AD16: =AA16/$B$3 -> 0.625 | AE16: =AB16/$B$3 -> 0.73214286 | AF16: 0.06 | AG16: 0.35 | AH16: =SUM(AF16:AG16) -> 0.41 | AI16: =AF16/$B$3 -> 0.10714286 | AJ16: =AG16/$B$3 -> 0.625 | AK16: =AH16/$B$3 -> 0.73214286 | AL16: =1/AD16 -> 1.6 | AM16: =1/AE16 -> 1.3658537
A17: 2021 | B17: =FORECAST($A17, $B$6:$B$15, $A$6:$A$15) + 0.002 -> 0.028218912 | C17: =FORECAST($A17, $C$6:$C$15, $A$6:$A$15) + 0.001 -> 0.039609417 | D17: =SUM(B17:C17) -> 0.067828329 | E17: =B17/$B$3 -> 0.050390915 | F17: =C17/$B$3 -> 0.070731102 | G17: =D17/$B$3 -> 0.12112202 | H17: =FORECAST($A17, $H$6:$H$15, $A$6:$A$15) + 0.002 -> 0.032874477 | I17: =FORECAST($A17, $I$6:$I$15, $A$6:$A$15) + 0.001 -> 0.0455294 | J17: =SUM(H17:I17) -> 0.078403877 | K17: =H17/$B$3 -> 0.058704424 | L17: =I17/$B$3 -> 0.0813025 | M17: =J17/$B$3 -> 0.14000692 | N17: =$B$15 -> 0.026666597 | O17: =FORECAST($A17, $C$10:$C$15, $A$10:$A$15) + 0.001 -> 0.040870886 | P17: =SUM(N17:O17) -> 0.067537483 | Q17: =N17/$B$3 -> 0.047618923 | R17: =O17/$B$3 -> 0.072983725 | S17: =P17/$B$3 -> 0.12060265 | T17: 0.06 | U17: 0.2 | V17: =SUM(T17:U17) -> 0.26 | W17: =T17/$B$3 -> 0.10714286 | X17: =U17/$B$3 -> 0.35714286 | Y17: =V17/$B$3 -> 0.46428571 | Z17: 0.04 | AA17: 0.15 | AB17: =SUM(Z17:AA17) -> 0.19 | AC17: =Z17/$B$3 -> 0.071428571 | AD17: =AA17/$B$3 -> 0.26785714 | AE17: =AB17/$B$3 -> 0.33928571 | AF17: 0.04 | AG17: 0.17 | AH17: =SUM(AF17:AG17) -> 0.21 | AI17: =AF17/$B$3 -> 0.071428571 | AJ17: =AG17/$B$3 -> 0.30357143 | AK17: =AH17/$B$3 -> 0.375 | AL17: =1/AD17 -> 3.7333333 | AM17: =1/AE17 -> 2.9473684
A18: 2022 | B18: =FORECAST($A18, $B$6:$B$15, $A$6:$A$15) + 0.002 -> 0.028573491 | C18: =FORECAST($A18, $C$6:$C$15, $A$6:$A$15) + 0.001 -> 0.041216951 | D18: =SUM(B18:C18) -> 0.069790443 | E18: =B18/$B$3 -> 0.051024092 | F18: =C18/$B$3 -> 0.073601699 | G18: =D18/$B$3 -> 0.12462579 | H18: =FORECAST($A18, $H$6:$H$15, $A$6:$A$15) + 0.002 -> 0.03367644 | I18: =FORECAST($A18, $I$6:$I$15, $A$6:$A$15) + 0.001 -> 0.047700739 | J18: =SUM(H18:I18) -> 0.081377178 | K18: =H18/$B$3 -> 0.060136499 | L18: =I18/$B$3 -> 0.085179891 | M18: =J18/$B$3 -> 0.14531639 | N18: =$B$15 -> 0.026666597 | O18: =FORECAST($A18, $C$10:$C$15, $A$10:$A$15) + 0.001 -> 0.042775494 | P18: =SUM(N18:O18) -> 0.069442091 | Q18: =N18/$B$3 -> 0.047618923 | R18: =O18/$B$3 -> 0.07638481 | S18: =P18/$B$3 -> 0.12400373 | T18: 0.044 | U18: 0.15 | V18: =SUM(T18:U18) -> 0.194 | W18: =T18/$B$3 -> 0.078571429 | X18: =U18/$B$3 -> 0.26785714 | Y18: =V18/$B$3 -> 0.34642857 | Z18: 0.0325 | AA18: 0.1 | AB18: =SUM(Z18:AA18) -> 0.1325 | AC18: =Z18/$B$3 -> 0.058035714 | AD18: =AA18/$B$3 -> 0.17857143 | AE18: =AB18/$B$3 -> 0.23660714 | AF18: 0.0325 | AG18: 0.115 | AH18: =SUM(AF18:AG18) -> 0.1475 | AI18: =AF18/$B$3 -> 0.058035714 | AJ18: =AG18/$B$3 -> 0.20535714 | AK18: =AH18/$B$3 -> 0.26339286 | AL18: =1/AD18 -> 5.6 | AM18: =1/AE18 -> 4.2264151
A19: 2023 | B19: =FORECAST($A19, $B$6:$B$15, $A$6:$A$15) + 0.002 -> 0.028928071 | C19: =FORECAST($A19, $C$6:$C$15, $A$6:$A$15) + 0.001 -> 0.042824486 | D19: =SUM(B19:C19) -> 0.071752556 | E19: =B19/$B$3 -> 0.051657269 | F19: =C19/$B$3 -> 0.076472296 | G19: =D19/$B$3 -> 0.12812957 | H19: =FORECAST($A19, $H$6:$H$15, $A$6:$A$15) + 0.002 -> 0.034478402 | I19: =FORECAST($A19, $I$6:$I$15, $A$6:$A$15) + 0.001 -> 0.049872077 | J19: =SUM(H19:I19) -> 0.084350479 | K19: =H19/$B$3 -> 0.061568575 | L19: =I19/$B$3 -> 0.089057281 | M19: =J19/$B$3 -> 0.15062586 | N19: =$B$15 -> 0.026666597 | O19: =FORECAST($A19, $C$10:$C$15, $A$10:$A$15) + 0.001 -> 0.044680102 | P19: =SUM(N19:O19) -> 0.071346698 | Q19: =N19/$B$3 -> 0.047618923 | R19: =O19/$B$3 -> 0.079785896 | S19: =P19/$B$3 -> 0.12740482 | T19: 0.0375 | U19: 0.12 | V19: =SUM(T19:U19) -> 0.1575 | W19: =T19/$B$3 -> 0.066964286 | X19: =U19/$B$3 -> 0.21428571 | Y19: =V19/$B$3 -> 0.28125 | Z19: 0.03 | AA19: 0.083 | AB19: =SUM(Z19:AA19) -> 0.113 | AC19: =Z19/$B$3 -> 0.053571429 | AD19: =AA19/$B$3 -> 0.14821429 | AE19: =AB19/$B$3 -> 0.20178571 | AF19: 0.03 | AG19: 0.092 | AH19: =SUM(AF19:AG19) -> 0.122 | AI19: =AF19/$B$3 -> 0.053571429 | AJ19: =AG19/$B$3 -> 0.16428571 | AK19: =AH19/$B$3 -> 0.21785714 | AL19: =1/AD19 -> 6.746988 | AM19: =1/AE19 -> 4.9557522
A20: 2024 | B20: =FORECAST($A20, $B$6:$B$15, $A$6:$A$15) + 0.002 -> 0.02928265 | C20: =FORECAST($A20, $C$6:$C$15, $A$6:$A$15) + 0.001 -> 0.04443202 | D20: =SUM(B20:C20) -> 0.07371467 | E20: =B20/$B$3 -> 0.052290446 | F20: =C20/$B$3 -> 0.079342893 | G20: =D20/$B$3 -> 0.13163334 | H20: =FORECAST($A20, $H$6:$H$15, $A$6:$A$15) + 0.002 -> 0.035280364 | I20: =FORECAST($A20, $I$6:$I$15, $A$6:$A$15) + 0.001 -> 0.052043416 | J20: =SUM(H20:I20) -> 0.08732378 | K20: =H20/$B$3 -> 0.063000651 | L20: =I20/$B$3 -> 0.092934671 | M20: =J20/$B$3 -> 0.15593532 | N20: =$B$15 -> 0.026666597 | O20: =FORECAST($A20, $C$10:$C$15, $A$10:$A$15) + 0.001 -> 0.04658471 | P20: =SUM(N20:O20) -> 0.073251306 | Q20: =N20/$B$3 -> 0.047618923 | R20: =O20/$B$3 -> 0.083186981 | S20: =P20/$B$3 -> 0.1308059 | T20: 0.035 | U20: 0.1025 | V20: =SUM(T20:U20) -> 0.1375 | W20: =T20/$B$3 -> 0.0625 | X20: =U20/$B$3 -> 0.18303571 | Y20: =V20/$B$3 -> 0.24553571 | Z20: =Z19 -> 0.03 | AA20: 0.08 | AB20: =SUM(Z20:AA20) -> 0.11 | AC20: =Z20/$B$3 -> 0.053571429 | AD20: =AA20/$B$3 -> 0.14285714 | AE20: =AB20/$B$3 -> 0.19642857 | AF20: =AF19 -> 0.03 | AG20: 0.08 | AH20: =SUM(AF20:AG20) -> 0.11 | AI20: =AF20/$B$3 -> 0.053571429 | AJ20: =AG20/$B$3 -> 0.14285714 | AK20: =AH20/$B$3 -> 0.19642857 | AL20: =1/AD20 -> 7 | AM20: =1/AE20 -> 5.0909091
A21: 2025 | B21: =FORECAST($A21, $B$6:$B$15, $A$6:$A$15) + 0.002 -> 0.029637229 | C21: =FORECAST($A21, $C$6:$C$15, $A$6:$A$15) + 0.001 -> 0.046039555 | D21: =SUM(B21:C21) -> 0.075676783 | E21: =B21/$B$3 -> 0.052923623 | F21: =C21/$B$3 -> 0.082213491 | G21: =D21/$B$3 -> 0.13513711 | H21: =FORECAST($A21, $H$6:$H$15, $A$6:$A$15) + 0.002 -> 0.036082327 | I21: =FORECAST($A21, $I$6:$I$15, $A$6:$A$15) + 0.001 -> 0.054214755 | J21: =SUM(H21:I21) -> 0.090297081 | K21: =H21/$B$3 -> 0.064432726 | L21: =I21/$B$3 -> 0.096812062 | M21: =J21/$B$3 -> 0.16124479 | N21: =$B$15 -> 0.026666597 | O21: =FORECAST($A21, $C$10:$C$15, $A$10:$A$15) + 0.001 -> 0.048489317 | P21: =SUM(N21:O21) -> 0.075155914 | Q21: =N21/$B$3 -> 0.047618923 | R21: =O21/$B$3 -> 0.086588067 | S21: =P21/$B$3 -> 0.13420699 | T21: =T20 -> 0.035 | U21: 0.1 | V21: =SUM(T21:U21) -> 0.135 | W21: =T21/$B$3 -> 0.0625 | X21: =U21/$B$3 -> 0.17857143 | Y21: =V21/$B$3 -> 0.24107143 | Z21: =Z20 -> 0.03 | AA21: =AA20 -> 0.08 | AB21: =SUM(Z21:AA21) -> 0.11 | AC21: =Z21/$B$3 -> 0.053571429 | AD21: =AA21/$B$3 -> 0.14285714 | AE21: =AB21/$B$3 -> 0.19642857 | AF21: =AF20 -> 0.03 | AG21: 0.074 | AH21: =SUM(AF21:AG21) -> 0.104 | AI21: =AF21/$B$3 -> 0.053571429 | AJ21: =AG21/$B$3 -> 0.13214286 | AK21: =AH21/$B$3 -> 0.18571429 | AL21: =1/AD21 -> 7 | AM21: =1/AE21 -> 5.0909091
A22: 2026 | B22: =FORECAST($A22, $B$6:$B$15, $A$6:$A$15) + 0.002 -> 0.029991808 | C22: =FORECAST($A22, $C$6:$C$15, $A$6:$A$15) + 0.001 -> 0.047647089 | D22: =SUM(B22:C22) -> 0.077638897 | E22: =B22/$B$3 -> 0.0535568 | F22: =C22/$B$3 -> 0.085084088 | G22: =D22/$B$3 -> 0.13864089 | H22: =FORECAST($A22, $H$6:$H$15, $A$6:$A$15) + 0.002 -> 0.036884289 | I22: =FORECAST($A22, $I$6:$I$15, $A$6:$A$15) + 0.001 -> 0.056386093 | J22: =SUM(H22:I22) -> 0.093270382 | K22: =H22/$B$3 -> 0.065864802 | L22: =I22/$B$3 -> 0.10068945 | M22: =J22/$B$3 -> 0.16655425 | N22: =$B$15 -> 0.026666597 | O22: =FORECAST($A22, $C$10:$C$15, $A$10:$A$15) + 0.001 -> 0.050393925 | P22: =SUM(N22:O22) -> 0.077060522 | Q22: =N22/$B$3 -> 0.047618923 | R22: =O22/$B$3 -> 0.089989152 | S22: =P22/$B$3 -> 0.13760808 | T22: =T21 -> 0.035 | U22: =U21 -> 0.1 | V22: =SUM(T22:U22) -> 0.135 | W22: =T22/$B$3 -> 0.0625 | X22: =U22/$B$3 -> 0.17857143 | Y22: =V22/$B$3 -> 0.24107143 | Z22: =Z21 -> 0.03 | AA22: =AA21 -> 0.08 | AB22: =SUM(Z22:AA22) -> 0.11 | AC22: =Z22/$B$3 -> 0.053571429 | AD22: =AA22/$B$3 -> 0.14285714 | AE22: =AB22/$B$3 -> 0.19642857 | AF22: =AF21 -> 0.03 | AG22: 0.071 | AH22: =SUM(AF22:AG22) -> 0.101 | AI22: =AF22/$B$3 -> 0.053571429 | AJ22: =AG22/$B$3 -> 0.12678571 | AK22: =AH22/$B$3 -> 0.18035714 | AL22: =1/AD22 -> 7 | AM22: =1/AE22 -> 5.0909091
A23: 2027 | B23: =FORECAST($A23, $B$6:$B$15, $A$6:$A$15) + 0.002 -> 0.030346387 | C23: =FORECAST($A23, $C$6:$C$15, $A$6:$A$15) + 0.001 -> 0.049254624 | D23: =SUM(B23:C23) -> 0.079601011 | E23: =B23/$B$3 -> 0.054189977 | F23: =C23/$B$3 -> 0.087954685 | G23: =D23/$B$3 -> 0.14214466 | H23: =FORECAST($A23, $H$6:$H$15, $A$6:$A$15) + 0.002 -> 0.037686251 | I23: =FORECAST($A23, $I$6:$I$15, $A$6:$A$15) + 0.001 -> 0.058557432 | J23: =SUM(H23:I23) -> 0.096243683 | K23: =H23/$B$3 -> 0.067296877 | L23: =I23/$B$3 -> 0.10456684 | M23: =J23/$B$3 -> 0.17186372 | N23: =$B$15 -> 0.026666597 | O23: =FORECAST($A23, $C$10:$C$15, $A$10:$A$15) + 0.001 -> 0.052298533 | P23: =SUM(N23:O23) -> 0.07896513 | Q23: =N23/$B$3 -> 0.047618923 | R23: =O23/$B$3 -> 0.093390238 | S23: =P23/$B$3 -> 0.14100916 | T23: =T22 -> 0.035 | U23: =U22 -> 0.1 | V23: =SUM(T23:U23) -> 0.135 | W23: =T23/$B$3 -> 0.0625 | X23: =U23/$B$3 -> 0.17857143 | Y23: =V23/$B$3 -> 0.24107143 | Z23: =Z22 -> 0.03 | AA23: =AA22 -> 0.08 | AB23: =SUM(Z23:AA23) -> 0.11 | AC23: =Z23/$B$3 -> 0.053571429 | AD23: =AA23/$B$3 -> 0.14285714 | AE23: =AB23/$B$3 -> 0.19642857 | AF23: =AF22 -> 0.03 | AG23: 0.07 | AH23: =SUM(AF23:AG23) -> 0.1 | AI23: =AF23/$B$3 -> 0.053571429 | AJ23: =AG23/$B$3 -> 0.125 | AK23: =AH23/$B$3 -> 0.17857143 | AL23: =1/AD23 -> 7 | AM23: =1/AE23 -> 5.0909091
A24: 2028 | B24: =FORECAST($A24, $B$6:$B$15, $A$6:$A$15) + 0.002 -> 0.030700966 | C24: =FORECAST($A24, $C$6:$C$15, $A$6:$A$15) + 0.001 -> 0.050862158 | D24: =SUM(B24:C24) -> 0.081563124 | E24: =B24/$B$3 -> 0.054823154 | F24: =C24/$B$3 -> 0.090825282 | G24: =D24/$B$3 -> 0.14564844 | H24: =FORECAST($A24, $H$6:$H$15, $A$6:$A$15) + 0.002 -> 0.038488214 | I24: =FORECAST($A24, $I$6:$I$15, $A$6:$A$15) + 0.001 -> 0.06072877 | J24: =SUM(H24:I24) -> 0.099216984 | K24: =H24/$B$3 -> 0.068728953 | L24: =I24/$B$3 -> 0.10844423 | M24: =J24/$B$3 -> 0.17717319 | N24: =$B$15 -> 0.026666597 | O24: =FORECAST($A24, $C$10:$C$15, $A$10:$A$15) + 0.001 -> 0.054203141 | P24: =SUM(N24:O24) -> 0.080869738 | Q24: =N24/$B$3 -> 0.047618923 | R24: =O24/$B$3 -> 0.096791323 | S24: =P24/$B$3 -> 0.14441025 | T24: =T23 -> 0.035 | U24: =U23 -> 0.1 | V24: =SUM(T24:U24) -> 0.135 | W24: =T24/$B$3 -> 0.0625 | X24: =U24/$B$3 -> 0.17857143 | Y24: =V24/$B$3 -> 0.24107143 | Z24: =Z23 -> 0.03 | AA24: =AA23 -> 0.08 | AB24: =SUM(Z24:AA24) -> 0.11 | AC24: =Z24/$B$3 -> 0.053571429 | AD24: =AA24/$B$3 -> 0.14285714 | AE24: =AB24/$B$3 -> 0.19642857 | AF24: =AF23 -> 0.03 | AG24: 0.07 | AH24: =SUM(AF24:AG24) -> 0.1 | AI24: =AF24/$B$3 -> 0.053571429 | AJ24: =AG24/$B$3 -> 0.125 | AK24: =AH24/$B$3 -> 0.17857143 | AL24: =1/AD24 -> 7 | AM24: =1/AE24 -> 5.0909091
A25: 2029 | B25: =FORECAST($A25, $B$6:$B$15, $A$6:$A$15) + 0.002 -> 0.031055545 | C25: =FORECAST($A25, $C$6:$C$15, $A$6:$A$15) + 0.001 -> 0.052469692 | D25: =SUM(B25:C25) -> 0.083525238 | E25: =B25/$B$3 -> 0.055456331 | F25: =C25/$B$3 -> 0.093695879 | G25: =D25/$B$3 -> 0.14915221 | H25: =FORECAST($A25, $H$6:$H$15, $A$6:$A$15) + 0.002 -> 0.039290176 | I25: =FORECAST($A25, $I$6:$I$15, $A$6:$A$15) + 0.001 -> 0.062900109 | J25: =SUM(H25:I25) -> 0.10219028 | K25: =H25/$B$3 -> 0.070161029 | L25: =I25/$B$3 -> 0.11232162 | M25: =J25/$B$3 -> 0.18248265 | N25: =$B$15 -> 0.026666597 | O25: =FORECAST($A25, $C$10:$C$15, $A$10:$A$15) + 0.001 -> 0.056107749 | P25: =SUM(N25:O25) -> 0.082774346 | Q25: =N25/$B$3 -> 0.047618923 | R25: =O25/$B$3 -> 0.10019241 | S25: =P25/$B$3 -> 0.14781133 | T25: =T24 -> 0.035 | U25: =U24 -> 0.1 | V25: =SUM(T25:U25) -> 0.135 | W25: =T25/$B$3 -> 0.0625 | X25: =U25/$B$3 -> 0.17857143 | Y25: =V25/$B$3 -> 0.24107143 | Z25: =Z24 -> 0.03 | AA25: =AA24 -> 0.08 | AB25: =SUM(Z25:AA25) -> 0.11 | AC25: =Z25/$B$3 -> 0.053571429 | AD25: =AA25/$B$3 -> 0.14285714 | AE25: =AB25/$B$3 -> 0.19642857 | AF25: =AF24 -> 0.03 | AG25: 0.0705 | AH25: =SUM(AF25:AG25) -> 0.1005 | AI25: =AF25/$B$3 -> 0.053571429 | AJ25: =AG25/$B$3 -> 0.12589286 | AK25: =AH25/$B$3 -> 0.17946429 | AL25: =1/AD25 -> 7 | AM25: =1/AE25 -> 5.0909091
A26: 2030 | B26: =FORECAST($A26, $B$6:$B$15, $A$6:$A$15) + 0.002 -> 0.031410124 | C26: =FORECAST($A26, $C$6:$C$15, $A$6:$A$15) + 0.001 -> 0.054077227 | D26: =SUM(B26:C26) -> 0.085487351 | E26: =B26/$B$3 -> 0.056089508 | F26: =C26/$B$3 -> 0.096566477 | G26: =D26/$B$3 -> 0.15265598 | H26: =FORECAST($A26, $H$6:$H$15, $A$6:$A$15) + 0.002 -> 0.040092138 | I26: =FORECAST($A26, $I$6:$I$15, $A$6:$A$15) + 0.001 -> 0.065071448 | J26: =SUM(H26:I26) -> 0.10516359 | K26: =H26/$B$3 -> 0.071593104 | L26: =I26/$B$3 -> 0.11619901 | M26: =J26/$B$3 -> 0.18779212 | N26: =$B$15 -> 0.026666597 | O26: =FORECAST($A26, $C$10:$C$15, $A$10:$A$15) + 0.001 -> 0.058012357 | P26: =SUM(N26:O26) -> 0.084678954 | Q26: =N26/$B$3 -> 0.047618923 | R26: =O26/$B$3 -> 0.10359349 | S26: =P26/$B$3 -> 0.15121242 | T26: =T25 -> 0.035 | U26: =U25 -> 0.1 | V26: =SUM(T26:U26) -> 0.135 | W26: =T26/$B$3 -> 0.0625 | X26: =U26/$B$3 -> 0.17857143 | Y26: =V26/$B$3 -> 0.24107143 | Z26: =Z25 -> 0.03 | AA26: =AA25 -> 0.08 | AB26: =SUM(Z26:AA26) -> 0.11 | AC26: =Z26/$B$3 -> 0.053571429 | AD26: =AA26/$B$3 -> 0.14285714 | AE26: =AB26/$B$3 -> 0.19642857 | AF26: =AF25 -> 0.03 | AG26: 0.072 | AH26: =SUM(AF26:AG26) -> 0.102 | AI26: =AF26/$B$3 -> 0.053571429 | AJ26: =AG26/$B$3 -> 0.12857143 | AK26: =AH26/$B$3 -> 0.18214286 | AL26: =1/AD26 -> 7 | AM26: =1/AE26 -> 5.0909091
A27: 2031 | B27: =FORECAST($A27, $B$6:$B$15, $A$6:$A$15) + 0.002 -> 0.031764703 | C27: =FORECAST($A27, $C$6:$C$15, $A$6:$A$15) + 0.001 -> 0.055684761 | D27: =SUM(B27:C27) -> 0.087449465 | E27: =B27/$B$3 -> 0.056722685 | F27: =C27/$B$3 -> 0.099437074 | G27: =D27/$B$3 -> 0.15615976 | H27: =FORECAST($A27, $H$6:$H$15, $A$6:$A$15) + 0.002 -> 0.040894101 | I27: =FORECAST($A27, $I$6:$I$15, $A$6:$A$15) + 0.001 -> 0.067242786 | J27: =SUM(H27:I27) -> 0.10813689 | K27: =H27/$B$3 -> 0.07302518 | L27: =I27/$B$3 -> 0.1200764 | M27: =J27/$B$3 -> 0.19310158 | N27: =$B$15 -> 0.026666597 | O27: =FORECAST($A27, $C$10:$C$15, $A$10:$A$15) + 0.001 -> 0.059916965 | P27: =SUM(N27:O27) -> 0.086583562 | Q27: =N27/$B$3 -> 0.047618923 | R27: =O27/$B$3 -> 0.10699458 | S27: =P27/$B$3 -> 0.1546135 | T27: =T26 -> 0.035 | U27: =U26 -> 0.1 | V27: =SUM(T27:U27) -> 0.135 | W27: =T27/$B$3 -> 0.0625 | X27: =U27/$B$3 -> 0.17857143 | Y27: =V27/$B$3 -> 0.24107143 | Z27: =Z26 -> 0.03 | AA27: =AA26 -> 0.08 | AB27: =SUM(Z27:AA27) -> 0.11 | AC27: =Z27/$B$3 -> 0.053571429 | AD27: =AA27/$B$3 -> 0.14285714 | AE27: =AB27/$B$3 -> 0.19642857 | AF27: =AF26 -> 0.03 | AG27: =(AG$46-AG$26)/($A$46-$A$26) + AG26 -> 0.0734 | AH27: =SUM(AF27:AG27) -> 0.1034 | AI27: =AF27/$B$3 -> 0.053571429 | AJ27: =AG27/$B$3 -> 0.13107143 | AK27: =AH27/$B$3 -> 0.18464286 | AL27: =1/AD27 -> 7 | AM27: =1/AE27 -> 5.0909091
A28: 2032 | B28: =FORECAST($A28, $B$6:$B$15, $A$6:$A$15) + 0.002 -> 0.032119282 | C28: =FORECAST($A28, $C$6:$C$15, $A$6:$A$15) + 0.001 -> 0.057292296 | D28: =SUM(B28:C28) -> 0.089411578 | E28: =B28/$B$3 -> 0.057355862 | F28: =C28/$B$3 -> 0.10230767 | G28: =D28/$B$3 -> 0.15966353 | H28: =FORECAST($A28, $H$6:$H$15, $A$6:$A$15) + 0.002 -> 0.041696063 | I28: =FORECAST($A28, $I$6:$I$15, $A$6:$A$15) + 0.001 -> 0.069414125 | J28: =SUM(H28:I28) -> 0.11111019 | K28: =H28/$B$3 -> 0.074457255 | L28: =I28/$B$3 -> 0.12395379 | M28: =J28/$B$3 -> 0.19841105 | N28: =$B$15 -> 0.026666597 | O28: =FORECAST($A28, $C$10:$C$15, $A$10:$A$15) + 0.001 -> 0.061821573 | P28: =SUM(N28:O28) -> 0.088488169 | Q28: =N28/$B$3 -> 0.047618923 | R28: =O28/$B$3 -> 0.11039567 | S28: =P28/$B$3 -> 0.15801459 | T28: =T27 -> 0.035 | U28: =U27 -> 0.1 | V28: =SUM(T28:U28) -> 0.135 | W28: =T28/$B$3 -> 0.0625 | X28: =U28/$B$3 -> 0.17857143 | Y28: =V28/$B$3 -> 0.24107143 | Z28: =Z27 -> 0.03 | AA28: =AA27 -> 0.08 | AB28: =SUM(Z28:AA28) -> 0.11 | AC28: =Z28/$B$3 -> 0.053571429 | AD28: =AA28/$B$3 -> 0.14285714 | AE28: =AB28/$B$3 -> 0.19642857 | AF28: =AF27 -> 0.03 | AG28: =(AG$46-AG$26)/($A$46-$A$26) + AG27 -> 0.0748 | AH28: =SUM(AF28:AG28) -> 0.1048 | AI28: =AF28/$B$3 -> 0.053571429 | AJ28: =AG28/$B$3 -> 0.13357143 | AK28: =AH28/$B$3 -> 0.18714286 | AL28: =1/AD28 -> 7 | AM28: =1/AE28 -> 5.0909091
A29: 2033 | B29: =FORECAST($A29, $B$6:$B$15, $A$6:$A$15) + 0.002 -> 0.032473862 | C29: =FORECAST($A29, $C$6:$C$15, $A$6:$A$15) + 0.001 -> 0.05889983 | D29: =SUM(B29:C29) -> 0.091373692 | E29: =B29/$B$3 -> 0.057989039 | F29: =C29/$B$3 -> 0.10517827 | G29: =D29/$B$3 -> 0.16316731 | H29: =FORECAST($A29, $H$6:$H$15, $A$6:$A$15) + 0.002 -> 0.042498025 | I29: =FORECAST($A29, $I$6:$I$15, $A$6:$A$15) + 0.001 -> 0.071585463 | J29: =SUM(H29:I29) -> 0.11408349 | K29: =H29/$B$3 -> 0.075889331 | L29: =I29/$B$3 -> 0.12783118 | M29: =J29/$B$3 -> 0.20372052 | N29: =$B$15 -> 0.026666597 | O29: =FORECAST($A29, $C$10:$C$15, $A$10:$A$15) + 0.001 -> 0.06372618 | P29: =SUM(N29:O29) -> 0.090392777 | Q29: =N29/$B$3 -> 0.047618923 | R29: =O29/$B$3 -> 0.11379675 | S29: =P29/$B$3 -> 0.16141567 | T29: =T28 -> 0.035 | U29: =U28 -> 0.1 | V29: =SUM(T29:U29) -> 0.135 | W29: =T29/$B$3 -> 0.0625 | X29: =U29/$B$3 -> 0.17857143 | Y29: =V29/$B$3 -> 0.24107143 | Z29: =Z28 -> 0.03 | AA29: =AA28 -> 0.08 | AB29: =SUM(Z29:AA29) -> 0.11 | AC29: =Z29/$B$3 -> 0.053571429 | AD29: =AA29/$B$3 -> 0.14285714 | AE29: =AB29/$B$3 -> 0.19642857 | AF29: =AF28 -> 0.03 | AG29: =(AG$46-AG$26)/($A$46-$A$26) + AG28 -> 0.0762 | AH29: =SUM(AF29:AG29) -> 0.1062 | AI29: =AF29/$B$3 -> 0.053571429 | AJ29: =AG29/$B$3 -> 0.13607143 | AK29: =AH29/$B$3 -> 0.18964286 | AL29: =1/AD29 -> 7 | AM29: =1/AE29 -> 5.0909091
A30: 2034 | B30: =FORECAST($A30, $B$6:$B$15, $A$6:$A$15) + 0.002 -> 0.032828441 | C30: =FORECAST($A30, $C$6:$C$15, $A$6:$A$15) + 0.001 -> 0.060507365 | D30: =SUM(B30:C30) -> 0.093335805 | E30: =B30/$B$3 -> 0.058622216 | F30: =C30/$B$3 -> 0.10804887 | G30: =D30/$B$3 -> 0.16667108 | H30: =FORECAST($A30, $H$6:$H$15, $A$6:$A$15) + 0.002 -> 0.043299988 | I30: =FORECAST($A30, $I$6:$I$15, $A$6:$A$15) + 0.001 -> 0.073756802 | J30: =SUM(H30:I30) -> 0.11705679 | K30: =H30/$B$3 -> 0.077321407 | L30: =I30/$B$3 -> 0.13170857 | M30: =J30/$B$3 -> 0.20902998 | N30: =$B$15 -> 0.026666597 | O30: =FORECAST($A30, $C$10:$C$15, $A$10:$A$15) + 0.001 -> 0.065630788 | P30: =SUM(N30:O30) -> 0.092297385 | Q30: =N30/$B$3 -> 0.047618923 | R30: =O30/$B$3 -> 0.11719784 | S30: =P30/$B$3 -> 0.16481676 | T30: =T29 -> 0.035 | U30: =U29 -> 0.1 | V30: =SUM(T30:U30) -> 0.135 | W30: =T30/$B$3 -> 0.0625 | X30: =U30/$B$3 -> 0.17857143 | Y30: =V30/$B$3 -> 0.24107143 | Z30: =Z29 -> 0.03 | AA30: =AA29 -> 0.08 | AB30: =SUM(Z30:AA30) -> 0.11 | AC30: =Z30/$B$3 -> 0.053571429 | AD30: =AA30/$B$3 -> 0.14285714 | AE30: =AB30/$B$3 -> 0.19642857 | AF30: =AF29 -> 0.03 | AG30: =(AG$46-AG$26)/($A$46-$A$26) + AG29 -> 0.0776 | AH30: =SUM(AF30:AG30) -> 0.1076 | AI30: =AF30/$B$3 -> 0.053571429 | AJ30: =AG30/$B$3 -> 0.13857143 | AK30: =AH30/$B$3 -> 0.19214286 | AL30: =1/AD30 -> 7 | AM30: =1/AE30 -> 5.0909091
A31: 2035 | B31: =FORECAST($A31, $B$6:$B$15, $A$6:$A$15) + 0.002 -> 0.03318302 | C31: =FORECAST($A31, $C$6:$C$15, $A$6:$A$15) + 0.001 -> 0.062114899 | D31: =SUM(B31:C31) -> 0.095297919 | E31: =B31/$B$3 -> 0.059255393 | F31: =C31/$B$3 -> 0.11091946 | G31: =D31/$B$3 -> 0.17017486 | H31: =FORECAST($A31, $H$6:$H$15, $A$6:$A$15) + 0.002 -> 0.04410195 | I31: =FORECAST($A31, $I$6:$I$15, $A$6:$A$15) + 0.001 -> 0.075928141 | J31: =SUM(H31:I31) -> 0.12003009 | K31: =H31/$B$3 -> 0.078753482 | L31: =I31/$B$3 -> 0.13558597 | M31: =J31/$B$3 -> 0.21433945 | N31: =$B$15 -> 0.026666597 | O31: =FORECAST($A31, $C$10:$C$15, $A$10:$A$15) + 0.001 -> 0.067535396 | P31: =SUM(N31:O31) -> 0.094201993 | Q31: =N31/$B$3 -> 0.047618923 | R31: =O31/$B$3 -> 0.12059892 | S31: =P31/$B$3 -> 0.16821784 | T31: =T30 -> 0.035 | U31: =U30 -> 0.1 | V31: =SUM(T31:U31) -> 0.135 | W31: =T31/$B$3 -> 0.0625 | X31: =U31/$B$3 -> 0.17857143 | Y31: =V31/$B$3 -> 0.24107143 | Z31: =Z30 -> 0.03 | AA31: =AA30 -> 0.08 | AB31: =SUM(Z31:AA31) -> 0.11 | AC31: =Z31/$B$3 -> 0.053571429 | AD31: =AA31/$B$3 -> 0.14285714 | AE31: =AB31/$B$3 -> 0.19642857 | AF31: =AF30 -> 0.03 | AG31: =(AG$46-AG$26)/($A$46-$A$26) + AG30 -> 0.079 | AH31: =SUM(AF31:AG31) -> 0.109 | AI31: =AF31/$B$3 -> 0.053571429 | AJ31: =AG31/$B$3 -> 0.14107143 | AK31: =AH31/$B$3 -> 0.19464286 | AL31: =1/AD31 -> 7 | AM31: =1/AE31 -> 5.0909091
A32: 2036 | B32: =FORECAST($A32, $B$6:$B$15, $A$6:$A$15) + 0.002 -> 0.033537599 | C32: =FORECAST($A32, $C$6:$C$15, $A$6:$A$15) + 0.001 -> 0.063722433 | D32: =SUM(B32:C32) -> 0.097260032 | E32: =B32/$B$3 -> 0.05988857 | F32: =C32/$B$3 -> 0.11379006 | G32: =D32/$B$3 -> 0.17367863 | H32: =FORECAST($A32, $H$6:$H$15, $A$6:$A$15) + 0.002 -> 0.044903912 | I32: =FORECAST($A32, $I$6:$I$15, $A$6:$A$15) + 0.001 -> 0.078099479 | J32: =SUM(H32:I32) -> 0.12300339 | K32: =H32/$B$3 -> 0.080185558 | L32: =I32/$B$3 -> 0.13946336 | M32: =J32/$B$3 -> 0.21964891 | N32: =$B$15 -> 0.026666597 | O32: =FORECAST($A32, $C$10:$C$15, $A$10:$A$15) + 0.001 -> 0.069440004 | P32: =SUM(N32:O32) -> 0.096106601 | Q32: =N32/$B$3 -> 0.047618923 | R32: =O32/$B$3 -> 0.12400001 | S32: =P32/$B$3 -> 0.17161893 | T32: =T31 -> 0.035 | U32: =U31 -> 0.1 | V32: =SUM(T32:U32) -> 0.135 | W32: =T32/$B$3 -> 0.0625 | X32: =U32/$B$3 -> 0.17857143 | Y32: =V32/$B$3 -> 0.24107143 | Z32: =Z31 -> 0.03 | AA32: =AA31 -> 0.08 | AB32: =SUM(Z32:AA32) -> 0.11 | AC32: =Z32/$B$3 -> 0.053571429 | AD32: =AA32/$B$3 -> 0.14285714 | AE32: =AB32/$B$3 -> 0.19642857 | AF32: =AF31 -> 0.03 | AG32: =(AG$46-AG$26)/($A$46-$A$26) + AG31 -> 0.0804 | AH32: =SUM(AF32:AG32) -> 0.1104 | AI32: =AF32/$B$3 -> 0.053571429 | AJ32: =AG32/$B$3 -> 0.14357143 | AK32: =AH32/$B$3 -> 0.19714286 | AL32: =1/AD32 -> 7 | AM32: =1/AE32 -> 5.0909091
A33: 2037 | B33: =FORECAST($A33, $B$6:$B$15, $A$6:$A$15) + 0.002 -> 0.033892178 | C33: =FORECAST($A33, $C$6:$C$15, $A$6:$A$15) + 0.001 -> 0.065329968 | D33: =SUM(B33:C33) -> 0.099222146 | E33: =B33/$B$3 -> 0.060521746 | F33: =C33/$B$3 -> 0.11666066 | G33: =D33/$B$3 -> 0.1771824 | H33: =FORECAST($A33, $H$6:$H$15, $A$6:$A$15) + 0.002 -> 0.045705875 | I33: =FORECAST($A33, $I$6:$I$15, $A$6:$A$15) + 0.001 -> 0.080270818 | J33: =SUM(H33:I33) -> 0.12597669 | K33: =H33/$B$3 -> 0.081617633 | L33: =I33/$B$3 -> 0.14334075 | M33: =J33/$B$3 -> 0.22495838 | N33: =$B$15 -> 0.026666597 | O33: =FORECAST($A33, $C$10:$C$15, $A$10:$A$15) + 0.001 -> 0.071344612 | P33: =SUM(N33:O33) -> 0.098011209 | Q33: =N33/$B$3 -> 0.047618923 | R33: =O33/$B$3 -> 0.12740109 | S33: =P33/$B$3 -> 0.17502002 | T33: =T32 -> 0.035 | U33: =U32 -> 0.1 | V33: =SUM(T33:U33) -> 0.135 | W33: =T33/$B$3 -> 0.0625 | X33: =U33/$B$3 -> 0.17857143 | Y33: =V33/$B$3 -> 0.24107143 | Z33: =Z32 -> 0.03 | AA33: =AA32 -> 0.08 | AB33: =SUM(Z33:AA33) -> 0.11 | AC33: =Z33/$B$3 -> 0.053571429 | AD33: =AA33/$B$3 -> 0.14285714 | AE33: =AB33/$B$3 -> 0.19642857 | AF33: =AF32 -> 0.03 | AG33: =(AG$46-AG$26)/($A$46-$A$26) + AG32 -> 0.0818 | AH33: =SUM(AF33:AG33) -> 0.1118 | AI33: =AF33/$B$3 -> 0.053571429 | AJ33: =AG33/$B$3 -> 0.14607143 | AK33: =AH33/$B$3 -> 0.19964286 | AL33: =1/AD33 -> 7 | AM33: =1/AE33 -> 5.0909091
A34: 2038 | B34: =FORECAST($A34, $B$6:$B$15, $A$6:$A$15) + 0.002 -> 0.034246757 | C34: =FORECAST($A34, $C$6:$C$15, $A$6:$A$15) + 0.001 -> 0.066937502 | D34: =SUM(B34:C34) -> 0.10118426 | E34: =B34/$B$3 -> 0.061154923 | F34: =C34/$B$3 -> 0.11953125 | G34: =D34/$B$3 -> 0.18068618 | H34: =FORECAST($A34, $H$6:$H$15, $A$6:$A$15) + 0.002 -> 0.046507837 | I34: =FORECAST($A34, $I$6:$I$15, $A$6:$A$15) + 0.001 -> 0.082442156 | J34: =SUM(H34:I34) -> 0.12894999 | K34: =H34/$B$3 -> 0.083049709 | L34: =I34/$B$3 -> 0.14721814 | M34: =J34/$B$3 -> 0.23026785 | N34: =$B$15 -> 0.026666597 | O34: =FORECAST($A34, $C$10:$C$15, $A$10:$A$15) + 0.001 -> 0.07324922 | P34: =SUM(N34:O34) -> 0.099915817 | Q34: =N34/$B$3 -> 0.047618923 | R34: =O34/$B$3 -> 0.13080218 | S34: =P34/$B$3 -> 0.1784211 | T34: =T33 -> 0.035 | U34: =U33 -> 0.1 | V34: =SUM(T34:U34) -> 0.135 | W34: =T34/$B$3 -> 0.0625 | X34: =U34/$B$3 -> 0.17857143 | Y34: =V34/$B$3 -> 0.24107143 | Z34: =Z33 -> 0.03 | AA34: =AA33 -> 0.08 | AB34: =SUM(Z34:AA34) -> 0.11 | AC34: =Z34/$B$3 -> 0.053571429 | AD34: =AA34/$B$3 -> 0.14285714 | AE34: =AB34/$B$3 -> 0.19642857 | AF34: =AF33 -> 0.03 | AG34: =(AG$46-AG$26)/($A$46-$A$26) + AG33 -> 0.0832 | AH34: =SUM(AF34:AG34) -> 0.1132 | AI34: =AF34/$B$3 -> 0.053571429 | AJ34: =AG34/$B$3 -> 0.14857143 | AK34: =AH34/$B$3 -> 0.20214286 | AL34: =1/AD34 -> 7 | AM34: =1/AE34 -> 5.0909091
A35: 2039 | B35: =FORECAST($A35, $B$6:$B$15, $A$6:$A$15) + 0.002 -> 0.034601336 | C35: =FORECAST($A35, $C$6:$C$15, $A$6:$A$15) + 0.001 -> 0.068545037 | D35: =SUM(B35:C35) -> 0.10314637 | E35: =B35/$B$3 -> 0.0617881 | F35: =C35/$B$3 -> 0.12240185 | G35: =D35/$B$3 -> 0.18418995 | H35: =FORECAST($A35, $H$6:$H$15, $A$6:$A$15) + 0.002 -> 0.047309799 | I35: =FORECAST($A35, $I$6:$I$15, $A$6:$A$15) + 0.001 -> 0.084613495 | J35: =SUM(H35:I35) -> 0.13192329 | K35: =H35/$B$3 -> 0.084481785 | L35: =I35/$B$3 -> 0.15109553 | M35: =J35/$B$3 -> 0.23557731 | N35: =$B$15 -> 0.026666597 | O35: =FORECAST($A35, $C$10:$C$15, $A$10:$A$15) + 0.001 -> 0.075153828 | P35: =SUM(N35:O35) -> 0.10182042 | Q35: =N35/$B$3 -> 0.047618923 | R35: =O35/$B$3 -> 0.13420326 | S35: =P35/$B$3 -> 0.18182219 | T35: =T34 -> 0.035 | U35: =U34 -> 0.1 | V35: =SUM(T35:U35) -> 0.135 | W35: =T35/$B$3 -> 0.0625 | X35: =U35/$B$3 -> 0.17857143 | Y35: =V35/$B$3 -> 0.24107143 | Z35: =Z34 -> 0.03 | AA35: =AA34 -> 0.08 | AB35: =SUM(Z35:AA35) -> 0.11 | AC35: =Z35/$B$3 -> 0.053571429 | AD35: =AA35/$B$3 -> 0.14285714 | AE35: =AB35/$B$3 -> 0.19642857 | AF35: =AF34 -> 0.03 | AG35: =(AG$46-AG$26)/($A$46-$A$26) + AG34 -> 0.0846 | AH35: =SUM(AF35:AG35) -> 0.1146 | AI35: =AF35/$B$3 -> 0.053571429 | AJ35: =AG35/$B$3 -> 0.15107143 | AK35: =AH35/$B$3 -> 0.20464286 | AL35: =1/AD35 -> 7 | AM35: =1/AE35 -> 5.0909091
A36: 2040 | B36: =FORECAST($A36, $B$6:$B$15, $A$6:$A$15) + 0.002 -> 0.034955915 | C36: =FORECAST($A36, $C$6:$C$15, $A$6:$A$15) + 0.001 -> 0.070152571 | D36: =SUM(B36:C36) -> 0.10510849 | E36: =B36/$B$3 -> 0.062421277 | F36: =C36/$B$3 -> 0.12527245 | G36: =D36/$B$3 -> 0.18769373 | H36: =FORECAST($A36, $H$6:$H$15, $A$6:$A$15) + 0.002 -> 0.048111762 | I36: =FORECAST($A36, $I$6:$I$15, $A$6:$A$15) + 0.001 -> 0.086784834 | J36: =SUM(H36:I36) -> 0.1348966 | K36: =H36/$B$3 -> 0.08591386 | L36: =I36/$B$3 -> 0.15497292 | M36: =J36/$B$3 -> 0.24088678 | N36: =$B$15 -> 0.026666597 | O36: =FORECAST($A36, $C$10:$C$15, $A$10:$A$15) + 0.001 -> 0.077058436 | P36: =SUM(N36:O36) -> 0.10372503 | Q36: =N36/$B$3 -> 0.047618923 | R36: =O36/$B$3 -> 0.13760435 | S36: =P36/$B$3 -> 0.18522327 | T36: =T35 -> 0.035 | U36: =U35 -> 0.1 | V36: =SUM(T36:U36) -> 0.135 | W36: =T36/$B$3 -> 0.0625 | X36: =U36/$B$3 -> 0.17857143 | Y36: =V36/$B$3 -> 0.24107143 | Z36: =Z35 -> 0.03 | AA36: =AA35 -> 0.08 | AB36: =SUM(Z36:AA36) -> 0.11 | AC36: =Z36/$B$3 -> 0.053571429 | AD36: =AA36/$B$3 -> 0.14285714 | AE36: =AB36/$B$3 -> 0.19642857 | AF36: =AF35 -> 0.03 | AG36: =(AG$46-AG$26)/($A$46-$A$26) + AG35 -> 0.086 | AH36: =SUM(AF36:AG36) -> 0.116 | AI36: =AF36/$B$3 -> 0.053571429 | AJ36: =AG36/$B$3 -> 0.15357143 | AK36: =AH36/$B$3 -> 0.20714286 | AL36: =1/AD36 -> 7 | AM36: =1/AE36 -> 5.0909091
A37: 2041 | B37: =FORECAST($A37, $B$6:$B$15, $A$6:$A$15) + 0.002 -> 0.035310494 | C37: =FORECAST($A37, $C$6:$C$15, $A$6:$A$15) + 0.001 -> 0.071760106 | D37: =SUM(B37:C37) -> 0.1070706 | E37: =B37/$B$3 -> 0.063054454 | F37: =C37/$B$3 -> 0.12814305 | G37: =D37/$B$3 -> 0.1911975 | H37: =FORECAST($A37, $H$6:$H$15, $A$6:$A$15) + 0.002 -> 0.048913724 | I37: =FORECAST($A37, $I$6:$I$15, $A$6:$A$15) + 0.001 -> 0.088956172 | J37: =SUM(H37:I37) -> 0.1378699 | K37: =H37/$B$3 -> 0.087345936 | L37: =I37/$B$3 -> 0.15885031 | M37: =J37/$B$3 -> 0.24619624 | N37: =$B$15 -> 0.026666597 | O37: =FORECAST($A37, $C$10:$C$15, $A$10:$A$15) + 0.001 -> 0.078963044 | P37: =SUM(N37:O37) -> 0.10562964 | Q37: =N37/$B$3 -> 0.047618923 | R37: =O37/$B$3 -> 0.14100543 | S37: =P37/$B$3 -> 0.18862436 | T37: =T36 -> 0.035 | U37: =U36 -> 0.1 | V37: =SUM(T37:U37) -> 0.135 | W37: =T37/$B$3 -> 0.0625 | X37: =U37/$B$3 -> 0.17857143 | Y37: =V37/$B$3 -> 0.24107143 | Z37: =Z36 -> 0.03 | AA37: =AA36 -> 0.08 | AB37: =SUM(Z37:AA37) -> 0.11 | AC37: =Z37/$B$3 -> 0.053571429 | AD37: =AA37/$B$3 -> 0.14285714 | AE37: =AB37/$B$3 -> 0.19642857 | AF37: =AF36 -> 0.03 | AG37: =(AG$46-AG$26)/($A$46-$A$26) + AG36 -> 0.0874 | AH37: =SUM(AF37:AG37) -> 0.1174 | AI37: =AF37/$B$3 -> 0.053571429 | AJ37: =AG37/$B$3 -> 0.15607143 | AK37: =AH37/$B$3 -> 0.20964286 | AL37: =1/AD37 -> 7 | AM37: =1/AE37 -> 5.0909091
A38: 2042 | B38: =FORECAST($A38, $B$6:$B$15, $A$6:$A$15) + 0.002 -> 0.035665074 | C38: =FORECAST($A38, $C$6:$C$15, $A$6:$A$15) + 0.001 -> 0.07336764 | D38: =SUM(B38:C38) -> 0.10903271 | E38: =B38/$B$3 -> 0.063687631 | F38: =C38/$B$3 -> 0.13101364 | G38: =D38/$B$3 -> 0.19470127 | H38: =FORECAST($A38, $H$6:$H$15, $A$6:$A$15) + 0.002 -> 0.049715686 | I38: =FORECAST($A38, $I$6:$I$15, $A$6:$A$15) + 0.001 -> 0.091127511 | J38: =SUM(H38:I38) -> 0.1408432 | K38: =H38/$B$3 -> 0.088778011 | L38: =I38/$B$3 -> 0.1627277 | M38: =J38/$B$3 -> 0.25150571 | N38: =$B$15 -> 0.026666597 | O38: =FORECAST($A38, $C$10:$C$15, $A$10:$A$15) + 0.001 -> 0.080867651 | P38: =SUM(N38:O38) -> 0.10753425 | Q38: =N38/$B$3 -> 0.047618923 | R38: =O38/$B$3 -> 0.14440652 | S38: =P38/$B$3 -> 0.19202544 | T38: =T37 -> 0.035 | U38: =U37 -> 0.1 | V38: =SUM(T38:U38) -> 0.135 | W38: =T38/$B$3 -> 0.0625 | X38: =U38/$B$3 -> 0.17857143 | Y38: =V38/$B$3 -> 0.24107143 | Z38: =Z37 -> 0.03 | AA38: =AA37 -> 0.08 | AB38: =SUM(Z38:AA38) -> 0.11 | AC38: =Z38/$B$3 -> 0.053571429 | AD38: =AA38/$B$3 -> 0.14285714 | AE38: =AB38/$B$3 -> 0.19642857 | AF38: =AF37 -> 0.03 | AG38: =(AG$46-AG$26)/($A$46-$A$26) + AG37 -> 0.0888 | AH38: =SUM(AF38:AG38) -> 0.1188 | AI38: =AF38/$B$3 -> 0.053571429 | AJ38: =AG38/$B$3 -> 0.15857143 | AK38: =AH38/$B$3 -> 0.21214286 | AL38: =1/AD38 -> 7 | AM38: =1/AE38 -> 5.0909091
A39: 2043 | B39: =FORECAST($A39, $B$6:$B$15, $A$6:$A$15) + 0.002 -> 0.036019653 | C39: =FORECAST($A39, $C$6:$C$15, $A$6:$A$15) + 0.001 -> 0.074975174 | D39: =SUM(B39:C39) -> 0.11099483 | E39: =B39/$B$3 -> 0.064320808 | F39: =C39/$B$3 -> 0.13388424 | G39: =D39/$B$3 -> 0.19820505 | H39: =FORECAST($A39, $H$6:$H$15, $A$6:$A$15) + 0.002 -> 0.050517649 | I39: =FORECAST($A39, $I$6:$I$15, $A$6:$A$15) + 0.001 -> 0.093298849 | J39: =SUM(H39:I39) -> 0.1438165 | K39: =H39/$B$3 -> 0.090210087 | L39: =I39/$B$3 -> 0.16660509 | M39: =J39/$B$3 -> 0.25681518 | N39: =$B$15 -> 0.026666597 | O39: =FORECAST($A39, $C$10:$C$15, $A$10:$A$15) + 0.001 -> 0.082772259 | P39: =SUM(N39:O39) -> 0.10943886 | Q39: =N39/$B$3 -> 0.047618923 | R39: =O39/$B$3 -> 0.14780761 | S39: =P39/$B$3 -> 0.19542653 | T39: =(T$56-T$38)/($A$56-$A$38) + T38 -> 0.035277778 | U39: =(U$56-U$31)/($A$56-$A$31) + U31 -> 0.1012 | V39: =SUM(T39:U39) -> 0.13647778 | W39: =T39/$B$3 -> 0.062996032 | X39: =U39/$B$3 -> 0.18071429 | Y39: =V39/$B$3 -> 0.24371032 | Z39: =(Z$56-Z$38)/($A$56-$A$38) + Z38 -> 0.030277778 | AA39: =(AA$56-AA$31)/($A$56-$A$31) + AA31 -> 0.0812 | AB39: =SUM(Z39:AA39) -> 0.11147778 | AC39: =Z39/$B$3 -> 0.05406746 | AD39: =AA39/$B$3 -> 0.145 | AE39: =AB39/$B$3 -> 0.19906746 | AF39: =(AF$56-AF$38)/($A$56-$A$38) + AF38 -> 0.030277778 | AG39: =(AG$46-AG$26)/($A$46-$A$26) + AG38 -> 0.0902 | AH39: =SUM(AF39:AG39) -> 0.12047778 | AI39: =AF39/$B$3 -> 0.05406746 | AJ39: =AG39/$B$3 -> 0.16107143 | AK39: =AH39/$B$3 -> 0.21513889 | AL39: =1/AD39 -> 6.8965517 | AM39: =1/AE39 -> 5.0234227
A40: 2044 | B40: =FORECAST($A40, $B$6:$B$15, $A$6:$A$15) + 0.002 -> 0.036374232 | C40: =FORECAST($A40, $C$6:$C$15, $A$6:$A$15) + 0.001 -> 0.076582709 | D40: =SUM(B40:C40) -> 0.11295694 | E40: =B40/$B$3 -> 0.064953985 | F40: =C40/$B$3 -> 0.13675484 | G40: =D40/$B$3 -> 0.20170882 | H40: =FORECAST($A40, $H$6:$H$15, $A$6:$A$15) + 0.002 -> 0.051319611 | I40: =FORECAST($A40, $I$6:$I$15, $A$6:$A$15) + 0.001 -> 0.095470188 | J40: =SUM(H40:I40) -> 0.1467898 | K40: =H40/$B$3 -> 0.091642163 | L40: =I40/$B$3 -> 0.17048248 | M40: =J40/$B$3 -> 0.26212464 | N40: =$B$15 -> 0.026666597 | O40: =FORECAST($A40, $C$10:$C$15, $A$10:$A$15) + 0.001 -> 0.084676867 | P40: =SUM(N40:O40) -> 0.11134346 | Q40: =N40/$B$3 -> 0.047618923 | R40: =O40/$B$3 -> 0.15120869 | S40: =P40/$B$3 -> 0.19882761 | T40: =(T$56-T$38)/($A$56-$A$38) + T39 -> 0.035555556 | U40: =(U$56-U$38)/($A$56-$A$38) + U39 -> 0.10286667 | V40: =SUM(T40:U40) -> 0.13842222 | W40: =T40/$B$3 -> 0.063492063 | X40: =U40/$B$3 -> 0.18369048 | Y40: =V40/$B$3 -> 0.24718254 | Z40: =(Z$56-Z$38)/($A$56-$A$38) + Z39 -> 0.030555556 | AA40: =(AA$56-AA$38)/($A$56-$A$38) + AA39 -> 0.082866667 | AB40: =SUM(Z40:AA40) -> 0.11342222 | AC40: =Z40/$B$3 -> 0.054563492 | AD40: =AA40/$B$3 -> 0.14797619 | AE40: =AB40/$B$3 -> 0.20253968 | AF40: =(AF$56-AF$38)/($A$56-$A$38) + AF39 -> 0.030555556 | AG40: =(AG$46-AG$26)/($A$46-$A$26) + AG39 -> 0.0916 | AH40: =SUM(AF40:AG40) -> 0.12215556 | AI40: =AF40/$B$3 -> 0.054563492 | AJ40: =AG40/$B$3 -> 0.16357143 | AK40: =AH40/$B$3 -> 0.21813492 | AL40: =1/AD40 -> 6.7578439 | AM40: =1/AE40 -> 4.9373041
A41: 2045 | B41: =FORECAST($A41, $B$6:$B$15, $A$6:$A$15) + 0.002 -> 0.036728811 | C41: =FORECAST($A41, $C$6:$C$15, $A$6:$A$15) + 0.001 -> 0.078190243 | D41: =SUM(B41:C41) -> 0.11491905 | E41: =B41/$B$3 -> 0.065587162 | F41: =C41/$B$3 -> 0.13962543 | G41: =D41/$B$3 -> 0.2052126 | H41: =FORECAST($A41, $H$6:$H$15, $A$6:$A$15) + 0.002 -> 0.052121573 | I41: =FORECAST($A41, $I$6:$I$15, $A$6:$A$15) + 0.001 -> 0.097641527 | J41: =SUM(H41:I41) -> 0.1497631 | K41: =H41/$B$3 -> 0.093074238 | L41: =I41/$B$3 -> 0.17435987 | M41: =J41/$B$3 -> 0.26743411 | N41: =$B$15 -> 0.026666597 | O41: =FORECAST($A41, $C$10:$C$15, $A$10:$A$15) + 0.001 -> 0.086581475 | P41: =SUM(N41:O41) -> 0.11324807 | Q41: =N41/$B$3 -> 0.047618923 | R41: =O41/$B$3 -> 0.15460978 | S41: =P41/$B$3 -> 0.2022287 | T41: =(T$56-T$38)/($A$56-$A$38) + T40 -> 0.035833333 | U41: =(U$56-U$38)/($A$56-$A$38) + U40 -> 0.10453333 | V41: =SUM(T41:U41) -> 0.14036667 | W41: =T41/$B$3 -> 0.063988095 | X41: =U41/$B$3 -> 0.18666667 | Y41: =V41/$B$3 -> 0.25065476 | Z41: =(Z$56-Z$38)/($A$56-$A$38) + Z40 -> 0.030833333 | AA41: =(AA$56-AA$38)/($A$56-$A$38) + AA40 -> 0.084533333 | AB41: =SUM(Z41:AA41) -> 0.11536667 | AC41: =Z41/$B$3 -> 0.055059524 | AD41: =AA41/$B$3 -> 0.15095238 | AE41: =AB41/$B$3 -> 0.2060119 | AF41: =(AF$56-AF$38)/($A$56-$A$38) + AF40 -> 0.030833333 | AG41: =(AG$46-AG$26)/($A$46-$A$26) + AG40 -> 0.093 | AH41: =SUM(AF41:AG41) -> 0.12383333 | AI41: =AF41/$B$3 -> 0.055059524 | AJ41: =AG41/$B$3 -> 0.16607143 | AK41: =AH41/$B$3 -> 0.22113095 | AL41: =1/AD41 -> 6.6246057 | AM41: =1/AE41 -> 4.8540884
A42: 2046 | B42: =FORECAST($A42, $B$6:$B$15, $A$6:$A$15) + 0.002 -> 0.03708339 | C42: =FORECAST($A42, $C$6:$C$15, $A$6:$A$15) + 0.001 -> 0.079797778 | D42: =SUM(B42:C42) -> 0.11688117 | E42: =B42/$B$3 -> 0.066220339 | F42: =C42/$B$3 -> 0.14249603 | G42: =D42/$B$3 -> 0.20871637 | H42: =FORECAST($A42, $H$6:$H$15, $A$6:$A$15) + 0.002 -> 0.052923536 | I42: =FORECAST($A42, $I$6:$I$15, $A$6:$A$15) + 0.001 -> 0.099812865 | J42: =SUM(H42:I42) -> 0.1527364 | K42: =H42/$B$3 -> 0.094506314 | L42: =I42/$B$3 -> 0.17823726 | M42: =J42/$B$3 -> 0.27274357 | N42: =$B$15 -> 0.026666597 | O42: =FORECAST($A42, $C$10:$C$15, $A$10:$A$15) + 0.001 -> 0.088486083 | P42: =SUM(N42:O42) -> 0.11515268 | Q42: =N42/$B$3 -> 0.047618923 | R42: =O42/$B$3 -> 0.15801086 | S42: =P42/$B$3 -> 0.20562979 | T42: =(T$56-T$38)/($A$56-$A$38) + T41 -> 0.036111111 | U42: =(U$56-U$38)/($A$56-$A$38) + U41 -> 0.1062 | V42: =SUM(T42:U42) -> 0.14231111 | W42: =T42/$B$3 -> 0.064484127 | X42: =U42/$B$3 -> 0.18964286 | Y42: =V42/$B$3 -> 0.25412698 | Z42: =(Z$56-Z$38)/($A$56-$A$38) + Z41 -> 0.031111111 | AA42: =(AA$56-AA$38)/($A$56-$A$38) + AA41 -> 0.0862 | AB42: =SUM(Z42:AA42) -> 0.11731111 | AC42: =Z42/$B$3 -> 0.055555556 | AD42: =AA42/$B$3 -> 0.15392857 | AE42: =AB42/$B$3 -> 0.20948413 | AF42: =(AF$56-AF$38)/($A$56-$A$38) + AF41 -> 0.031111111 | AG42: =(AG$46-AG$26)/($A$46-$A$26) + AG41 -> 0.0944 | AH42: =SUM(AF42:AG42) -> 0.12551111 | AI42: =AF42/$B$3 -> 0.055555556 | AJ42: =AG42/$B$3 -> 0.16857143 | AK42: =AH42/$B$3 -> 0.22412698 | AL42: =1/AD42 -> 6.4965197 | AM42: =1/AE42 -> 4.7736314
A43: 2047 | B43: =FORECAST($A43, $B$6:$B$15, $A$6:$A$15) + 0.002 -> 0.037437969 | C43: =FORECAST($A43, $C$6:$C$15, $A$6:$A$15) + 0.001 -> 0.081405312 | D43: =SUM(B43:C43) -> 0.11884328 | E43: =B43/$B$3 -> 0.066853516 | F43: =C43/$B$3 -> 0.14536663 | G43: =D43/$B$3 -> 0.21222015 | H43: =FORECAST($A43, $H$6:$H$15, $A$6:$A$15) + 0.002 -> 0.053725498 | I43: =FORECAST($A43, $I$6:$I$15, $A$6:$A$15) + 0.001 -> 0.1019842 | J43: =SUM(H43:I43) -> 0.1557097 | K43: =H43/$B$3 -> 0.095938389 | L43: =I43/$B$3 -> 0.18211465 | M43: =J43/$B$3 -> 0.27805304 | N43: =$B$15 -> 0.026666597 | O43: =FORECAST($A43, $C$10:$C$15, $A$10:$A$15) + 0.001 -> 0.090390691 | P43: =SUM(N43:O43) -> 0.11705729 | Q43: =N43/$B$3 -> 0.047618923 | R43: =O43/$B$3 -> 0.16141195 | S43: =P43/$B$3 -> 0.20903087 | T43: =(T$56-T$38)/($A$56-$A$38) + T42 -> 0.036388889 | U43: =(U$56-U$38)/($A$56-$A$38) + U42 -> 0.10786667 | V43: =SUM(T43:U43) -> 0.14425556 | W43: =T43/$B$3 -> 0.064980159 | X43: =U43/$B$3 -> 0.19261905 | Y43: =V43/$B$3 -> 0.25759921 | Z43: =(Z$56-Z$38)/($A$56-$A$38) + Z42 -> 0.031388889 | AA43: =(AA$56-AA$38)/($A$56-$A$38) + AA42 -> 0.087866667 | AB43: =SUM(Z43:AA43) -> 0.11925556 | AC43: =Z43/$B$3 -> 0.056051587 | AD43: =AA43/$B$3 -> 0.15690476 | AE43: =AB43/$B$3 -> 0.21295635 | AF43: =(AF$56-AF$38)/($A$56-$A$38) + AF42 -> 0.031388889 | AG43: =(AG$46-AG$26)/($A$46-$A$26) + AG42 -> 0.0958 | AH43: =SUM(AF43:AG43) -> 0.12718889 | AI43: =AF43/$B$3 -> 0.056051587 | AJ43: =AG43/$B$3 -> 0.17107143 | AK43: =AH43/$B$3 -> 0.22712302 | AL43: =1/AD43 -> 6.3732929 | AM43: =1/AE43 -> 4.695798
A44: 2048 | B44: =FORECAST($A44, $B$6:$B$15, $A$6:$A$15) + 0.002 -> 0.037792548 | C44: =FORECAST($A44, $C$6:$C$15, $A$6:$A$15) + 0.001 -> 0.083012847 | D44: =SUM(B44:C44) -> 0.12080539 | E44: =B44/$B$3 -> 0.067486693 | F44: =C44/$B$3 -> 0.14823723 | G44: =D44/$B$3 -> 0.21572392 | H44: =FORECAST($A44, $H$6:$H$15, $A$6:$A$15) + 0.002 -> 0.05452746 | I44: =FORECAST($A44, $I$6:$I$15, $A$6:$A$15) + 0.001 -> 0.10415554 | J44: =SUM(H44:I44) -> 0.158683 | K44: =H44/$B$3 -> 0.097370465 | L44: =I44/$B$3 -> 0.18599204 | M44: =J44/$B$3 -> 0.2833625 | N44: =$B$15 -> 0.026666597 | O44: =FORECAST($A44, $C$10:$C$15, $A$10:$A$15) + 0.001 -> 0.092295299 | P44: =SUM(N44:O44) -> 0.1189619 | Q44: =N44/$B$3 -> 0.047618923 | R44: =O44/$B$3 -> 0.16481303 | S44: =P44/$B$3 -> 0.21243196 | T44: =(T$56-T$38)/($A$56-$A$38) + T43 -> 0.036666667 | U44: =(U$56-U$38)/($A$56-$A$38) + U43 -> 0.10953333 | V44: =SUM(T44:U44) -> 0.1462 | W44: =T44/$B$3 -> 0.06547619 | X44: =U44/$B$3 -> 0.19559524 | Y44: =V44/$B$3 -> 0.26107143 | Z44: =(Z$56-Z$38)/($A$56-$A$38) + Z43 -> 0.031666667 | AA44: =(AA$56-AA$38)/($A$56-$A$38) + AA43 -> 0.089533333 | AB44: =SUM(Z44:AA44) -> 0.1212 | AC44: =Z44/$B$3 -> 0.056547619 | AD44: =AA44/$B$3 -> 0.15988095 | AE44: =AB44/$B$3 -> 0.21642857 | AF44: =(AF$56-AF$38)/($A$56-$A$38) + AF43 -> 0.031666667 | AG44: =(AG$46-AG$26)/($A$46-$A$26) + AG43 -> 0.0972 | AH44: =SUM(AF44:AG44) -> 0.12886667 | AI44: =AF44/$B$3 -> 0.056547619 | AJ44: =AG44/$B$3 -> 0.17357143 | AK44: =AH44/$B$3 -> 0.23011905 | AL44: =1/AD44 -> 6.2546538 | AM44: =1/AE44 -> 4.620462
A45: 2049 | B45: =FORECAST($A45, $B$6:$B$15, $A$6:$A$15) + 0.002 -> 0.038147127 | C45: =FORECAST($A45, $C$6:$C$15, $A$6:$A$15) + 0.001 -> 0.084620381 | D45: =SUM(B45:C45) -> 0.12276751 | E45: =B45/$B$3 -> 0.06811987 | F45: =C45/$B$3 -> 0.15110782 | G45: =D45/$B$3 -> 0.21922769 | H45: =FORECAST($A45, $H$6:$H$15, $A$6:$A$15) + 0.002 -> 0.055329423 | I45: =FORECAST($A45, $I$6:$I$15, $A$6:$A$15) + 0.001 -> 0.10632688 | J45: =SUM(H45:I45) -> 0.1616563 | K45: =H45/$B$3 -> 0.098802541 | L45: =I45/$B$3 -> 0.18986943 | M45: =J45/$B$3 -> 0.28867197 | N45: =$B$15 -> 0.026666597 | O45: =FORECAST($A45, $C$10:$C$15, $A$10:$A$15) + 0.001 -> 0.094199907 | P45: =SUM(N45:O45) -> 0.1208665 | Q45: =N45/$B$3 -> 0.047618923 | R45: =O45/$B$3 -> 0.16821412 | S45: =P45/$B$3 -> 0.21583304 | T45: =(T$56-T$38)/($A$56-$A$38) + T44 -> 0.036944444 | U45: =(U$56-U$38)/($A$56-$A$38) + U44 -> 0.1112 | V45: =SUM(T45:U45) -> 0.14814444 | W45: =T45/$B$3 -> 0.065972222 | X45: =U45/$B$3 -> 0.19857143 | Y45: =V45/$B$3 -> 0.26454365 | Z45: =(Z$56-Z$38)/($A$56-$A$38) + Z44 -> 0.031944444 | AA45: =(AA$56-AA$38)/($A$56-$A$38) + AA44 -> 0.0912 | AB45: =SUM(Z45:AA45) -> 0.12314444 | AC45: =Z45/$B$3 -> 0.057043651 | AD45: =AA45/$B$3 -> 0.16285714 | AE45: =AB45/$B$3 -> 0.21990079 | AF45: =(AF$56-AF$38)/($A$56-$A$38) + AF44 -> 0.031944444 | AG45: =(AG$46-AG$26)/($A$46-$A$26) + AG44 -> 0.0986 | AH45: =SUM(AF45:AG45) -> 0.13054444 | AI45: =AF45/$B$3 -> 0.057043651 | AJ45: =AG45/$B$3 -> 0.17607143 | AK45: =AH45/$B$3 -> 0.23311508 | AL45: =1/AD45 -> 6.1403509 | AM45: =1/AE45 -> 4.5475052
A46: 2050 | B46: =FORECAST($A46, $B$6:$B$15, $A$6:$A$15) + 0.002 -> 0.038501706 | C46: =FORECAST($A46, $C$6:$C$15, $A$6:$A$15) + 0.001 -> 0.086227915 | D46: =SUM(B46:C46) -> 0.12472962 | E46: =B46/$B$3 -> 0.068753047 | F46: =C46/$B$3 -> 0.15397842 | G46: =D46/$B$3 -> 0.22273147 | H46: =FORECAST($A46, $H$6:$H$15, $A$6:$A$15) + 0.002 -> 0.056131385 | I46: =FORECAST($A46, $I$6:$I$15, $A$6:$A$15) + 0.001 -> 0.10849822 | J46: =SUM(H46:I46) -> 0.1646296 | K46: =H46/$B$3 -> 0.10023462 | L46: =I46/$B$3 -> 0.19374682 | M46: =J46/$B$3 -> 0.29398144 | N46: =$B$15 -> 0.026666597 | O46: =FORECAST($A46, $C$10:$C$15, $A$10:$A$15) + 0.001 -> 0.096104515 | P46: =SUM(N46:O46) -> 0.12277111 | Q46: =N46/$B$3 -> 0.047618923 | R46: =O46/$B$3 -> 0.1716152 | S46: =P46/$B$3 -> 0.21923413 | T46: =(T$56-T$38)/($A$56-$A$38) + T45 -> 0.037222222 | U46: =(U$56-U$38)/($A$56-$A$38) + U45 -> 0.11286667 | V46: =SUM(T46:U46) -> 0.15008889 | W46: =T46/$B$3 -> 0.066468254 | X46: =U46/$B$3 -> 0.20154762 | Y46: =V46/$B$3 -> 0.26801587 | Z46: =(Z$56-Z$38)/($A$56-$A$38) + Z45 -> 0.032222222 | AA46: =(AA$56-AA$38)/($A$56-$A$38) + AA45 -> 0.092866667 | AB46: =SUM(Z46:AA46) -> 0.12508889 | AC46: =Z46/$B$3 -> 0.057539683 | AD46: =AA46/$B$3 -> 0.16583333 | AE46: =AB46/$B$3 -> 0.22337302 | AF46: =(AF$56-AF$38)/($A$56-$A$38) + AF45 -> 0.032222222 | AG46: 0.1 | AH46: =SUM(AF46:AG46) -> 0.13222222 | AI46: =AF46/$B$3 -> 0.057539683 | AJ46: =AG46/$B$3 -> 0.17857143 | AK46: =AH46/$B$3 -> 0.23611111 | AL46: =1/AD46 -> 6.0301508 | AM46: =1/AE46 -> 4.4768165
A47: 2051 | B47: =FORECAST($A47, $B$6:$B$15, $A$6:$A$15) + 0.002 -> 0.038856286 | C47: =FORECAST($A47, $C$6:$C$15, $A$6:$A$15) + 0.001 -> 0.08783545 | D47: =SUM(B47:C47) -> 0.12669174 | E47: =B47/$B$3 -> 0.069386224 | F47: =C47/$B$3 -> 0.15684902 | G47: =D47/$B$3 -> 0.22623524 | H47: =FORECAST($A47, $H$6:$H$15, $A$6:$A$15) + 0.002 -> 0.056933347 | I47: =FORECAST($A47, $I$6:$I$15, $A$6:$A$15) + 0.001 -> 0.11066956 | J47: =SUM(H47:I47) -> 0.16760291 | K47: =H47/$B$3 -> 0.10166669 | L47: =I47/$B$3 -> 0.19762421 | M47: =J47/$B$3 -> 0.2992909 | N47: =$B$15 -> 0.026666597 | O47: =FORECAST($A47, $C$10:$C$15, $A$10:$A$15) + 0.001 -> 0.098009122 | P47: =SUM(N47:O47) -> 0.12467572 | Q47: =N47/$B$3 -> 0.047618923 | R47: =O47/$B$3 -> 0.17501629 | S47: =P47/$B$3 -> 0.22263521 | T47: =(T$56-T$38)/($A$56-$A$38) + T46 -> 0.0375 | U47: =(U$56-U$38)/($A$56-$A$38) + U46 -> 0.11453333 | V47: =SUM(T47:U47) -> 0.15203333 | W47: =T47/$B$3 -> 0.066964286 | X47: =U47/$B$3 -> 0.20452381 | Y47: =V47/$B$3 -> 0.2714881 | Z47: =(Z$56-Z$38)/($A$56-$A$38) + Z46 -> 0.0325 | AA47: =(AA$56-AA$38)/($A$56-$A$38) + AA46 -> 0.094533333 | AB47: =SUM(Z47:AA47) -> 0.12703333 | AC47: =Z47/$B$3 -> 0.058035714 | AD47: =AA47/$B$3 -> 0.16880952 | AE47: =AB47/$B$3 -> 0.22684524 | AF47: =(AF$56-AF$38)/($A$56-$A$38) + AF46 -> 0.0325 | AG47: =(AG$56-AG$46)/($A$56-$A$46) + AG46 -> 0.10175 | AH47: =SUM(AF47:AG47) -> 0.13425 | AI47: =AF47/$B$3 -> 0.058035714 | AJ47: =AG47/$B$3 -> 0.18169643 | AK47: =AH47/$B$3 -> 0.23973214 | AL47: =1/AD47 -> 5.9238364 | AM47: =1/AE47 -> 4.4082918
A48: 2052 | B48: =FORECAST($A48, $B$6:$B$15, $A$6:$A$15) + 0.002 -> 0.039210865 | C48: =FORECAST($A48, $C$6:$C$15, $A$6:$A$15) + 0.001 -> 0.089442984 | D48: =SUM(B48:C48) -> 0.12865385 | E48: =B48/$B$3 -> 0.070019401 | F48: =C48/$B$3 -> 0.15971961 | G48: =D48/$B$3 -> 0.22973902 | H48: =FORECAST($A48, $H$6:$H$15, $A$6:$A$15) + 0.002 -> 0.05773531 | I48: =FORECAST($A48, $I$6:$I$15, $A$6:$A$15) + 0.001 -> 0.1128409 | J48: =SUM(H48:I48) -> 0.17057621 | K48: =H48/$B$3 -> 0.10309877 | L48: =I48/$B$3 -> 0.2015016 | M48: =J48/$B$3 -> 0.30460037 | N48: =$B$15 -> 0.026666597 | O48: =FORECAST($A48, $C$10:$C$15, $A$10:$A$15) + 0.001 -> 0.09991373 | P48: =SUM(N48:O48) -> 0.12658033 | Q48: =N48/$B$3 -> 0.047618923 | R48: =O48/$B$3 -> 0.17841738 | S48: =P48/$B$3 -> 0.2260363 | T48: =(T$56-T$38)/($A$56-$A$38) + T47 -> 0.037777778 | U48: =(U$56-U$38)/($A$56-$A$38) + U47 -> 0.1162 | V48: =SUM(T48:U48) -> 0.15397778 | W48: =T48/$B$3 -> 0.067460317 | X48: =U48/$B$3 -> 0.2075 | Y48: =V48/$B$3 -> 0.27496032 | Z48: =(Z$56-Z$38)/($A$56-$A$38) + Z47 -> 0.032777778 | AA48: =(AA$56-AA$38)/($A$56-$A$38) + AA47 -> 0.0962 | AB48: =SUM(Z48:AA48) -> 0.12897778 | AC48: =Z48/$B$3 -> 0.058531746 | AD48: =AA48/$B$3 -> 0.17178571 | AE48: =AB48/$B$3 -> 0.23031746 | AF48: =(AF$56-AF$38)/($A$56-$A$38) + AF47 -> 0.032777778 | AG48: =(AG$56-AG$46)/($A$56-$A$46) + AG47 -> 0.1035 | AH48: =SUM(AF48:AG48) -> 0.13627778 | AI48: =AF48/$B$3 -> 0.058531746 | AJ48: =AG48/$B$3 -> 0.18482143 | AK48: =AH48/$B$3 -> 0.24335317 | AL48: =1/AD48 -> 5.8212058 | AM48: =1/AE48 -> 4.3418332
A49: 2053 | B49: =FORECAST($A49, $B$6:$B$15, $A$6:$A$15) + 0.002 -> 0.039565444 | C49: =FORECAST($A49, $C$6:$C$15, $A$6:$A$15) + 0.001 -> 0.091050519 | D49: =SUM(B49:C49) -> 0.13061596 | E49: =B49/$B$3 -> 0.070652578 | F49: =C49/$B$3 -> 0.16259021 | G49: =D49/$B$3 -> 0.23324279 | H49: =FORECAST($A49, $H$6:$H$15, $A$6:$A$15) + 0.002 -> 0.058537272 | I49: =FORECAST($A49, $I$6:$I$15, $A$6:$A$15) + 0.001 -> 0.11501224 | J49: =SUM(H49:I49) -> 0.17354951 | K49: =H49/$B$3 -> 0.10453084 | L49: =I49/$B$3 -> 0.20537899 | M49: =J49/$B$3 -> 0.30990983 | N49: =$B$15 -> 0.026666597 | O49: =FORECAST($A49, $C$10:$C$15, $A$10:$A$15) + 0.001 -> 0.10181834 | P49: =SUM(N49:O49) -> 0.12848494 | Q49: =N49/$B$3 -> 0.047618923 | R49: =O49/$B$3 -> 0.18181846 | S49: =P49/$B$3 -> 0.22943738 | T49: =(T$56-T$38)/($A$56-$A$38) + T48 -> 0.038055556 | U49: =(U$56-U$38)/($A$56-$A$38) + U48 -> 0.11786667 | V49: =SUM(T49:U49) -> 0.15592222 | W49: =T49/$B$3 -> 0.067956349 | X49: =U49/$B$3 -> 0.21047619 | Y49: =V49/$B$3 -> 0.27843254 | Z49: =(Z$56-Z$38)/($A$56-$A$38) + Z48 -> 0.033055556 | AA49: =(AA$56-AA$38)/($A$56-$A$38) + AA48 -> 0.097866667 | AB49: =SUM(Z49:AA49) -> 0.13092222 | AC49: =Z49/$B$3 -> 0.059027778 | AD49: =AA49/$B$3 -> 0.1747619 | AE49: =AB49/$B$3 -> 0.23378968 | AF49: =(AF$56-AF$38)/($A$56-$A$38) + AF48 -> 0.033055556 | AG49: =(AG$56-AG$46)/($A$56-$A$46) + AG48 -> 0.10525 | AH49: =SUM(AF49:AG49) -> 0.13830556 | AI49: =AF49/$B$3 -> 0.059027778 | AJ49: =AG49/$B$3 -> 0.18794643 | AK49: =AH49/$B$3 -> 0.24697421 | AL49: =1/AD49 -> 5.7220708 | AM49: =1/AE49 -> 4.2773487
A50: 2054 | B50: =FORECAST($A50, $B$6:$B$15, $A$6:$A$15) + 0.002 -> 0.039920023 | C50: =FORECAST($A50, $C$6:$C$15, $A$6:$A$15) + 0.001 -> 0.092658053 | D50: =SUM(B50:C50) -> 0.13257808 | E50: =B50/$B$3 -> 0.071285755 | F50: =C50/$B$3 -> 0.16546081 | G50: =D50/$B$3 -> 0.23674656 | H50: =FORECAST($A50, $H$6:$H$15, $A$6:$A$15) + 0.002 -> 0.059339234 | I50: =FORECAST($A50, $I$6:$I$15, $A$6:$A$15) + 0.001 -> 0.11718357 | J50: =SUM(H50:I50) -> 0.17652281 | K50: =H50/$B$3 -> 0.10596292 | L50: =I50/$B$3 -> 0.20925638 | M50: =J50/$B$3 -> 0.3152193 | N50: =$B$15 -> 0.026666597 | O50: =FORECAST($A50, $C$10:$C$15, $A$10:$A$15) + 0.001 -> 0.10372295 | P50: =SUM(N50:O50) -> 0.13038954 | Q50: =N50/$B$3 -> 0.047618923 | R50: =O50/$B$3 -> 0.18521955 | S50: =P50/$B$3 -> 0.23283847 | T50: =(T$56-T$38)/($A$56-$A$38) + T49 -> 0.038333333 | U50: =(U$56-U$38)/($A$56-$A$38) + U49 -> 0.11953333 | V50: =SUM(T50:U50) -> 0.15786667 | W50: =T50/$B$3 -> 0.068452381 | X50: =U50/$B$3 -> 0.21345238 | Y50: =V50/$B$3 -> 0.28190476 | Z50: =(Z$56-Z$38)/($A$56-$A$38) + Z49 -> 0.033333333 | AA50: =(AA$56-AA$38)/($A$56-$A$38) + AA49 -> 0.099533333 | AB50: =SUM(Z50:AA50) -> 0.13286667 | AC50: =Z50/$B$3 -> 0.05952381 | AD50: =AA50/$B$3 -> 0.1777381 | AE50: =AB50/$B$3 -> 0.2372619 | AF50: =(AF$56-AF$38)/($A$56-$A$38) + AF49 -> 0.033333333 | AG50: =(AG$56-AG$46)/($A$56-$A$46) + AG49 -> 0.107 | AH50: =SUM(AF50:AG50) -> 0.14033333 | AI50: =AF50/$B$3 -> 0.05952381 | AJ50: =AG50/$B$3 -> 0.19107143 | AK50: =AH50/$B$3 -> 0.25059524 | AL50: =1/AD50 -> 5.6262559 | AM50: =1/AE50 -> 4.2147516
A51: 2055 | B51: =FORECAST($A51, $B$6:$B$15, $A$6:$A$15) + 0.002 -> 0.040274602 | C51: =FORECAST($A51, $C$6:$C$15, $A$6:$A$15) + 0.001 -> 0.094265588 | D51: =SUM(B51:C51) -> 0.13454019 | E51: =B51/$B$3 -> 0.071918932 | F51: =C51/$B$3 -> 0.16833141 | G51: =D51/$B$3 -> 0.24025034 | H51: =FORECAST($A51, $H$6:$H$15, $A$6:$A$15) + 0.002 -> 0.060141197 | I51: =FORECAST($A51, $I$6:$I$15, $A$6:$A$15) + 0.001 -> 0.11935491 | J51: =SUM(H51:I51) -> 0.17949611 | K51: =H51/$B$3 -> 0.10739499 | L51: =I51/$B$3 -> 0.21313377 | M51: =J51/$B$3 -> 0.32052877 | N51: =$B$15 -> 0.026666597 | O51: =FORECAST($A51, $C$10:$C$15, $A$10:$A$15) + 0.001 -> 0.10562755 | P51: =SUM(N51:O51) -> 0.13229415 | Q51: =N51/$B$3 -> 0.047618923 | R51: =O51/$B$3 -> 0.18862063 | S51: =P51/$B$3 -> 0.23623955 | T51: =(T$56-T$38)/($A$56-$A$38) + T50 -> 0.038611111 | U51: =(U$56-U$38)/($A$56-$A$38) + U50 -> 0.1212 | V51: =SUM(T51:U51) -> 0.15981111 | W51: =T51/$B$3 -> 0.068948413 | X51: =U51/$B$3 -> 0.21642857 | Y51: =V51/$B$3 -> 0.28537698 | Z51: =(Z$56-Z$38)/($A$56-$A$38) + Z50 -> 0.033611111 | AA51: =(AA$56-AA$38)/($A$56-$A$38) + AA50 -> 0.1012 | AB51: =SUM(Z51:AA51) -> 0.13481111 | AC51: =Z51/$B$3 -> 0.060019841 | AD51: =AA51/$B$3 -> 0.18071429 | AE51: =AB51/$B$3 -> 0.24073413 | AF51: =(AF$56-AF$38)/($A$56-$A$38) + AF50 -> 0.033611111 | AG51: =(AG$56-AG$46)/($A$56-$A$46) + AG50 -> 0.10875 | AH51: =SUM(AF51:AG51) -> 0.14236111 | AI51: =AF51/$B$3 -> 0.060019841 | AJ51: =AG51/$B$3 -> 0.19419643 | AK51: =AH51/$B$3 -> 0.25421627 | AL51: =1/AD51 -> 5.5335968 | AM51: =1/AE51 -> 4.1539603
A52: 2056 | B52: =FORECAST($A52, $B$6:$B$15, $A$6:$A$15) + 0.002 -> 0.040629181 | C52: =FORECAST($A52, $C$6:$C$15, $A$6:$A$15) + 0.001 -> 0.095873122 | D52: =SUM(B52:C52) -> 0.1365023 | E52: =B52/$B$3 -> 0.072552109 | F52: =C52/$B$3 -> 0.171202 | G52: =D52/$B$3 -> 0.24375411 | H52: =FORECAST($A52, $H$6:$H$15, $A$6:$A$15) + 0.002 -> 0.060943159 | I52: =FORECAST($A52, $I$6:$I$15, $A$6:$A$15) + 0.001 -> 0.12152625 | J52: =SUM(H52:I52) -> 0.18246941 | K52: =H52/$B$3 -> 0.10882707 | L52: =I52/$B$3 -> 0.21701116 | M52: =J52/$B$3 -> 0.32583823 | N52: =$B$15 -> 0.026666597 | O52: =FORECAST($A52, $C$10:$C$15, $A$10:$A$15) + 0.001 -> 0.10753216 | P52: =SUM(N52:O52) -> 0.13419876 | Q52: =N52/$B$3 -> 0.047618923 | R52: =O52/$B$3 -> 0.19202172 | S52: =P52/$B$3 -> 0.23964064 | T52: =(T$56-T$38)/($A$56-$A$38) + T51 -> 0.038888889 | U52: =(U$56-U$38)/($A$56-$A$38) + U51 -> 0.12286667 | V52: =SUM(T52:U52) -> 0.16175556 | W52: =T52/$B$3 -> 0.069444444 | X52: =U52/$B$3 -> 0.21940476 | Y52: =V52/$B$3 -> 0.28884921 | Z52: =(Z$56-Z$38)/($A$56-$A$38) + Z51 -> 0.033888889 | AA52: =(AA$56-AA$38)/($A$56-$A$38) + AA51 -> 0.10286667 | AB52: =SUM(Z52:AA52) -> 0.13675556 | AC52: =Z52/$B$3 -> 0.060515873 | AD52: =AA52/$B$3 -> 0.18369048 | AE52: =AB52/$B$3 -> 0.24420635 | AF52: =(AF$56-AF$38)/($A$56-$A$38) + AF51 -> 0.033888889 | AG52: =(AG$56-AG$46)/($A$56-$A$46) + AG51 -> 0.1105 | AH52: =SUM(AF52:AG52) -> 0.14438889 | AI52: =AF52/$B$3 -> 0.060515873 | AJ52: =AG52/$B$3 -> 0.19732143 | AK52: =AH52/$B$3 -> 0.2578373 | AL52: =1/AD52 -> 5.4439404 | AM52: =1/AE52 -> 4.0948976
A53: 2057 | B53: =FORECAST($A53, $B$6:$B$15, $A$6:$A$15) + 0.002 -> 0.04098376 | C53: =FORECAST($A53, $C$6:$C$15, $A$6:$A$15) + 0.001 -> 0.097480656 | D53: =SUM(B53:C53) -> 0.13846442 | E53: =B53/$B$3 -> 0.073185286 | F53: =C53/$B$3 -> 0.1740726 | G53: =D53/$B$3 -> 0.24725789 | H53: =FORECAST($A53, $H$6:$H$15, $A$6:$A$15) + 0.002 -> 0.061745121 | I53: =FORECAST($A53, $I$6:$I$15, $A$6:$A$15) + 0.001 -> 0.12369759 | J53: =SUM(H53:I53) -> 0.18544271 | K53: =H53/$B$3 -> 0.11025915 | L53: =I53/$B$3 -> 0.22088855 | M53: =J53/$B$3 -> 0.3311477 | N53: =$B$15 -> 0.026666597 | O53: =FORECAST($A53, $C$10:$C$15, $A$10:$A$15) + 0.001 -> 0.10943677 | P53: =SUM(N53:O53) -> 0.13610337 | Q53: =N53/$B$3 -> 0.047618923 | R53: =O53/$B$3 -> 0.1954228 | S53: =P53/$B$3 -> 0.24304173 | T53: =(T$56-T$38)/($A$56-$A$38) + T52 -> 0.039166667 | U53: =(U$56-U$38)/($A$56-$A$38) + U52 -> 0.12453333 | V53: =SUM(T53:U53) -> 0.1637 | W53: =T53/$B$3 -> 0.069940476 | X53: =U53/$B$3 -> 0.22238095 | Y53: =V53/$B$3 -> 0.29232143 | Z53: =(Z$56-Z$38)/($A$56-$A$38) + Z52 -> 0.034166667 | AA53: =(AA$56-AA$38)/($A$56-$A$38) + AA52 -> 0.10453333 | AB53: =SUM(Z53:AA53) -> 0.1387 | AC53: =Z53/$B$3 -> 0.061011905 | AD53: =AA53/$B$3 -> 0.18666667 | AE53: =AB53/$B$3 -> 0.24767857 | AF53: =(AF$56-AF$38)/($A$56-$A$38) + AF52 -> 0.034166667 | AG53: =(AG$56-AG$46)/($A$56-$A$46) + AG52 -> 0.11225 | AH53: =SUM(AF53:AG53) -> 0.14641667 | AI53: =AF53/$B$3 -> 0.061011905 | AJ53: =AG53/$B$3 -> 0.20044643 | AK53: =AH53/$B$3 -> 0.26145833 | AL53: =1/AD53 -> 5.3571429 | AM53: =1/AE53 -> 4.037491
A54: 2058 | B54: =FORECAST($A54, $B$6:$B$15, $A$6:$A$15) + 0.002 -> 0.041338339 | C54: =FORECAST($A54, $C$6:$C$15, $A$6:$A$15) + 0.001 -> 0.099088191 | D54: =SUM(B54:C54) -> 0.14042653 | E54: =B54/$B$3 -> 0.073818463 | F54: =C54/$B$3 -> 0.1769432 | G54: =D54/$B$3 -> 0.25076166 | H54: =FORECAST($A54, $H$6:$H$15, $A$6:$A$15) + 0.002 -> 0.062547084 | I54: =FORECAST($A54, $I$6:$I$15, $A$6:$A$15) + 0.001 -> 0.12586893 | J54: =SUM(H54:I54) -> 0.18841601 | K54: =H54/$B$3 -> 0.11169122 | L54: =I54/$B$3 -> 0.22476594 | M54: =J54/$B$3 -> 0.33645716 | N54: =$B$15 -> 0.026666597 | O54: =FORECAST($A54, $C$10:$C$15, $A$10:$A$15) + 0.001 -> 0.11134138 | P54: =SUM(N54:O54) -> 0.13800797 | Q54: =N54/$B$3 -> 0.047618923 | R54: =O54/$B$3 -> 0.19882389 | S54: =P54/$B$3 -> 0.24644281 | T54: =(T$56-T$38)/($A$56-$A$38) + T53 -> 0.039444444 | U54: =(U$56-U$38)/($A$56-$A$38) + U53 -> 0.1262 | V54: =SUM(T54:U54) -> 0.16564444 | W54: =T54/$B$3 -> 0.070436508 | X54: =U54/$B$3 -> 0.22535714 | Y54: =V54/$B$3 -> 0.29579365 | Z54: =(Z$56-Z$38)/($A$56-$A$38) + Z53 -> 0.034444444 | AA54: =(AA$56-AA$38)/($A$56-$A$38) + AA53 -> 0.1062 | AB54: =SUM(Z54:AA54) -> 0.14064444 | AC54: =Z54/$B$3 -> 0.061507937 | AD54: =AA54/$B$3 -> 0.18964286 | AE54: =AB54/$B$3 -> 0.25115079 | AF54: =(AF$56-AF$38)/($A$56-$A$38) + AF53 -> 0.034444444 | AG54: =(AG$56-AG$46)/($A$56-$A$46) + AG53 -> 0.114 | AH54: =SUM(AF54:AG54) -> 0.14844444 | AI54: =AF54/$B$3 -> 0.061507937 | AJ54: =AG54/$B$3 -> 0.20357143 | AK54: =AH54/$B$3 -> 0.26507937 | AL54: =1/AD54 -> 5.2730697 | AM54: =1/AE54 -> 3.9816717
A55: 2059 | B55: =FORECAST($A55, $B$6:$B$15, $A$6:$A$15) + 0.002 -> 0.041692918 | C55: =FORECAST($A55, $C$6:$C$15, $A$6:$A$15) + 0.001 -> 0.10069573 | D55: =SUM(B55:C55) -> 0.14238864 | E55: =B55/$B$3 -> 0.07445164 | F55: =C55/$B$3 -> 0.1798138 | G55: =D55/$B$3 -> 0.25426544 | H55: =FORECAST($A55, $H$6:$H$15, $A$6:$A$15) + 0.002 -> 0.063349046 | I55: =FORECAST($A55, $I$6:$I$15, $A$6:$A$15) + 0.001 -> 0.12804027 | J55: =SUM(H55:I55) -> 0.19138931 | K55: =H55/$B$3 -> 0.1131233 | L55: =I55/$B$3 -> 0.22864333 | M55: =J55/$B$3 -> 0.34176663 | N55: =$B$15 -> 0.026666597 | O55: =FORECAST($A55, $C$10:$C$15, $A$10:$A$15) + 0.001 -> 0.11324599 | P55: =SUM(N55:O55) -> 0.13991258 | Q55: =N55/$B$3 -> 0.047618923 | R55: =O55/$B$3 -> 0.20222497 | S55: =P55/$B$3 -> 0.2498439 | T55: =(T$56-T$38)/($A$56-$A$38) + T54 -> 0.039722222 | U55: =(U$56-U$38)/($A$56-$A$38) + U54 -> 0.12786667 | V55: =SUM(T55:U55) -> 0.16758889 | W55: =T55/$B$3 -> 0.07093254 | X55: =U55/$B$3 -> 0.22833333 | Y55: =V55/$B$3 -> 0.29926587 | Z55: =(Z$56-Z$38)/($A$56-$A$38) + Z54 -> 0.034722222 | AA55: =(AA$56-AA$38)/($A$56-$A$38) + AA54 -> 0.10786667 | AB55: =SUM(Z55:AA55) -> 0.14258889 | AC55: =Z55/$B$3 -> 0.062003968 | AD55: =AA55/$B$3 -> 0.19261905 | AE55: =AB55/$B$3 -> 0.25462302 | AF55: =(AF$56-AF$38)/($A$56-$A$38) + AF54 -> 0.034722222 | AG55: =(AG$56-AG$46)/($A$56-$A$46) + AG54 -> 0.11575 | AH55: =SUM(AF55:AG55) -> 0.15047222 | AI55: =AF55/$B$3 -> 0.062003968 | AJ55: =AG55/$B$3 -> 0.20669643 | AK55: =AH55/$B$3 -> 0.2687004 | AL55: =1/AD55 -> 5.1915946 | AM55: =1/AE55 -> 3.9273747
A56: 2060 | B56: =FORECAST($A56, $B$6:$B$15, $A$6:$A$15) + 0.002 -> 0.042047497 | C56: =FORECAST($A56, $C$6:$C$15, $A$6:$A$15) + 0.001 -> 0.10230326 | D56: =SUM(B56:C56) -> 0.14435076 | E56: =B56/$B$3 -> 0.075084817 | F56: =C56/$B$3 -> 0.18268439 | G56: =D56/$B$3 -> 0.25776921 | H56: =FORECAST($A56, $H$6:$H$15, $A$6:$A$15) + 0.002 -> 0.064151008 | I56: =FORECAST($A56, $I$6:$I$15, $A$6:$A$15) + 0.001 -> 0.13021161 | J56: =SUM(H56:I56) -> 0.19436261 | K56: =H56/$B$3 -> 0.11455537 | L56: =I56/$B$3 -> 0.23252072 | M56: =J56/$B$3 -> 0.3470761 | N56: =$B$15 -> 0.026666597 | O56: =FORECAST($A56, $C$10:$C$15, $A$10:$A$15) + 0.001 -> 0.11515059 | P56: =SUM(N56:O56) -> 0.14181719 | Q56: =N56/$B$3 -> 0.047618923 | R56: =O56/$B$3 -> 0.20562606 | S56: =P56/$B$3 -> 0.25324498 | T56: 0.04 | U56: 0.13 | V56: =SUM(T56:U56) -> 0.17 | W56: =T56/$B$3 -> 0.071428571 | X56: =U56/$B$3 -> 0.23214286 | Y56: =V56/$B$3 -> 0.30357143 | Z56: 0.035 | AA56: 0.11 | AB56: =SUM(Z56:AA56) -> 0.145 | AC56: =Z56/$B$3 -> 0.0625 | AD56: =AA56/$B$3 -> 0.19642857 | AE56: =AB56/$B$3 -> 0.25892857 | AF56: 0.035 | AG56: 0.1175 | AH56: =SUM(AF56:AG56) -> 0.1525 | AI56: =AF56/$B$3 -> 0.0625 | AJ56: =AG56/$B$3 -> 0.20982143 | AK56: =AH56/$B$3 -> 0.27232143 | AL56: =1/AD56 -> 5.0909091 | AM56: =1/AE56 -> 3.862069
A59: Notes
A60: • 69% of U.S. employees worked from home at the peak of the pandemic [State of the Remote Workforce, Global Workplace Analytics and OwlLabs, 2020 – based on 2,500 survey responses from full-time workers]
A61: • 56% of employees have a job where at least some of what they do could be done remotely [Global Workplace Analytics]
A62: https://globalworkplaceanalytics.com/telecommuting-statistics

Sheet Forecast (r1)
A1: Forecast Share of Work At Home, Telecommute & Home-Based Workers
B3: 0.56 | C3: share of employment eligible to telecommute
B4: 5-Year ACS (2010-2019 Trend) | H4: 1-Year ACS (2010-2019 Trend) | N4: 5-Year ACS (2010-2014 Trend) | T4: Post Covid - Upper | Z4: Post Covid - Lower
B5: Home-Based | C5: Telecommute | D5: Work At Home | E5: % of Workers Who Can Work At Home | H5: Home-Based | I5: Telecommute | J5: Work At Home | K5: % of Workers Who Can Work At Home | N5: Home-Based | O5: Telecommute | P5: Work At Home | Q5: % of Workers Who Can Work At Home | T5: Home-Based | U5: Telecommute | V5: Work At Home | W5: % of Workers Who Can Work At Home | Z5: Home-Based | AA5: Telecommute | AB5: Work At Home | AC5: % of Workers Who Can Work At Home
A6: 2010 | B6: =HLOOKUP($A6, WAH_byCounty!$AZ$6:$BI$9, 2, FALSE) -> 0.024156393 | C6: =HLOOKUP($A6, WAH_byCounty!$AZ$6:$BI$9, 3, FALSE) -> 0.02188431 | D6: =SUM(B6:C6) -> 0.046040703 | H6: =B6/D6 * J6 -> 0.022378086 | I6: =C6/D6 * J6 -> 0.020273265 | J6: 0.042651351
A7: 2011 | B7: =HLOOKUP($A7, WAH_byCounty!$AZ$6:$BI$9, 2, FALSE) -> 0.023616541 | C7: =HLOOKUP($A7, WAH_byCounty!$AZ$6:$BI$9, 3, FALSE) -> 0.023317437 | D7: =SUM(B7:C7) -> 0.046933978 | E7: =B7/$B$3 -> 0.042172394 | F7: =C7/$B$3 -> 0.041638281 | G7: =D7/$B$3 -> 0.083810675 | H7: =B7/D7 * J7 -> 0.023758557 | I7: =C7/D7 * J7 -> 0.023457655 | J7: 0.047216212
A8: 2012 | B8: =HLOOKUP($A8, WAH_byCounty!$AZ$6:$BI$9, 2, FALSE) -> 0.022667213 | C8: =HLOOKUP($A8, WAH_byCounty!$AZ$6:$BI$9, 3, FALSE) -> 0.023317753 | D8: =SUM(B8:C8) -> 0.045984966 | E8: =B8/$B$3 -> 0.040477166 | F8: =C8/$B$3 -> 0.041638844 | G8: =D8/$B$3 -> 0.082116011 | H8: =B8/D8 * J8 -> 0.023339433 | I8: =C8/D8 * J8 -> 0.024009265 | J8: 0.047348698
A9: 2013 | B9: =HLOOKUP($A9, WAH_byCounty!$AZ$6:$BI$9, 2, FALSE) -> 0.022171769 | C9: =HLOOKUP($A9, WAH_byCounty!$AZ$6:$BI$9, 3, FALSE) -> 0.02528403 | D9: =SUM(B9:C9) -> 0.047455799 | E9: =B9/$B$3 -> 0.039592445 | F9: =C9/$B$3 -> 0.045150053 | G9: =D9/$B$3 -> 0.084742498 | H9: =B9/D9 * J9 -> 0.023907051 | I9: =C9/D9 * J9 -> 0.027262894 | J9: 0.051169945
A10: 2014 | B10: =HLOOKUP($A10, WAH_byCounty!$AZ$6:$BI$9, 2, FALSE) -> 0.022228968 | C10: =HLOOKUP($A10, WAH_byCounty!$AZ$6:$BI$9, 3, FALSE) -> 0.0266197 | D10: =SUM(B10:C10) -> 0.048848668 | E10: =B10/$B$3 -> 0.039694585 | F10: =C10/$B$3 -> 0.047535179 | G10: =D10/$B$3 -> 0.087229764 | H10: =B10/D10 * J10 -> 0.025486223 | I10: =C10/D10 * J10 -> 0.030520339 | J10: 0.056006562
A11: 2015 | B11: =HLOOKUP($A11, WAH_byCounty!$AZ$6:$BI$9, 2, FALSE) -> 0.022692701 | C11: =HLOOKUP($A11, WAH_byCounty!$AZ$6:$BI$9, 3, FALSE) -> 0.028966157 | D11: =SUM(B11:C11) -> 0.051658859 | E11: =B11/$B$3 -> 0.040522681 | F11: =C11/$B$3 -> 0.051725281 | G11: =D11/$B$3 -> 0.092247962 | H11: =B11/D11 * J11 -> 0.024860784 | I11: =C11/D11 * J11 -> 0.031733612 | J11: 0.056594397
A12: 2016 | B12: =HLOOKUP($A12, WAH_byCounty!$AZ$6:$BI$9, 2, FALSE) -> 0.023436385 | C12: =HLOOKUP($A12, WAH_byCounty!$AZ$6:$BI$9, 3, FALSE) -> 0.029703592 | D12: =SUM(B12:C12) -> 0.053139977 | E12: =B12/$B$3 -> 0.041850688 | F12: =C12/$B$3 -> 0.053042128 | G12: =D12/$B$3 -> 0.094892816 | H12: =B12/D12 * J12 -> 0.025492764 | I12: =C12/D12 * J12 -> 0.032309874 | J12: 0.057802638
A13: 2017 | B13: =HLOOKUP($A13, WAH_byCounty!$AZ$6:$BI$9, 2, FALSE) -> 0.025113206 | C13: =HLOOKUP($A13, WAH_byCounty!$AZ$6:$BI$9, 3, FALSE) -> 0.032081021 | D13: =SUM(B13:C13) -> 0.057194228 | E13: =B13/$B$3 -> 0.044845011 | F13: =C13/$B$3 -> 0.057287538 | G13: =D13/$B$3 -> 0.10213255 | H13: =B13/D13 * J13 -> 0.029327256 | I13: =C13/D13 * J13 -> 0.037464286 | J13: 0.066791542
A14: 2018 | B14: =HLOOKUP($A14, WAH_byCounty!$AZ$6:$BI$9, 2, FALSE) -> 0.026391708 | C14: =HLOOKUP($A14, WAH_byCounty!$AZ$6:$BI$9, 3, FALSE) -> 0.033935668 | D14: =SUM(B14:C14) -> 0.060327376 | E14: =B14/$B$3 -> 0.04712805 | F14: =C14/$B$3 -> 0.060599407 | G14: =D14/$B$3 -> 0.10772746 | H14: =B14/D14 * J14 -> 0.028318982 | I14: =C14/D14 * J14 -> 0.036413845 | J14: 0.064732827
A15: 2019 | B15: =HLOOKUP($A15, WAH_byCounty!$AZ$6:$BI$9, 2, FALSE) -> 0.026666597 | C15: =HLOOKUP($A15, WAH_byCounty!$AZ$6:$BI$9, 3, FALSE) -> 0.036494763 | D15: =SUM(B15:C15) -> 0.06316136 | E15: =B15/$B$3 -> 0.047618923 | F15: =C15/$B$3 -> 0.06516922 | G15: =D15/$B$3 -> 0.11278814 | H15: =B15/D15 * J15 -> 0.029748085 | I15: =C15/D15 * J15 -> 0.040711957 | J15: 0.070460042 | K15: =H15/$B$3 -> 0.053121581 | L15: =I15/$B$3 -> 0.072699923 | M15: =J15/$B$3 -> 0.1258215 | Q15: =N15/$B$3 -> 0 | R15: =O15/$B$3 -> 0 | S15: =P15/$B$3 -> 0 | T15: =B15 -> 0.026666597 | U15: =C15 -> 0.036494763 | V15: =SUM(T15:U15) -> 0.06316136 | W15: =T15/$B$3 -> 0.047618923 | X15: =U15/$B$3 -> 0.06516922 | Y15: =V15/$B$3 -> 0.11278814 | Z15: =B15 -> 0.026666597 | AA15: =C15 -> 0.036494763 | AB15: =SUM(Z15:AA15) -> 0.06316136 | AC15: =Z15/$B$3 -> 0.047618923 | AD15: =AA15/$B$3 -> 0.06516922 | AE15: =AB15/$B$3 -> 0.11278814 | AF15: =1/AD15 -> 15.344667 | AG15: =1/AE15 -> 8.8661802
A16: 2020 | B16: =FORECAST($A16, $B$6:$B$15, $A$6:$A$15) + 0.002 -> 0.027864333 | C16: =FORECAST($A16, $C$6:$C$15, $A$6:$A$15) + 0.001 -> 0.038001883 | D16: =SUM(B16:C16) -> 0.065866216 | E16: =B16/$B$3 -> 0.049757738 | F16: =C16/$B$3 -> 0.067860505 | G16: =D16/$B$3 -> 0.11761824 | H16: =FORECAST($A16, $H$6:$H$15, $A$6:$A$15) + 0.002 -> 0.032072515 | I16: =FORECAST($A16, $I$6:$I$15, $A$6:$A$15) + 0.001 -> 0.043358062 | J16: =SUM(H16:I16) -> 0.075430577 | K16: =H16/$B$3 -> 0.057272348 | L16: =I16/$B$3 -> 0.07742511 | M16: =J16/$B$3 -> 0.13469746 | N16: =$B$15 -> 0.026666597 | O16: =FORECAST($A16, $C$10:$C$15, $A$10:$A$15) + 0.001 -> 0.038966278 | P16: =SUM(N16:O16) -> 0.065632875 | Q16: =N16/$B$3 -> 0.047618923 | R16: =O16/$B$3 -> 0.069582639 | S16: =P16/$B$3 -> 0.11720156 | T16: 0.08 | U16: 0.35 | V16: =SUM(T16:U16) -> 0.43 | W16: =T16/$B$3 -> 0.14285714 | X16: =U16/$B$3 -> 0.625 | Y16: =V16/$B$3 -> 0.76785714 | Z16: 0.06 | AA16: 0.35 | AB16: =SUM(Z16:AA16) -> 0.41 | AC16: =Z16/$B$3 -> 0.10714286 | AD16: =AA16/$B$3 -> 0.625 | AE16: =AB16/$B$3 -> 0.73214286 | AF16: =1/AD16 -> 1.6 | AG16: =1/AE16 -> 1.3658537
A17: 2021 | B17: =FORECAST($A17, $B$6:$B$15, $A$6:$A$15) + 0.002 -> 0.028218912 | C17: =FORECAST($A17, $C$6:$C$15, $A$6:$A$15) + 0.001 -> 0.039609417 | D17: =SUM(B17:C17) -> 0.067828329 | E17: =B17/$B$3 -> 0.050390915 | F17: =C17/$B$3 -> 0.070731102 | G17: =D17/$B$3 -> 0.12112202 | H17: =FORECAST($A17, $H$6:$H$15, $A$6:$A$15) + 0.002 -> 0.032874477 | I17: =FORECAST($A17, $I$6:$I$15, $A$6:$A$15) + 0.001 -> 0.0455294 | J17: =SUM(H17:I17) -> 0.078403877 | K17: =H17/$B$3 -> 0.058704424 | L17: =I17/$B$3 -> 0.0813025 | M17: =J17/$B$3 -> 0.14000692 | N17: =$B$15 -> 0.026666597 | O17: =FORECAST($A17, $C$10:$C$15, $A$10:$A$15) + 0.001 -> 0.040870886 | P17: =SUM(N17:O17) -> 0.067537483 | Q17: =N17/$B$3 -> 0.047618923 | R17: =O17/$B$3 -> 0.072983725 | S17: =P17/$B$3 -> 0.12060265 | T17: 0.06 | U17: 0.2 | V17: =SUM(T17:U17) -> 0.26 | W17: =T17/$B$3 -> 0.10714286 | X17: =U17/$B$3 -> 0.35714286 | Y17: =V17/$B$3 -> 0.46428571 | Z17: 0.04 | AA17: 0.15 | AB17: =SUM(Z17:AA17) -> 0.19 | AC17: =Z17/$B$3 -> 0.071428571 | AD17: =AA17/$B$3 -> 0.26785714 | AE17: =AB17/$B$3 -> 0.33928571 | AF17: =1/AD17 -> 3.7333333 | AG17: =1/AE17 -> 2.9473684
A18: 2022 | B18: =FORECAST($A18, $B$6:$B$15, $A$6:$A$15) + 0.002 -> 0.028573491 | C18: =FORECAST($A18, $C$6:$C$15, $A$6:$A$15) + 0.001 -> 0.041216951 | D18: =SUM(B18:C18) -> 0.069790443 | E18: =B18/$B$3 -> 0.051024092 | F18: =C18/$B$3 -> 0.073601699 | G18: =D18/$B$3 -> 0.12462579 | H18: =FORECAST($A18, $H$6:$H$15, $A$6:$A$15) + 0.002 -> 0.03367644 | I18: =FORECAST($A18, $I$6:$I$15, $A$6:$A$15) + 0.001 -> 0.047700739 | J18: =SUM(H18:I18) -> 0.081377178 | K18: =H18/$B$3 -> 0.060136499 | L18: =I18/$B$3 -> 0.085179891 | M18: =J18/$B$3 -> 0.14531639 | N18: =$B$15 -> 0.026666597 | O18: =FORECAST($A18, $C$10:$C$15, $A$10:$A$15) + 0.001 -> 0.042775494 | P18: =SUM(N18:O18) -> 0.069442091 | Q18: =N18/$B$3 -> 0.047618923 | R18: =O18/$B$3 -> 0.07638481 | S18: =P18/$B$3 -> 0.12400373 | T18: 0.044 | U18: 0.15 | V18: =SUM(T18:U18) -> 0.194 | W18: =T18/$B$3 -> 0.078571429 | X18: =U18/$B$3 -> 0.26785714 | Y18: =V18/$B$3 -> 0.34642857 | Z18: 0.0325 | AA18: 0.1 | AB18: =SUM(Z18:AA18) -> 0.1325 | AC18: =Z18/$B$3 -> 0.058035714 | AD18: =AA18/$B$3 -> 0.17857143 | AE18: =AB18/$B$3 -> 0.23660714 | AF18: =1/AD18 -> 5.6 | AG18: =1/AE18 -> 4.2264151
A19: 2023 | B19: =FORECAST($A19, $B$6:$B$15, $A$6:$A$15) + 0.002 -> 0.028928071 | C19: =FORECAST($A19, $C$6:$C$15, $A$6:$A$15) + 0.001 -> 0.042824486 | D19: =SUM(B19:C19) -> 0.071752556 | E19: =B19/$B$3 -> 0.051657269 | F19: =C19/$B$3 -> 0.076472296 | G19: =D19/$B$3 -> 0.12812957 | H19: =FORECAST($A19, $H$6:$H$15, $A$6:$A$15) + 0.002 -> 0.034478402 | I19: =FORECAST($A19, $I$6:$I$15, $A$6:$A$15) + 0.001 -> 0.049872077 | J19: =SUM(H19:I19) -> 0.084350479 | K19: =H19/$B$3 -> 0.061568575 | L19: =I19/$B$3 -> 0.089057281 | M19: =J19/$B$3 -> 0.15062586 | N19: =$B$15 -> 0.026666597 | O19: =FORECAST($A19, $C$10:$C$15, $A$10:$A$15) + 0.001 -> 0.044680102 | P19: =SUM(N19:O19) -> 0.071346698 | Q19: =N19/$B$3 -> 0.047618923 | R19: =O19/$B$3 -> 0.079785896 | S19: =P19/$B$3 -> 0.12740482 | T19: 0.0375 | U19: 0.12 | V19: =SUM(T19:U19) -> 0.1575 | W19: =T19/$B$3 -> 0.066964286 | X19: =U19/$B$3 -> 0.21428571 | Y19: =V19/$B$3 -> 0.28125 | Z19: 0.03 | AA19: 0.083 | AB19: =SUM(Z19:AA19) -> 0.113 | AC19: =Z19/$B$3 -> 0.053571429 | AD19: =AA19/$B$3 -> 0.14821429 | AE19: =AB19/$B$3 -> 0.20178571 | AF19: =1/AD19 -> 6.746988 | AG19: =1/AE19 -> 4.9557522
A20: 2024 | B20: =FORECAST($A20, $B$6:$B$15, $A$6:$A$15) + 0.002 -> 0.02928265 | C20: =FORECAST($A20, $C$6:$C$15, $A$6:$A$15) + 0.001 -> 0.04443202 | D20: =SUM(B20:C20) -> 0.07371467 | E20: =B20/$B$3 -> 0.052290446 | F20: =C20/$B$3 -> 0.079342893 | G20: =D20/$B$3 -> 0.13163334 | H20: =FORECAST($A20, $H$6:$H$15, $A$6:$A$15) + 0.002 -> 0.035280364 | I20: =FORECAST($A20, $I$6:$I$15, $A$6:$A$15) + 0.001 -> 0.052043416 | J20: =SUM(H20:I20) -> 0.08732378 | K20: =H20/$B$3 -> 0.063000651 | L20: =I20/$B$3 -> 0.092934671 | M20: =J20/$B$3 -> 0.15593532 | N20: =$B$15 -> 0.026666597 | O20: =FORECAST($A20, $C$10:$C$15, $A$10:$A$15) + 0.001 -> 0.04658471 | P20: =SUM(N20:O20) -> 0.073251306 | Q20: =N20/$B$3 -> 0.047618923 | R20: =O20/$B$3 -> 0.083186981 | S20: =P20/$B$3 -> 0.1308059 | T20: 0.035 | U20: 0.1025 | V20: =SUM(T20:U20) -> 0.1375 | W20: =T20/$B$3 -> 0.0625 | X20: =U20/$B$3 -> 0.18303571 | Y20: =V20/$B$3 -> 0.24553571 | Z20: =Z19 -> 0.03 | AA20: 0.08 | AB20: =SUM(Z20:AA20) -> 0.11 | AC20: =Z20/$B$3 -> 0.053571429 | AD20: =AA20/$B$3 -> 0.14285714 | AE20: =AB20/$B$3 -> 0.19642857 | AF20: =1/AD20 -> 7 | AG20: =1/AE20 -> 5.0909091
A21: 2025 | B21: =FORECAST($A21, $B$6:$B$15, $A$6:$A$15) + 0.002 -> 0.029637229 | C21: =FORECAST($A21, $C$6:$C$15, $A$6:$A$15) + 0.001 -> 0.046039555 | D21: =SUM(B21:C21) -> 0.075676783 | E21: =B21/$B$3 -> 0.052923623 | F21: =C21/$B$3 -> 0.082213491 | G21: =D21/$B$3 -> 0.13513711 | H21: =FORECAST($A21, $H$6:$H$15, $A$6:$A$15) + 0.002 -> 0.036082327 | I21: =FORECAST($A21, $I$6:$I$15, $A$6:$A$15) + 0.001 -> 0.054214755 | J21: =SUM(H21:I21) -> 0.090297081 | K21: =H21/$B$3 -> 0.064432726 | L21: =I21/$B$3 -> 0.096812062 | M21: =J21/$B$3 -> 0.16124479 | N21: =$B$15 -> 0.026666597 | O21: =FORECAST($A21, $C$10:$C$15, $A$10:$A$15) + 0.001 -> 0.048489317 | P21: =SUM(N21:O21) -> 0.075155914 | Q21: =N21/$B$3 -> 0.047618923 | R21: =O21/$B$3 -> 0.086588067 | S21: =P21/$B$3 -> 0.13420699 | T21: =T20 -> 0.035 | U21: 0.1 | V21: =SUM(T21:U21) -> 0.135 | W21: =T21/$B$3 -> 0.0625 | X21: =U21/$B$3 -> 0.17857143 | Y21: =V21/$B$3 -> 0.24107143 | Z21: =Z20 -> 0.03 | AA21: =AA20 -> 0.08 | AB21: =SUM(Z21:AA21) -> 0.11 | AC21: =Z21/$B$3 -> 0.053571429 | AD21: =AA21/$B$3 -> 0.14285714 | AE21: =AB21/$B$3 -> 0.19642857 | AF21: =1/AD21 -> 7 | AG21: =1/AE21 -> 5.0909091
A22: 2026 | B22: =FORECAST($A22, $B$6:$B$15, $A$6:$A$15) + 0.002 -> 0.029991808 | C22: =FORECAST($A22, $C$6:$C$15, $A$6:$A$15) + 0.001 -> 0.047647089 | D22: =SUM(B22:C22) -> 0.077638897 | E22: =B22/$B$3 -> 0.0535568 | F22: =C22/$B$3 -> 0.085084088 | G22: =D22/$B$3 -> 0.13864089 | H22: =FORECAST($A22, $H$6:$H$15, $A$6:$A$15) + 0.002 -> 0.036884289 | I22: =FORECAST($A22, $I$6:$I$15, $A$6:$A$15) + 0.001 -> 0.056386093 | J22: =SUM(H22:I22) -> 0.093270382 | K22: =H22/$B$3 -> 0.065864802 | L22: =I22/$B$3 -> 0.10068945 | M22: =J22/$B$3 -> 0.16655425 | N22: =$B$15 -> 0.026666597 | O22: =FORECAST($A22, $C$10:$C$15, $A$10:$A$15) + 0.001 -> 0.050393925 | P22: =SUM(N22:O22) -> 0.077060522 | Q22: =N22/$B$3 -> 0.047618923 | R22: =O22/$B$3 -> 0.089989152 | S22: =P22/$B$3 -> 0.13760808 | T22: =T21 -> 0.035 | U22: =U21 -> 0.1 | V22: =SUM(T22:U22) -> 0.135 | W22: =T22/$B$3 -> 0.0625 | X22: =U22/$B$3 -> 0.17857143 | Y22: =V22/$B$3 -> 0.24107143 | Z22: =Z21 -> 0.03 | AA22: =AA21 -> 0.08 | AB22: =SUM(Z22:AA22) -> 0.11 | AC22: =Z22/$B$3 -> 0.053571429 | AD22: =AA22/$B$3 -> 0.14285714 | AE22: =AB22/$B$3 -> 0.19642857 | AF22: =1/AD22 -> 7 | AG22: =1/AE22 -> 5.0909091
A23: 2027 | B23: =FORECAST($A23, $B$6:$B$15, $A$6:$A$15) + 0.002 -> 0.030346387 | C23: =FORECAST($A23, $C$6:$C$15, $A$6:$A$15) + 0.001 -> 0.049254624 | D23: =SUM(B23:C23) -> 0.079601011 | E23: =B23/$B$3 -> 0.054189977 | F23: =C23/$B$3 -> 0.087954685 | G23: =D23/$B$3 -> 0.14214466 | H23: =FORECAST($A23, $H$6:$H$15, $A$6:$A$15) + 0.002 -> 0.037686251 | I23: =FORECAST($A23, $I$6:$I$15, $A$6:$A$15) + 0.001 -> 0.058557432 | J23: =SUM(H23:I23) -> 0.096243683 | K23: =H23/$B$3 -> 0.067296877 | L23: =I23/$B$3 -> 0.10456684 | M23: =J23/$B$3 -> 0.17186372 | N23: =$B$15 -> 0.026666597 | O23: =FORECAST($A23, $C$10:$C$15, $A$10:$A$15) + 0.001 -> 0.052298533 | P23: =SUM(N23:O23) -> 0.07896513 | Q23: =N23/$B$3 -> 0.047618923 | R23: =O23/$B$3 -> 0.093390238 | S23: =P23/$B$3 -> 0.14100916 | T23: =T22 -> 0.035 | U23: =U22 -> 0.1 | V23: =SUM(T23:U23) -> 0.135 | W23: =T23/$B$3 -> 0.0625 | X23: =U23/$B$3 -> 0.17857143 | Y23: =V23/$B$3 -> 0.24107143 | Z23: =Z22 -> 0.03 | AA23: =AA22 -> 0.08 | AB23: =SUM(Z23:AA23) -> 0.11 | AC23: =Z23/$B$3 -> 0.053571429 | AD23: =AA23/$B$3 -> 0.14285714 | AE23: =AB23/$B$3 -> 0.19642857 | AF23: =1/AD23 -> 7 | AG23: =1/AE23 -> 5.0909091
A24: 2028 | B24: =FORECAST($A24, $B$6:$B$15, $A$6:$A$15) + 0.002 -> 0.030700966 | C24: =FORECAST($A24, $C$6:$C$15, $A$6:$A$15) + 0.001 -> 0.050862158 | D24: =SUM(B24:C24) -> 0.081563124 | E24: =B24/$B$3 -> 0.054823154 | F24: =C24/$B$3 -> 0.090825282 | G24: =D24/$B$3 -> 0.14564844 | H24: =FORECAST($A24, $H$6:$H$15, $A$6:$A$15) + 0.002 -> 0.038488214 | I24: =FORECAST($A24, $I$6:$I$15, $A$6:$A$15) + 0.001 -> 0.06072877 | J24: =SUM(H24:I24) -> 0.099216984 | K24: =H24/$B$3 -> 0.068728953 | L24: =I24/$B$3 -> 0.10844423 | M24: =J24/$B$3 -> 0.17717319 | N24: =$B$15 -> 0.026666597 | O24: =FORECAST($A24, $C$10:$C$15, $A$10:$A$15) + 0.001 -> 0.054203141 | P24: =SUM(N24:O24) -> 0.080869738 | Q24: =N24/$B$3 -> 0.047618923 | R24: =O24/$B$3 -> 0.096791323 | S24: =P24/$B$3 -> 0.14441025 | T24: =T23 -> 0.035 | U24: =U23 -> 0.1 | V24: =SUM(T24:U24) -> 0.135 | W24: =T24/$B$3 -> 0.0625 | X24: =U24/$B$3 -> 0.17857143 | Y24: =V24/$B$3 -> 0.24107143 | Z24: =Z23 -> 0.03 | AA24: =AA23 -> 0.08 | AB24: =SUM(Z24:AA24) -> 0.11 | AC24: =Z24/$B$3 -> 0.053571429 | AD24: =AA24/$B$3 -> 0.14285714 | AE24: =AB24/$B$3 -> 0.19642857 | AF24: =1/AD24 -> 7 | AG24: =1/AE24 -> 5.0909091
A25: 2029 | B25: =FORECAST($A25, $B$6:$B$15, $A$6:$A$15) + 0.002 -> 0.031055545 | C25: =FORECAST($A25, $C$6:$C$15, $A$6:$A$15) + 0.001 -> 0.052469692 | D25: =SUM(B25:C25) -> 0.083525238 | E25: =B25/$B$3 -> 0.055456331 | F25: =C25/$B$3 -> 0.093695879 | G25: =D25/$B$3 -> 0.14915221 | H25: =FORECAST($A25, $H$6:$H$15, $A$6:$A$15) + 0.002 -> 0.039290176 | I25: =FORECAST($A25, $I$6:$I$15, $A$6:$A$15) + 0.001 -> 0.062900109 | J25: =SUM(H25:I25) -> 0.10219028 | K25: =H25/$B$3 -> 0.070161029 | L25: =I25/$B$3 -> 0.11232162 | M25: =J25/$B$3 -> 0.18248265 | N25: =$B$15 -> 0.026666597 | O25: =FORECAST($A25, $C$10:$C$15, $A$10:$A$15) + 0.001 -> 0.056107749 | P25: =SUM(N25:O25) -> 0.082774346 | Q25: =N25/$B$3 -> 0.047618923 | R25: =O25/$B$3 -> 0.10019241 | S25: =P25/$B$3 -> 0.14781133 | T25: =T24 -> 0.035 | U25: =U24 -> 0.1 | V25: =SUM(T25:U25) -> 0.135 | W25: =T25/$B$3 -> 0.0625 | X25: =U25/$B$3 -> 0.17857143 | Y25: =V25/$B$3 -> 0.24107143 | Z25: =Z24 -> 0.03 | AA25: =AA24 -> 0.08 | AB25: =SUM(Z25:AA25) -> 0.11 | AC25: =Z25/$B$3 -> 0.053571429 | AD25: =AA25/$B$3 -> 0.14285714 | AE25: =AB25/$B$3 -> 0.19642857 | AF25: =1/AD25 -> 7 | AG25: =1/AE25 -> 5.0909091
A26: 2030 | B26: =FORECAST($A26, $B$6:$B$15, $A$6:$A$15) + 0.002 -> 0.031410124 | C26: =FORECAST($A26, $C$6:$C$15, $A$6:$A$15) + 0.001 -> 0.054077227 | D26: =SUM(B26:C26) -> 0.085487351 | E26: =B26/$B$3 -> 0.056089508 | F26: =C26/$B$3 -> 0.096566477 | G26: =D26/$B$3 -> 0.15265598 | H26: =FORECAST($A26, $H$6:$H$15, $A$6:$A$15) + 0.002 -> 0.040092138 | I26: =FORECAST($A26, $I$6:$I$15, $A$6:$A$15) + 0.001 -> 0.065071448 | J26: =SUM(H26:I26) -> 0.10516359 | K26: =H26/$B$3 -> 0.071593104 | L26: =I26/$B$3 -> 0.11619901 | M26: =J26/$B$3 -> 0.18779212 | N26: =$B$15 -> 0.026666597 | O26: =FORECAST($A26, $C$10:$C$15, $A$10:$A$15) + 0.001 -> 0.058012357 | P26: =SUM(N26:O26) -> 0.084678954 | Q26: =N26/$B$3 -> 0.047618923 | R26: =O26/$B$3 -> 0.10359349 | S26: =P26/$B$3 -> 0.15121242 | T26: =T25 -> 0.035 | U26: =U25 -> 0.1 | V26: =SUM(T26:U26) -> 0.135 | W26: =T26/$B$3 -> 0.0625 | X26: =U26/$B$3 -> 0.17857143 | Y26: =V26/$B$3 -> 0.24107143 | Z26: =Z25 -> 0.03 | AA26: =AA25 -> 0.08 | AB26: =SUM(Z26:AA26) -> 0.11 | AC26: =Z26/$B$3 -> 0.053571429 | AD26: =AA26/$B$3 -> 0.14285714 | AE26: =AB26/$B$3 -> 0.19642857 | AF26: =1/AD26 -> 7 | AG26: =1/AE26 -> 5.0909091
A27: 2031 | B27: =FORECAST($A27, $B$6:$B$15, $A$6:$A$15) + 0.002 -> 0.031764703 | C27: =FORECAST($A27, $C$6:$C$15, $A$6:$A$15) + 0.001 -> 0.055684761 | D27: =SUM(B27:C27) -> 0.087449465 | E27: =B27/$B$3 -> 0.056722685 | F27: =C27/$B$3 -> 0.099437074 | G27: =D27/$B$3 -> 0.15615976 | H27: =FORECAST($A27, $H$6:$H$15, $A$6:$A$15) + 0.002 -> 0.040894101 | I27: =FORECAST($A27, $I$6:$I$15, $A$6:$A$15) + 0.001 -> 0.067242786 | J27: =SUM(H27:I27) -> 0.10813689 | K27: =H27/$B$3 -> 0.07302518 | L27: =I27/$B$3 -> 0.1200764 | M27: =J27/$B$3 -> 0.19310158 | N27: =$B$15 -> 0.026666597 | O27: =FORECAST($A27, $C$10:$C$15, $A$10:$A$15) + 0.001 -> 0.059916965 | P27: =SUM(N27:O27) -> 0.086583562 | Q27: =N27/$B$3 -> 0.047618923 | R27: =O27/$B$3 -> 0.10699458 | S27: =P27/$B$3 -> 0.1546135 | T27: =T26 -> 0.035 | U27: =U26 -> 0.1 | V27: =SUM(T27:U27) -> 0.135 | W27: =T27/$B$3 -> 0.0625 | X27: =U27/$B$3 -> 0.17857143 | Y27: =V27/$B$3 -> 0.24107143 | Z27: =Z26 -> 0.03 | AA27: =AA26 -> 0.08 | AB27: =SUM(Z27:AA27) -> 0.11 | AC27: =Z27/$B$3 -> 0.053571429 | AD27: =AA27/$B$3 -> 0.14285714 | AE27: =AB27/$B$3 -> 0.19642857 | AF27: =1/AD27 -> 7 | AG27: =1/AE27 -> 5.0909091
A28: 2032 | B28: =FORECAST($A28, $B$6:$B$15, $A$6:$A$15) + 0.002 -> 0.032119282 | C28: =FORECAST($A28, $C$6:$C$15, $A$6:$A$15) + 0.001 -> 0.057292296 | D28: =SUM(B28:C28) -> 0.089411578 | E28: =B28/$B$3 -> 0.057355862 | F28: =C28/$B$3 -> 0.10230767 | G28: =D28/$B$3 -> 0.15966353 | H28: =FORECAST($A28, $H$6:$H$15, $A$6:$A$15) + 0.002 -> 0.041696063 | I28: =FORECAST($A28, $I$6:$I$15, $A$6:$A$15) + 0.001 -> 0.069414125 | J28: =SUM(H28:I28) -> 0.11111019 | K28: =H28/$B$3 -> 0.074457255 | L28: =I28/$B$3 -> 0.12395379 | M28: =J28/$B$3 -> 0.19841105 | N28: =$B$15 -> 0.026666597 | O28: =FORECAST($A28, $C$10:$C$15, $A$10:$A$15) + 0.001 -> 0.061821573 | P28: =SUM(N28:O28) -> 0.088488169 | Q28: =N28/$B$3 -> 0.047618923 | R28: =O28/$B$3 -> 0.11039567 | S28: =P28/$B$3 -> 0.15801459 | T28: =T27 -> 0.035 | U28: =U27 -> 0.1 | V28: =SUM(T28:U28) -> 0.135 | W28: =T28/$B$3 -> 0.0625 | X28: =U28/$B$3 -> 0.17857143 | Y28: =V28/$B$3 -> 0.24107143 | Z28: =Z27 -> 0.03 | AA28: =AA27 -> 0.08 | AB28: =SUM(Z28:AA28) -> 0.11 | AC28: =Z28/$B$3 -> 0.053571429 | AD28: =AA28/$B$3 -> 0.14285714 | AE28: =AB28/$B$3 -> 0.19642857 | AF28: =1/AD28 -> 7 | AG28: =1/AE28 -> 5.0909091
A29: 2033 | B29: =FORECAST($A29, $B$6:$B$15, $A$6:$A$15) + 0.002 -> 0.032473862 | C29: =FORECAST($A29, $C$6:$C$15, $A$6:$A$15) + 0.001 -> 0.05889983 | D29: =SUM(B29:C29) -> 0.091373692 | E29: =B29/$B$3 -> 0.057989039 | F29: =C29/$B$3 -> 0.10517827 | G29: =D29/$B$3 -> 0.16316731 | H29: =FORECAST($A29, $H$6:$H$15, $A$6:$A$15) + 0.002 -> 0.042498025 | I29: =FORECAST($A29, $I$6:$I$15, $A$6:$A$15) + 0.001 -> 0.071585463 | J29: =SUM(H29:I29) -> 0.11408349 | K29: =H29/$B$3 -> 0.075889331 | L29: =I29/$B$3 -> 0.12783118 | M29: =J29/$B$3 -> 0.20372052 | N29: =$B$15 -> 0.026666597 | O29: =FORECAST($A29, $C$10:$C$15, $A$10:$A$15) + 0.001 -> 0.06372618 | P29: =SUM(N29:O29) -> 0.090392777 | Q29: =N29/$B$3 -> 0.047618923 | R29: =O29/$B$3 -> 0.11379675 | S29: =P29/$B$3 -> 0.16141567 | T29: =T28 -> 0.035 | U29: =U28 -> 0.1 | V29: =SUM(T29:U29) -> 0.135 | W29: =T29/$B$3 -> 0.0625 | X29: =U29/$B$3 -> 0.17857143 | Y29: =V29/$B$3 -> 0.24107143 | Z29: =Z28 -> 0.03 | AA29: =AA28 -> 0.08 | AB29: =SUM(Z29:AA29) -> 0.11 | AC29: =Z29/$B$3 -> 0.053571429 | AD29: =AA29/$B$3 -> 0.14285714 | AE29: =AB29/$B$3 -> 0.19642857 | AF29: =1/AD29 -> 7 | AG29: =1/AE29 -> 5.0909091
A30: 2034 | B30: =FORECAST($A30, $B$6:$B$15, $A$6:$A$15) + 0.002 -> 0.032828441 | C30: =FORECAST($A30, $C$6:$C$15, $A$6:$A$15) + 0.001 -> 0.060507365 | D30: =SUM(B30:C30) -> 0.093335805 | E30: =B30/$B$3 -> 0.058622216 | F30: =C30/$B$3 -> 0.10804887 | G30: =D30/$B$3 -> 0.16667108 | H30: =FORECAST($A30, $H$6:$H$15, $A$6:$A$15) + 0.002 -> 0.043299988 | I30: =FORECAST($A30, $I$6:$I$15, $A$6:$A$15) + 0.001 -> 0.073756802 | J30: =SUM(H30:I30) -> 0.11705679 | K30: =H30/$B$3 -> 0.077321407 | L30: =I30/$B$3 -> 0.13170857 | M30: =J30/$B$3 -> 0.20902998 | N30: =$B$15 -> 0.026666597 | O30: =FORECAST($A30, $C$10:$C$15, $A$10:$A$15) + 0.001 -> 0.065630788 | P30: =SUM(N30:O30) -> 0.092297385 | Q30: =N30/$B$3 -> 0.047618923 | R30: =O30/$B$3 -> 0.11719784 | S30: =P30/$B$3 -> 0.16481676 | T30: =T29 -> 0.035 | U30: =U29 -> 0.1 | V30: =SUM(T30:U30) -> 0.135 | W30: =T30/$B$3 -> 0.0625 | X30: =U30/$B$3 -> 0.17857143 | Y30: =V30/$B$3 -> 0.24107143 | Z30: =Z29 -> 0.03 | AA30: =AA29 -> 0.08 | AB30: =SUM(Z30:AA30) -> 0.11 | AC30: =Z30/$B$3 -> 0.053571429 | AD30: =AA30/$B$3 -> 0.14285714 | AE30: =AB30/$B$3 -> 0.19642857 | AF30: =1/AD30 -> 7 | AG30: =1/AE30 -> 5.0909091
A31: 2035 | B31: =FORECAST($A31, $B$6:$B$15, $A$6:$A$15) + 0.002 -> 0.03318302 | C31: =FORECAST($A31, $C$6:$C$15, $A$6:$A$15) + 0.001 -> 0.062114899 | D31: =SUM(B31:C31) -> 0.095297919 | E31: =B31/$B$3 -> 0.059255393 | F31: =C31/$B$3 -> 0.11091946 | G31: =D31/$B$3 -> 0.17017486 | H31: =FORECAST($A31, $H$6:$H$15, $A$6:$A$15) + 0.002 -> 0.04410195 | I31: =FORECAST($A31, $I$6:$I$15, $A$6:$A$15) + 0.001 -> 0.075928141 | J31: =SUM(H31:I31) -> 0.12003009 | K31: =H31/$B$3 -> 0.078753482 | L31: =I31/$B$3 -> 0.13558597 | M31: =J31/$B$3 -> 0.21433945 | N31: =$B$15 -> 0.026666597 | O31: =FORECAST($A31, $C$10:$C$15, $A$10:$A$15) + 0.001 -> 0.067535396 | P31: =SUM(N31:O31) -> 0.094201993 | Q31: =N31/$B$3 -> 0.047618923 | R31: =O31/$B$3 -> 0.12059892 | S31: =P31/$B$3 -> 0.16821784 | T31: =T30 -> 0.035 | U31: =U30 -> 0.1 | V31: =SUM(T31:U31) -> 0.135 | W31: =T31/$B$3 -> 0.0625 | X31: =U31/$B$3 -> 0.17857143 | Y31: =V31/$B$3 -> 0.24107143 | Z31: =Z30 -> 0.03 | AA31: =AA30 -> 0.08 | AB31: =SUM(Z31:AA31) -> 0.11 | AC31: =Z31/$B$3 -> 0.053571429 | AD31: =AA31/$B$3 -> 0.14285714 | AE31: =AB31/$B$3 -> 0.19642857 | AF31: =1/AD31 -> 7 | AG31: =1/AE31 -> 5.0909091
A32: 2036 | B32: =FORECAST($A32, $B$6:$B$15, $A$6:$A$15) + 0.002 -> 0.033537599 | C32: =FORECAST($A32, $C$6:$C$15, $A$6:$A$15) + 0.001 -> 0.063722433 | D32: =SUM(B32:C32) -> 0.097260032 | E32: =B32/$B$3 -> 0.05988857 | F32: =C32/$B$3 -> 0.11379006 | G32: =D32/$B$3 -> 0.17367863 | H32: =FORECAST($A32, $H$6:$H$15, $A$6:$A$15) + 0.002 -> 0.044903912 | I32: =FORECAST($A32, $I$6:$I$15, $A$6:$A$15) + 0.001 -> 0.078099479 | J32: =SUM(H32:I32) -> 0.12300339 | K32: =H32/$B$3 -> 0.080185558 | L32: =I32/$B$3 -> 0.13946336 | M32: =J32/$B$3 -> 0.21964891 | N32: =$B$15 -> 0.026666597 | O32: =FORECAST($A32, $C$10:$C$15, $A$10:$A$15) + 0.001 -> 0.069440004 | P32: =SUM(N32:O32) -> 0.096106601 | Q32: =N32/$B$3 -> 0.047618923 | R32: =O32/$B$3 -> 0.12400001 | S32: =P32/$B$3 -> 0.17161893 | T32: =T31 -> 0.035 | U32: =U31 -> 0.1 | V32: =SUM(T32:U32) -> 0.135 | W32: =T32/$B$3 -> 0.0625 | X32: =U32/$B$3 -> 0.17857143 | Y32: =V32/$B$3 -> 0.24107143 | Z32: =Z31 -> 0.03 | AA32: =AA31 -> 0.08 | AB32: =SUM(Z32:AA32) -> 0.11 | AC32: =Z32/$B$3 -> 0.053571429 | AD32: =AA32/$B$3 -> 0.14285714 | AE32: =AB32/$B$3 -> 0.19642857 | AF32: =1/AD32 -> 7 | AG32: =1/AE32 -> 5.0909091
A33: 2037 | B33: =FORECAST($A33, $B$6:$B$15, $A$6:$A$15) + 0.002 -> 0.033892178 | C33: =FORECAST($A33, $C$6:$C$15, $A$6:$A$15) + 0.001 -> 0.065329968 | D33: =SUM(B33:C33) -> 0.099222146 | E33: =B33/$B$3 -> 0.060521746 | F33: =C33/$B$3 -> 0.11666066 | G33: =D33/$B$3 -> 0.1771824 | H33: =FORECAST($A33, $H$6:$H$15, $A$6:$A$15) + 0.002 -> 0.045705875 | I33: =FORECAST($A33, $I$6:$I$15, $A$6:$A$15) + 0.001 -> 0.080270818 | J33: =SUM(H33:I33) -> 0.12597669 | K33: =H33/$B$3 -> 0.081617633 | L33: =I33/$B$3 -> 0.14334075 | M33: =J33/$B$3 -> 0.22495838 | N33: =$B$15 -> 0.026666597 | O33: =FORECAST($A33, $C$10:$C$15, $A$10:$A$15) + 0.001 -> 0.071344612 | P33: =SUM(N33:O33) -> 0.098011209 | Q33: =N33/$B$3 -> 0.047618923 | R33: =O33/$B$3 -> 0.12740109 | S33: =P33/$B$3 -> 0.17502002 | T33: =T32 -> 0.035 | U33: =U32 -> 0.1 | V33: =SUM(T33:U33) -> 0.135 | W33: =T33/$B$3 -> 0.0625 | X33: =U33/$B$3 -> 0.17857143 | Y33: =V33/$B$3 -> 0.24107143 | Z33: =Z32 -> 0.03 | AA33: =AA32 -> 0.08 | AB33: =SUM(Z33:AA33) -> 0.11 | AC33: =Z33/$B$3 -> 0.053571429 | AD33: =AA33/$B$3 -> 0.14285714 | AE33: =AB33/$B$3 -> 0.19642857 | AF33: =1/AD33 -> 7 | AG33: =1/AE33 -> 5.0909091
... A38: 2042 | B38: =FORECAST($A38, $B$6:$B$15, $A$6:$A$15) + 0.002 -> 0.035665074 | C38: =FORECAST($A38, $C$6:$C$15, $A$6:$A$15) + 0.001 -> 0.07336764 | D38: =SUM(B38:C38) -> 0.10903271 | E38: =B38/$B$3 -> 0.063687631 | F38: =C38/$B$3 -> 0.13101364 | G38: =D38/$B$3 -> 0.19470127 | H38: =FORECAST($A38, $H$6:$H$15, $A$6:$A$15) + 0.002 -> 0.049715686 | I38: =FORECAST($A38, $I$6:$I$15, $A$6:$A$15) + 0.001 -> 0.091127511 | J38: =SUM(H38:I38) -> 0.1408432 | K38: =H38/$B$3 -> 0.088778011 | L38: =I38/$B$3 -> 0.1627277 | M38: =J38/$B$3 -> 0.25150571 | N38: =$B$15 -> 0.026666597 | O38: =FORECAST($A38, $C$10:$C$15, $A$10:$A$15) + 0.001 -> 0.080867651 | P38: =SUM(N38:O38) -> 0.10753425 | Q38: =N38/$B$3 -> 0.047618923 | R38: =O38/$B$3 -> 0.14440652 | S38: =P38/$B$3 -> 0.19202544 | T38: =T37 -> 0.035 | U38: =U37 -> 0.1 | V38: =SUM(T38:U38) -> 0.135 | W38: =T38/$B$3 -> 0.0625 | X38: =U38/$B$3 -> 0.17857143 | Y38: =V38/$B$3 -> 0.24107143 | Z38: =Z37 -> 0.03 | AA38: =AA37 -> 0.08 | AB38: =SUM(Z38:AA38) -> 0.11 | AC38: =Z38/$B$3 -> 0.053571429 | AD38: =AA38/$B$3 -> 0.14285714 | AE38: =AB38/$B$3 -> 0.19642857 | AF38: =1/AD38 -> 7 | AG38: =1/AE38 -> 5.0909091
A39: 2043 | B39: =FORECAST($A39, $B$6:$B$15, $A$6:$A$15) + 0.002 -> 0.036019653 | C39: =FORECAST($A39, $C$6:$C$15, $A$6:$A$15) + 0.001 -> 0.074975174 | D39: =SUM(B39:C39) -> 0.11099483 | E39: =B39/$B$3 -> 0.064320808 | F39: =C39/$B$3 -> 0.13388424 | G39: =D39/$B$3 -> 0.19820505 | H39: =FORECAST($A39, $H$6:$H$15, $A$6:$A$15) + 0.002 -> 0.050517649 | I39: =FORECAST($A39, $I$6:$I$15, $A$6:$A$15) + 0.001 -> 0.093298849 | J39: =SUM(H39:I39) -> 0.1438165 | K39: =H39/$B$3 -> 0.090210087 | L39: =I39/$B$3 -> 0.16660509 | M39: =J39/$B$3 -> 0.25681518 | N39: =$B$15 -> 0.026666597 | O39: =FORECAST($A39, $C$10:$C$15, $A$10:$A$15) + 0.001 -> 0.082772259 | P39: =SUM(N39:O39) -> 0.10943886 | Q39: =N39/$B$3 -> 0.047618923 | R39: =O39/$B$3 -> 0.14780761 | S39: =P39/$B$3 -> 0.19542653 | T39: =(T$56-T$38)/($A$56-$A$38) + T38 -> 0.035277778 | U39: =(U$56-U$31)/($A$56-$A$31) + U31 -> 0.1012 | V39: =SUM(T39:U39) -> 0.13647778 | W39: =T39/$B$3 -> 0.062996032 | X39: =U39/$B$3 -> 0.18071429 | Y39: =V39/$B$3 -> 0.24371032 | Z39: =(Z$56-Z$38)/($A$56-$A$38) + Z38 -> 0.030277778 | AA39: =(AA$56-AA$31)/($A$56-$A$31) + AA31 -> 0.0812 | AB39: =SUM(Z39:AA39) -> 0.11147778 | AC39: =Z39/$B$3 -> 0.05406746 | AD39: =AA39/$B$3 -> 0.145 | AE39: =AB39/$B$3 -> 0.19906746 | AF39: =1/AD39 -> 6.8965517 | AG39: =1/AE39 -> 5.0234227
A40: 2044 | B40: =FORECAST($A40, $B$6:$B$15, $A$6:$A$15) + 0.002 -> 0.036374232 | C40: =FORECAST($A40, $C$6:$C$15, $A$6:$A$15) + 0.001 -> 0.076582709 | D40: =SUM(B40:C40) -> 0.11295694 | E40: =B40/$B$3 -> 0.064953985 | F40: =C40/$B$3 -> 0.13675484 | G40: =D40/$B$3 -> 0.20170882 | H40: =FORECAST($A40, $H$6:$H$15, $A$6:$A$15) + 0.002 -> 0.051319611 | I40: =FORECAST($A40, $I$6:$I$15, $A$6:$A$15) + 0.001 -> 0.095470188 | J40: =SUM(H40:I40) -> 0.1467898 | K40: =H40/$B$3 -> 0.091642163 | L40: =I40/$B$3 -> 0.17048248 | M40: =J40/$B$3 -> 0.26212464 | N40: =$B$15 -> 0.026666597 | O40: =FORECAST($A40, $C$10:$C$15, $A$10:$A$15) + 0.001 -> 0.084676867 | P40: =SUM(N40:O40) -> 0.11134346 | Q40: =N40/$B$3 -> 0.047618923 | R40: =O40/$B$3 -> 0.15120869 | S40: =P40/$B$3 -> 0.19882761 | T40: =(T$56-T$38)/($A$56-$A$38) + T39 -> 0.035555556 | U40: =(U$56-U$38)/($A$56-$A$38) + U39 -> 0.10286667 | V40: =SUM(T40:U40) -> 0.13842222 | W40: =T40/$B$3 -> 0.063492063 | X40: =U40/$B$3 -> 0.18369048 | Y40: =V40/$B$3 -> 0.24718254 | Z40: =(Z$56-Z$38)/($A$56-$A$38) + Z39 -> 0.030555556 | AA40: =(AA$56-AA$38)/($A$56-$A$38) + AA39 -> 0.082866667 | AB40: =SUM(Z40:AA40) -> 0.11342222 | AC40: =Z40/$B$3 -> 0.054563492 | AD40: =AA40/$B$3 -> 0.14797619 | AE40: =AB40/$B$3 -> 0.20253968 | AF40: =1/AD40 -> 6.7578439 | AG40: =1/AE40 -> 4.9373041
A41: 2045 | B41: =FORECAST($A41, $B$6:$B$15, $A$6:$A$15) + 0.002 -> 0.036728811 | C41: =FORECAST($A41, $C$6:$C$15, $A$6:$A$15) + 0.001 -> 0.078190243 | D41: =SUM(B41:C41) -> 0.11491905 | E41: =B41/$B$3 -> 0.065587162 | F41: =C41/$B$3 -> 0.13962543 | G41: =D41/$B$3 -> 0.2052126 | H41: =FORECAST($A41, $H$6:$H$15, $A$6:$A$15) + 0.002 -> 0.052121573 | I41: =FORECAST($A41, $I$6:$I$15, $A$6:$A$15) + 0.001 -> 0.097641527 | J41: =SUM(H41:I41) -> 0.1497631 | K41: =H41/$B$3 -> 0.093074238 | L41: =I41/$B$3 -> 0.17435987 | M41: =J41/$B$3 -> 0.26743411 | N41: =$B$15 -> 0.026666597 | O41: =FORECAST($A41, $C$10:$C$15, $A$10:$A$15) + 0.001 -> 0.086581475 | P41: =SUM(N41:O41) -> 0.11324807 | Q41: =N41/$B$3 -> 0.047618923 | R41: =O41/$B$3 -> 0.15460978 | S41: =P41/$B$3 -> 0.2022287 | T41: =(T$56-T$38)/($A$56-$A$38) + T40 -> 0.035833333 | U41: =(U$56-U$38)/($A$56-$A$38) + U40 -> 0.10453333 | V41: =SUM(T41:U41) -> 0.14036667 | W41: =T41/$B$3 -> 0.063988095 | X41: =U41/$B$3 -> 0.18666667 | Y41: =V41/$B$3 -> 0.25065476 | Z41: =(Z$56-Z$38)/($A$56-$A$38) + Z40 -> 0.030833333 | AA41: =(AA$56-AA$38)/($A$56-$A$38) + AA40 -> 0.084533333 | AB41: =SUM(Z41:AA41) -> 0.11536667 | AC41: =Z41/$B$3 -> 0.055059524 | AD41: =AA41/$B$3 -> 0.15095238 | AE41: =AB41/$B$3 -> 0.2060119 | AF41: =1/AD41 -> 6.6246057 | AG41: =1/AE41 -> 4.8540884
A42: 2046 | B42: =FORECAST($A42, $B$6:$B$15, $A$6:$A$15) + 0.002 -> 0.03708339 | C42: =FORECAST($A42, $C$6:$C$15, $A$6:$A$15) + 0.001 -> 0.079797778 | D42: =SUM(B42:C42) -> 0.11688117 | E42: =B42/$B$3 -> 0.066220339 | F42: =C42/$B$3 -> 0.14249603 | G42: =D42/$B$3 -> 0.20871637 | H42: =FORECAST($A42, $H$6:$H$15, $A$6:$A$15) + 0.002 -> 0.052923536 | I42: =FORECAST($A42, $I$6:$I$15, $A$6:$A$15) + 0.001 -> 0.099812865 | J42: =SUM(H42:I42) -> 0.1527364 | K42: =H42/$B$3 -> 0.094506314 | L42: =I42/$B$3 -> 0.17823726 | M42: =J42/$B$3 -> 0.27274357 | N42: =$B$15 -> 0.026666597 | O42: =FORECAST($A42, $C$10:$C$15, $A$10:$A$15) + 0.001 -> 0.088486083 | P42: =SUM(N42:O42) -> 0.11515268 | Q42: =N42/$B$3 -> 0.047618923 | R42: =O42/$B$3 -> 0.15801086 | S42: =P42/$B$3 -> 0.20562979 | T42: =(T$56-T$38)/($A$56-$A$38) + T41 -> 0.036111111 | U42: =(U$56-U$38)/($A$56-$A$38) + U41 -> 0.1062 | V42: =SUM(T42:U42) -> 0.14231111 | W42: =T42/$B$3 -> 0.064484127 | X42: =U42/$B$3 -> 0.18964286 | Y42: =V42/$B$3 -> 0.25412698 | Z42: =(Z$56-Z$38)/($A$56-$A$38) + Z41 -> 0.031111111 | AA42: =(AA$56-AA$38)/($A$56-$A$38) + AA41 -> 0.0862 | AB42: =SUM(Z42:AA42) -> 0.11731111 | AC42: =Z42/$B$3 -> 0.055555556 | AD42: =AA42/$B$3 -> 0.15392857 | AE42: =AB42/$B$3 -> 0.20948413 | AF42: =1/AD42 -> 6.4965197 | AG42: =1/AE42 -> 4.7736314
A43: 2047 | B43: =FORECAST($A43, $B$6:$B$15, $A$6:$A$15) + 0.002 -> 0.037437969 | C43: =FORECAST($A43, $C$6:$C$15, $A$6:$A$15) + 0.001 -> 0.081405312 | D43: =SUM(B43:C43) -> 0.11884328 | E43: =B43/$B$3 -> 0.066853516 | F43: =C43/$B$3 -> 0.14536663 | G43: =D43/$B$3 -> 0.21222015 | H43: =FORECAST($A43, $H$6:$H$15, $A$6:$A$15) + 0.002 -> 0.053725498 | I43: =FORECAST($A43, $I$6:$I$15, $A$6:$A$15) + 0.001 -> 0.1019842 | J43: =SUM(H43:I43) -> 0.1557097 | K43: =H43/$B$3 -> 0.095938389 | L43: =I43/$B$3 -> 0.18211465 | M43: =J43/$B$3 -> 0.27805304 | N43: =$B$15 -> 0.026666597 | O43: =FORECAST($A43, $C$10:$C$15, $A$10:$A$15) + 0.001 -> 0.090390691 | P43: =SUM(N43:O43) -> 0.11705729 | Q43: =N43/$B$3 -> 0.047618923 | R43: =O43/$B$3 -> 0.16141195 | S43: =P43/$B$3 -> 0.20903087 | T43: =(T$56-T$38)/($A$56-$A$38) + T42 -> 0.036388889 | U43: =(U$56-U$38)/($A$56-$A$38) + U42 -> 0.10786667 | V43: =SUM(T43:U43) -> 0.14425556 | W43: =T43/$B$3 -> 0.064980159 | X43: =U43/$B$3 -> 0.19261905 | Y43: =V43/$B$3 -> 0.25759921 | Z43: =(Z$56-Z$38)/($A$56-$A$38) + Z42 -> 0.031388889 | AA43: =(AA$56-AA$38)/($A$56-$A$38) + AA42 -> 0.087866667 | AB43: =SUM(Z43:AA43) -> 0.11925556 | AC43: =Z43/$B$3 -> 0.056051587 | AD43: =AA43/$B$3 -> 0.15690476 | AE43: =AB43/$B$3 -> 0.21295635 | AF43: =1/AD43 -> 6.3732929 | AG43: =1/AE43 -> 4.695798
A44: 2048 | B44: =FORECAST($A44, $B$6:$B$15, $A$6:$A$15) + 0.002 -> 0.037792548 | C44: =FORECAST($A44, $C$6:$C$15, $A$6:$A$15) + 0.001 -> 0.083012847 | D44: =SUM(B44:C44) -> 0.12080539 | E44: =B44/$B$3 -> 0.067486693 | F44: =C44/$B$3 -> 0.14823723 | G44: =D44/$B$3 -> 0.21572392 | H44: =FORECAST($A44, $H$6:$H$15, $A$6:$A$15) + 0.002 -> 0.05452746 | I44: =FORECAST($A44, $I$6:$I$15, $A$6:$A$15) + 0.001 -> 0.10415554 | J44: =SUM(H44:I44) -> 0.158683 | K44: =H44/$B$3 -> 0.097370465 | L44: =I44/$B$3 -> 0.18599204 | M44: =J44/$B$3 -> 0.2833625 | N44: =$B$15 -> 0.026666597 | O44: =FORECAST($A44, $C$10:$C$15, $A$10:$A$15) + 0.001 -> 0.092295299 | P44: =SUM(N44:O44) -> 0.1189619 | Q44: =N44/$B$3 -> 0.047618923 | R44: =O44/$B$3 -> 0.16481303 | S44: =P44/$B$3 -> 0.21243196 | T44: =(T$56-T$38)/($A$56-$A$38) + T43 -> 0.036666667 | U44: =(U$56-U$38)/($A$56-$A$38) + U43 -> 0.10953333 | V44: =SUM(T44:U44) -> 0.1462 | W44: =T44/$B$3 -> 0.06547619 | X44: =U44/$B$3 -> 0.19559524 | Y44: =V44/$B$3 -> 0.26107143 | Z44: =(Z$56-Z$38)/($A$56-$A$38) + Z43 -> 0.031666667 | AA44: =(AA$56-AA$38)/($A$56-$A$38) + AA43 -> 0.089533333 | AB44: =SUM(Z44:AA44) -> 0.1212 | AC44: =Z44/$B$3 -> 0.056547619 | AD44: =AA44/$B$3 -> 0.15988095 | AE44: =AB44/$B$3 -> 0.21642857 | AF44: =1/AD44 -> 6.2546538 | AG44: =1/AE44 -> 4.620462
A45: 2049 | B45: =FORECAST($A45, $B$6:$B$15, $A$6:$A$15) + 0.002 -> 0.038147127 | C45: =FORECAST($A45, $C$6:$C$15, $A$6:$A$15) + 0.001 -> 0.084620381 | D45: =SUM(B45:C45) -> 0.12276751 | E45: =B45/$B$3 -> 0.06811987 | F45: =C45/$B$3 -> 0.15110782 | G45: =D45/$B$3 -> 0.21922769 | H45: =FORECAST($A45, $H$6:$H$15, $A$6:$A$15) + 0.002 -> 0.055329423 | I45: =FORECAST($A45, $I$6:$I$15, $A$6:$A$15) + 0.001 -> 0.10632688 | J45: =SUM(H45:I45) -> 0.1616563 | K45: =H45/$B$3 -> 0.098802541 | L45: =I45/$B$3 -> 0.18986943 | M45: =J45/$B$3 -> 0.28867197 | N45: =$B$15 -> 0.026666597 | O45: =FORECAST($A45, $C$10:$C$15, $A$10:$A$15) + 0.001 -> 0.094199907 | P45: =SUM(N45:O45) -> 0.1208665 | Q45: =N45/$B$3 -> 0.047618923 | R45: =O45/$B$3 -> 0.16821412 | S45: =P45/$B$3 -> 0.21583304 | T45: =(T$56-T$38)/($A$56-$A$38) + T44 -> 0.036944444 | U45: =(U$56-U$38)/($A$56-$A$38) + U44 -> 0.1112 | V45: =SUM(T45:U45) -> 0.14814444 | W45: =T45/$B$3 -> 0.065972222 | X45: =U45/$B$3 -> 0.19857143 | Y45: =V45/$B$3 -> 0.26454365 | Z45: =(Z$56-Z$38)/($A$56-$A$38) + Z44 -> 0.031944444 | AA45: =(AA$56-AA$38)/($A$56-$A$38) + AA44 -> 0.0912 | AB45: =SUM(Z45:AA45) -> 0.12314444 | AC45: =Z45/$B$3 -> 0.057043651 | AD45: =AA45/$B$3 -> 0.16285714 | AE45: =AB45/$B$3 -> 0.21990079 | AF45: =1/AD45 -> 6.1403509 | AG45: =1/AE45 -> 4.5475052
A46: 2050 | B46: =FORECAST($A46, $B$6:$B$15, $A$6:$A$15) + 0.002 -> 0.038501706 | C46: =FORECAST($A46, $C$6:$C$15, $A$6:$A$15) + 0.001 -> 0.086227915 | D46: =SUM(B46:C46) -> 0.12472962 | E46: =B46/$B$3 -> 0.068753047 | F46: =C46/$B$3 -> 0.15397842 | G46: =D46/$B$3 -> 0.22273147 | H46: =FORECAST($A46, $H$6:$H$15, $A$6:$A$15) + 0.002 -> 0.056131385 | I46: =FORECAST($A46, $I$6:$I$15, $A$6:$A$15) + 0.001 -> 0.10849822 | J46: =SUM(H46:I46) -> 0.1646296 | K46: =H46/$B$3 -> 0.10023462 | L46: =I46/$B$3 -> 0.19374682 | M46: =J46/$B$3 -> 0.29398144 | N46: =$B$15 -> 0.026666597 | O46: =FORECAST($A46, $C$10:$C$15, $A$10:$A$15) + 0.001 -> 0.096104515 | P46: =SUM(N46:O46) -> 0.12277111 | Q46: =N46/$B$3 -> 0.047618923 | R46: =O46/$B$3 -> 0.1716152 | S46: =P46/$B$3 -> 0.21923413 | T46: =(T$56-T$38)/($A$56-$A$38) + T45 -> 0.037222222 | U46: =(U$56-U$38)/($A$56-$A$38) + U45 -> 0.11286667 | V46: =SUM(T46:U46) -> 0.15008889 | W46: =T46/$B$3 -> 0.066468254 | X46: =U46/$B$3 -> 0.20154762 | Y46: =V46/$B$3 -> 0.26801587 | Z46: =(Z$56-Z$38)/($A$56-$A$38) + Z45 -> 0.032222222 | AA46: =(AA$56-AA$38)/($A$56-$A$38) + AA45 -> 0.092866667 | AB46: =SUM(Z46:AA46) -> 0.12508889 | AC46: =Z46/$B$3 -> 0.057539683 | AD46: =AA46/$B$3 -> 0.16583333 | AE46: =AB46/$B$3 -> 0.22337302 | AF46: =1/AD46 -> 6.0301508 | AG46: =1/AE46 -> 4.4768165
A47: 2051 | B47: =FORECAST($A47, $B$6:$B$15, $A$6:$A$15) + 0.002 -> 0.038856286 | C47: =FORECAST($A47, $C$6:$C$15, $A$6:$A$15) + 0.001 -> 0.08783545 | D47: =SUM(B47:C47) -> 0.12669174 | E47: =B47/$B$3 -> 0.069386224 | F47: =C47/$B$3 -> 0.15684902 | G47: =D47/$B$3 -> 0.22623524 | H47: =FORECAST($A47, $H$6:$H$15, $A$6:$A$15) + 0.002 -> 0.056933347 | I47: =FORECAST($A47, $I$6:$I$15, $A$6:$A$15) + 0.001 -> 0.11066956 | J47: =SUM(H47:I47) -> 0.16760291 | K47: =H47/$B$3 -> 0.10166669 | L47: =I47/$B$3 -> 0.19762421 | M47: =J47/$B$3 -> 0.2992909 | N47: =$B$15 -> 0.026666597 | O47: =FORECAST($A47, $C$10:$C$15, $A$10:$A$15) + 0.001 -> 0.098009122 | P47: =SUM(N47:O47) -> 0.12467572 | Q47: =N47/$B$3 -> 0.047618923 | R47: =O47/$B$3 -> 0.17501629 | S47: =P47/$B$3 -> 0.22263521 | T47: =(T$56-T$38)/($A$56-$A$38) + T46 -> 0.0375 | U47: =(U$56-U$38)/($A$56-$A$38) + U46 -> 0.11453333 | V47: =SUM(T47:U47) -> 0.15203333 | W47: =T47/$B$3 -> 0.066964286 | X47: =U47/$B$3 -> 0.20452381 | Y47: =V47/$B$3 -> 0.2714881 | Z47: =(Z$56-Z$38)/($A$56-$A$38) + Z46 -> 0.0325 | AA47: =(AA$56-AA$38)/($A$56-$A$38) + AA46 -> 0.094533333 | AB47: =SUM(Z47:AA47) -> 0.12703333 | AC47: =Z47/$B$3 -> 0.058035714 | AD47: =AA47/$B$3 -> 0.16880952 | AE47: =AB47/$B$3 -> 0.22684524 | AF47: =1/AD47 -> 5.9238364 | AG47: =1/AE47 -> 4.4082918
A48: 2052 | B48: =FORECAST($A48, $B$6:$B$15, $A$6:$A$15) + 0.002 -> 0.039210865 | C48: =FORECAST($A48, $C$6:$C$15, $A$6:$A$15) + 0.001 -> 0.089442984 | D48: =SUM(B48:C48) -> 0.12865385 | E48: =B48/$B$3 -> 0.070019401 | F48: =C48/$B$3 -> 0.15971961 | G48: =D48/$B$3 -> 0.22973902 | H48: =FORECAST($A48, $H$6:$H$15, $A$6:$A$15) + 0.002 -> 0.05773531 | I48: =FORECAST($A48, $I$6:$I$15, $A$6:$A$15) + 0.001 -> 0.1128409 | J48: =SUM(H48:I48) -> 0.17057621 | K48: =H48/$B$3 -> 0.10309877 | L48: =I48/$B$3 -> 0.2015016 | M48: =J48/$B$3 -> 0.30460037 | N48: =$B$15 -> 0.026666597 | O48: =FORECAST($A48, $C$10:$C$15, $A$10:$A$15) + 0.001 -> 0.09991373 | P48: =SUM(N48:O48) -> 0.12658033 | Q48: =N48/$B$3 -> 0.047618923 | R48: =O48/$B$3 -> 0.17841738 | S48: =P48/$B$3 -> 0.2260363 | T48: =(T$56-T$38)/($A$56-$A$38) + T47 -> 0.037777778 | U48: =(U$56-U$38)/($A$56-$A$38) + U47 -> 0.1162 | V48: =SUM(T48:U48) -> 0.15397778 | W48: =T48/$B$3 -> 0.067460317 | X48: =U48/$B$3 -> 0.2075 | Y48: =V48/$B$3 -> 0.27496032 | Z48: =(Z$56-Z$38)/($A$56-$A$38) + Z47 -> 0.032777778 | AA48: =(AA$56-AA$38)/($A$56-$A$38) + AA47 -> 0.0962 | AB48: =SUM(Z48:AA48) -> 0.12897778 | AC48: =Z48/$B$3 -> 0.058531746 | AD48: =AA48/$B$3 -> 0.17178571 | AE48: =AB48/$B$3 -> 0.23031746 | AF48: =1/AD48 -> 5.8212058 | AG48: =1/AE48 -> 4.3418332
A49: 2053 | B49: =FORECAST($A49, $B$6:$B$15, $A$6:$A$15) + 0.002 -> 0.039565444 | C49: =FORECAST($A49, $C$6:$C$15, $A$6:$A$15) + 0.001 -> 0.091050519 | D49: =SUM(B49:C49) -> 0.13061596 | E49: =B49/$B$3 -> 0.070652578 | F49: =C49/$B$3 -> 0.16259021 | G49: =D49/$B$3 -> 0.23324279 | H49: =FORECAST($A49, $H$6:$H$15, $A$6:$A$15) + 0.002 -> 0.058537272 | I49: =FORECAST($A49, $I$6:$I$15, $A$6:$A$15) + 0.001 -> 0.11501224 | J49: =SUM(H49:I49) -> 0.17354951 | K49: =H49/$B$3 -> 0.10453084 | L49: =I49/$B$3 -> 0.20537899 | M49: =J49/$B$3 -> 0.30990983 | N49: =$B$15 -> 0.026666597 | O49: =FORECAST($A49, $C$10:$C$15, $A$10:$A$15) + 0.001 -> 0.10181834 | P49: =SUM(N49:O49) -> 0.12848494 | Q49: =N49/$B$3 -> 0.047618923 | R49: =O49/$B$3 -> 0.18181846 | S49: =P49/$B$3 -> 0.22943738 | T49: =(T$56-T$38)/($A$56-$A$38) + T48 -> 0.038055556 | U49: =(U$56-U$38)/($A$56-$A$38) + U48 -> 0.11786667 | V49: =SUM(T49:U49) -> 0.15592222 | W49: =T49/$B$3 -> 0.067956349 | X49: =U49/$B$3 -> 0.21047619 | Y49: =V49/$B$3 -> 0.27843254 | Z49: =(Z$56-Z$38)/($A$56-$A$38) + Z48 -> 0.033055556 | AA49: =(AA$56-AA$38)/($A$56-$A$38) + AA48 -> 0.097866667 | AB49: =SUM(Z49:AA49) -> 0.13092222 | AC49: =Z49/$B$3 -> 0.059027778 | AD49: =AA49/$B$3 -> 0.1747619 | AE49: =AB49/$B$3 -> 0.23378968 | AF49: =1/AD49 -> 5.7220708 | AG49: =1/AE49 -> 4.2773487
A50: 2054 | B50: =FORECAST($A50, $B$6:$B$15, $A$6:$A$15) + 0.002 -> 0.039920023 | C50: =FORECAST($A50, $C$6:$C$15, $A$6:$A$15) + 0.001 -> 0.092658053 | D50: =SUM(B50:C50) -> 0.13257808 | E50: =B50/$B$3 -> 0.071285755 | F50: =C50/$B$3 -> 0.16546081 | G50: =D50/$B$3 -> 0.23674656 | H50: =FORECAST($A50, $H$6:$H$15, $A$6:$A$15) + 0.002 -> 0.059339234 | I50: =FORECAST($A50, $I$6:$I$15, $A$6:$A$15) + 0.001 -> 0.11718357 | J50: =SUM(H50:I50) -> 0.17652281 | K50: =H50/$B$3 -> 0.10596292 | L50: =I50/$B$3 -> 0.20925638 | M50: =J50/$B$3 -> 0.3152193 | N50: =$B$15 -> 0.026666597 | O50: =FORECAST($A50, $C$10:$C$15, $A$10:$A$15) + 0.001 -> 0.10372295 | P50: =SUM(N50:O50) -> 0.13038954 | Q50: =N50/$B$3 -> 0.047618923 | R50: =O50/$B$3 -> 0.18521955 | S50: =P50/$B$3 -> 0.23283847 | T50: =(T$56-T$38)/($A$56-$A$38) + T49 -> 0.038333333 | U50: =(U$56-U$38)/($A$56-$A$38) + U49 -> 0.11953333 | V50: =SUM(T50:U50) -> 0.15786667 | W50: =T50/$B$3 -> 0.068452381 | X50: =U50/$B$3 -> 0.21345238 | Y50: =V50/$B$3 -> 0.28190476 | Z50: =(Z$56-Z$38)/($A$56-$A$38) + Z49 -> 0.033333333 | AA50: =(AA$56-AA$38)/($A$56-$A$38) + AA49 -> 0.099533333 | AB50: =SUM(Z50:AA50) -> 0.13286667 | AC50: =Z50/$B$3 -> 0.05952381 | AD50: =AA50/$B$3 -> 0.1777381 | AE50: =AB50/$B$3 -> 0.2372619 | AF50: =1/AD50 -> 5.6262559 | AG50: =1/AE50 -> 4.2147516
A51: 2055 | B51: =FORECAST($A51, $B$6:$B$15, $A$6:$A$15) + 0.002 -> 0.040274602 | C51: =FORECAST($A51, $C$6:$C$15, $A$6:$A$15) + 0.001 -> 0.094265588 | D51: =SUM(B51:C51) -> 0.13454019 | E51: =B51/$B$3 -> 0.071918932 | F51: =C51/$B$3 -> 0.16833141 | G51: =D51/$B$3 -> 0.24025034 | H51: =FORECAST($A51, $H$6:$H$15, $A$6:$A$15) + 0.002 -> 0.060141197 | I51: =FORECAST($A51, $I$6:$I$15, $A$6:$A$15) + 0.001 -> 0.11935491 | J51: =SUM(H51:I51) -> 0.17949611 | K51: =H51/$B$3 -> 0.10739499 | L51: =I51/$B$3 -> 0.21313377 | M51: =J51/$B$3 -> 0.32052877 | N51: =$B$15 -> 0.026666597 | O51: =FORECAST($A51, $C$10:$C$15, $A$10:$A$15) + 0.001 -> 0.10562755 | P51: =SUM(N51:O51) -> 0.13229415 | Q51: =N51/$B$3 -> 0.047618923 | R51: =O51/$B$3 -> 0.18862063 | S51: =P51/$B$3 -> 0.23623955 | T51: =(T$56-T$38)/($A$56-$A$38) + T50 -> 0.038611111 | U51: =(U$56-U$38)/($A$56-$A$38) + U50 -> 0.1212 | V51: =SUM(T51:U51) -> 0.15981111 | W51: =T51/$B$3 -> 0.068948413 | X51: =U51/$B$3 -> 0.21642857 | Y51: =V51/$B$3 -> 0.28537698 | Z51: =(Z$56-Z$38)/($A$56-$A$38) + Z50 -> 0.033611111 | AA51: =(AA$56-AA$38)/($A$56-$A$38) + AA50 -> 0.1012 | AB51: =SUM(Z51:AA51) -> 0.13481111 | AC51: =Z51/$B$3 -> 0.060019841 | AD51: =AA51/$B$3 -> 0.18071429 | AE51: =AB51/$B$3 -> 0.24073413 | AF51: =1/AD51 -> 5.5335968 | AG51: =1/AE51 -> 4.1539603
... A55: 2059 | B55: =FORECAST($A55, $B$6:$B$15, $A$6:$A$15) + 0.002 -> 0.041692918 | C55: =FORECAST($A55, $C$6:$C$15, $A$6:$A$15) + 0.001 -> 0.10069573 | D55: =SUM(B55:C55) -> 0.14238864 | E55: =B55/$B$3 -> 0.07445164 | F55: =C55/$B$3 -> 0.1798138 | G55: =D55/$B$3 -> 0.25426544 | H55: =FORECAST($A55, $H$6:$H$15, $A$6:$A$15) + 0.002 -> 0.063349046 | I55: =FORECAST($A55, $I$6:$I$15, $A$6:$A$15) + 0.001 -> 0.12804027 | J55: =SUM(H55:I55) -> 0.19138931 | K55: =H55/$B$3 -> 0.1131233 | L55: =I55/$B$3 -> 0.22864333 | M55: =J55/$B$3 -> 0.34176663 | N55: =$B$15 -> 0.026666597 | O55: =FORECAST($A55, $C$10:$C$15, $A$10:$A$15) + 0.001 -> 0.11324599 | P55: =SUM(N55:O55) -> 0.13991258 | Q55: =N55/$B$3 -> 0.047618923 | R55: =O55/$B$3 -> 0.20222497 | S55: =P55/$B$3 -> 0.2498439 | T55: =(T$56-T$38)/($A$56-$A$38) + T54 -> 0.039722222 | U55: =(U$56-U$38)/($A$56-$A$38) + U54 -> 0.12786667 | V55: =SUM(T55:U55) -> 0.16758889 | W55: =T55/$B$3 -> 0.07093254 | X55: =U55/$B$3 -> 0.22833333 | Y55: =V55/$B$3 -> 0.29926587 | Z55: =(Z$56-Z$38)/($A$56-$A$38) + Z54 -> 0.034722222 | AA55: =(AA$56-AA$38)/($A$56-$A$38) + AA54 -> 0.10786667 | AB55: =SUM(Z55:AA55) -> 0.14258889 | AC55: =Z55/$B$3 -> 0.062003968 | AD55: =AA55/$B$3 -> 0.19261905 | AE55: =AB55/$B$3 -> 0.25462302 | AF55: =1/AD55 -> 5.1915946 | AG55: =1/AE55 -> 3.9273747
A56: 2060 | B56: =FORECAST($A56, $B$6:$B$15, $A$6:$A$15) + 0.002 -> 0.042047497 | C56: =FORECAST($A56, $C$6:$C$15, $A$6:$A$15) + 0.001 -> 0.10230326 | D56: =SUM(B56:C56) -> 0.14435076 | E56: =B56/$B$3 -> 0.075084817 | F56: =C56/$B$3 -> 0.18268439 | G56: =D56/$B$3 -> 0.25776921 | H56: =FORECAST($A56, $H$6:$H$15, $A$6:$A$15) + 0.002 -> 0.064151008 | I56: =FORECAST($A56, $I$6:$I$15, $A$6:$A$15) + 0.001 -> 0.13021161 | J56: =SUM(H56:I56) -> 0.19436261 | K56: =H56/$B$3 -> 0.11455537 | L56: =I56/$B$3 -> 0.23252072 | M56: =J56/$B$3 -> 0.3470761 | N56: =$B$15 -> 0.026666597 | O56: =FORECAST($A56, $C$10:$C$15, $A$10:$A$15) + 0.001 -> 0.11515059 | P56: =SUM(N56:O56) -> 0.14181719 | Q56: =N56/$B$3 -> 0.047618923 | R56: =O56/$B$3 -> 0.20562606 | S56: =P56/$B$3 -> 0.25324498 | T56: 0.04 | U56: 0.13 | V56: =SUM(T56:U56) -> 0.17 | W56: =T56/$B$3 -> 0.071428571 | X56: =U56/$B$3 -> 0.23214286 | Y56: =V56/$B$3 -> 0.30357143 | Z56: 0.035 | AA56: 0.11 | AB56: =SUM(Z56:AA56) -> 0.145 | AC56: =Z56/$B$3 -> 0.0625 | AD56: =AA56/$B$3 -> 0.19642857 | AE56: =AB56/$B$3 -> 0.25892857 | AF56: =1/AD56 -> 5.0909091 | AG56: =1/AE56 -> 3.862069
A59: Notes
A60: • 69% of U.S. employees worked from home at the peak of the pandemic [State of the Remote Workforce, Global Workplace Analytics and OwlLabs, 2020 – based on 2,500 survey responses from full-time workers]
A61: • 56% of employees have a job where at least some of what they do could be done remotely [Global Workplace Analytics]
A62: https://globalworkplaceanalytics.com/telecommuting-statistics

Sheet WAH_byCounty
B1: Share of Work At Home Charts by County | BK1: Share of Work At Home Charts | CI1: Calculate Share: Work At Home | CV1: Calculate Share: Telecommute | DI1: Calculate Share: Home-Based-Job | DV1: Calculate Telecommute Workers | EI1: Calculate Home-Based-Job Workers | EW1: Extract Worker Tables: Total Workers, Worked at Home, Self-employed in own incorporated & not incorporated business
CP4: Work-At-Home Share of Total Workers | DC4: Telecommute Worker Share of Total Workers | DP4: Home-Based-Job Worker Share of Total Workers | DW4: Telecommute Job Workers | EC4: Workers | EJ4: Home-Based Job Workers | EP4: Workers | EW4: 100 | EX4: =VLOOKUP(EW4, lu_WrkType, 2, FALSE) -> Total Workers | FD4: Workers | FJ4: 700 | FK4: =VLOOKUP(FJ4, lu_WrkType, 2, FALSE) -> Worked at home | FQ4: Workers | FW4: 712 | FX4: =VLOOKUP(FW4, lu_WrkType, 2, FALSE) -> Self-employed in own incorporated business workers | GD4: Workers | GJ4: 760 | GK4: =VLOOKUP(GJ4, lu_WrkType, 2, FALSE) -> Self-employed in own not incorporated business workers | GQ4: Workers
AX5: 101 | AY5: =VLOOKUP(AX5, lu_CoName, 2, FALSE) -> Wasatch Front | DW5: (Non-Self-Employed Workers Who Work At Home) | EJ5: (Self-Employed Workers Who Work At Home)
AZ6: 2010 | BA6: 2011 | BB6: 2012 | BC6: 2013 | BD6: 2014 | BE6: 2015 | BF6: 2016 | BG6: 2017 | BH6: 2018 | BI6: 2019 | CK6: 2010 | CL6: 2011 | CM6: 2012 | CN6: 2013 | CO6: 2014 | CP6: 2015 | CQ6: 2016 | CR6: 2017 | CS6: 2018 | CT6: 2019 | CX6: 2010 | CY6: 2011 | CZ6: 2012 | DA6: 2013 | DB6: 2014 | DC6: 2015 | DD6: 2016 | DE6: 2017 | DF6: 2018 | DG6: 2019 | DK6: 2010 | DL6: 2011 | DM6: 2012 | DN6: 2013 | DO6: 2014 | DP6: 2015 | DQ6: 2016 | DR6: 2017 | DS6: 2018 | DT6: 2019 | DX6: 2010 | DY6: 2011 | DZ6: 2012 | EA6: 2013 | EB6: 2014 | EC6: 2015 | ED6: 2016 | EE6: 2017 | EF6: 2018 | EG6: 2019 | EK6: 2010 | EL6: 2011 | EM6: 2012 | EN6: 2013 | EO6: 2014 | EP6: 2015 | EQ6: 2016 | ER6: 2017 | ES6: 2018 | ET6: 2019 | EY6: 2010 | EZ6: 2011 | FA6: 2012 | FB6: 2013 | FC6: 2014 | FD6: 2015 | FE6: 2016 | FF6: 2017 | FG6: 2018 | FH6: 2019 | FL6: 2010 | FM6: 2011 | FN6: 2012 | FO6: 2013 | FP6: 2014 | FQ6: 2015 | FR6: 2016 | FS6: 2017 | FT6: 2018 | FU6: 2019 | FY6: 2010 | FZ6: 2011 | GA6: 2012 | GB6: 2013 | GC6: 2014 | GD6: 2015 | GE6: 2016 | GF6: 2017 | GG6: 2018 | GH6: 2019 | GL6: 2010 | GM6: 2011 | GN6: 2012 | GO6: 2013 | GP6: 2014 | GQ6: 2015 | GR6: 2016 | GS6: 2017 | GT6: 2018 | GU6: 2019
AY7: Home-Based-Job | AZ7: =INDEX($DK$7:$DT$13, MATCH(AY5, $DJ$7:$DJ$13,0), MATCH(AZ$6, $DK$6:$DT$6, 0)) -> 0.024156393 | BA7: =INDEX($DK$7:$DT$13, MATCH(AY5, $DJ$7:$DJ$13,0), MATCH(BA$6, $DK$6:$DT$6, 0)) -> 0.023616541 | BB7: =INDEX($DK$7:$DT$13, MATCH(AY5, $DJ$7:$DJ$13,0), MATCH(BB$6, $DK$6:$DT$6, 0)) -> 0.022667213 | BC7: =INDEX($DK$7:$DT$13, MATCH(AY5, $DJ$7:$DJ$13,0), MATCH(BC$6, $DK$6:$DT$6, 0)) -> 0.022171769 | BD7: =INDEX($DK$7:$DT$13, MATCH(AY5, $DJ$7:$DJ$13,0), MATCH(BD$6, $DK$6:$DT$6, 0)) -> 0.022228968 | BE7: =INDEX($DK$7:$DT$13, MATCH(AY5, $DJ$7:$DJ$13,0), MATCH(BE$6, $DK$6:$DT$6, 0)) -> 0.022692701 | BF7: =INDEX($DK$7:$DT$13, MATCH(AY5, $DJ$7:$DJ$13,0), MATCH(BF$6, $DK$6:$DT$6, 0)) -> 0.023436385 | BG7: =INDEX($DK$7:$DT$13, MATCH(AY5, $DJ$7:$DJ$13,0), MATCH(BG$6, $DK$6:$DT$6, 0)) -> 0.025113206 | BH7: =INDEX($DK$7:$DT$13, MATCH(AY5, $DJ$7:$DJ$13,0), MATCH(BH$6, $DK$6:$DT$6, 0)) -> 0.026391708 | BI7: =INDEX($DK$7:$DT$13, MATCH(AY5, $DJ$7:$DJ$13,0), MATCH(BI$6, $DK$6:$DT$6, 0)) -> 0.026666597 | CI7: 101 | CJ7: =VLOOKUP(CI7, lu_CoName, 2, FALSE) -> Wasatch Front | CK7: =CX7 + DK7 -> 0.046040703 | CL7: =CY7 + DL7 -> 0.046933978 | CM7: =CZ7 + DM7 -> 0.045984966 | CN7: =DA7 + DN7 -> 0.047455799 | CO7: =DB7 + DO7 -> 0.048848668 | CP7: =DC7 + DP7 -> 0.051658859 | CQ7: =DD7 + DQ7 -> 0.053139977 | CR7: =DE7 + DR7 -> 0.057194228 | ... CT7: =DG7 + DT7 -> 0.06316136 | CV7: =$CI7 -> 101 | CW7: =$CJ7 -> Wasatch Front | CX7: =IFERROR(DX7/EY7, 0) -> 0.02188431 | CY7: =IFERROR(DY7/EZ7, 0) -> 0.023317437 | CZ7: =IFERROR(DZ7/FA7, 0) -> 0.023317753 | DA7: =IFERROR(EA7/FB7, 0) -> 0.02528403 | DB7: =IFERROR(EB7/FC7, 0) -> 0.0266197 | DC7: =IFERROR(EC7/FD7, 0) -> 0.028966157 | DD7: =IFERROR(ED7/FE7, 0) -> 0.029703592 | DE7: =IFERROR(EE7/FF7, 0) -> 0.032081021 | ... DG7: =IFERROR(EG7/FH7, 0) -> 0.036494763 | DI7: =$CI7 -> 101 | DJ7: =$CJ7 -> Wasatch Front | DK7: =IFERROR(EK7/EY7, 0) -> 0.024156393 | DL7: =IFERROR(EL7/EZ7, 0) -> 0.023616541 | DM7: =IFERROR(EM7/FA7, 0) -> 0.022667213 | DN7: =IFERROR(EN7/FB7, 0) -> 0.022171769 | DO7: =IFERROR(EO7/FC7, 0) -> 0.022228968 | DP7: =IFERROR(EP7/FD7, 0) -> 0.022692701 | DQ7: =IFERROR(EQ7/FE7, 0) -> 0.023436385 | DR7: =IFERROR(ER7/FF7, 0) -> 0.025113206 | ... DT7: =IFERROR(ET7/FH7, 0) -> 0.026666597 | DV7: =$CI7 -> 101 | DW7: =$CJ7 -> Wasatch Front | DX7: =SUM(DX8:DX11) -> 20458 | DY7: =SUM(DY8:DY11) -> 22140 | DZ7: =SUM(DZ8:DZ11) -> 22474 | EA7: =SUM(EA8:EA11) -> 24567 | EB7: =SUM(EB8:EB11) -> 26397 | EC7: =SUM(EC8:EC11) -> 29592 | ED7: =SUM(ED8:ED11) -> 31224 | EE7: =SUM(EE8:EE11) -> 34651 | ... EG7: =SUM(EG8:EG11) -> 41793 | EI7: =$CI7 -> 101 | EJ7: =$CJ7 -> Wasatch Front | EK7: =SUM(EK8:EK11) -> 22582 | EL7: =SUM(EL8:EL11) -> 22424 | EM7: =SUM(EM8:EM11) -> 21847 | EN7: =SUM(EN8:EN11) -> 21543 | EO7: =SUM(EO8:EO11) -> 22043 | EP7: =SUM(EP8:EP11) -> 23183 | EQ7: =SUM(EQ8:EQ11) -> 24636 | ER7: =SUM(ER8:ER11) -> 27125 | ... ET7: =SUM(ET8:ET11) -> 30538 | EW7: =$CI7 -> 101 | EX7: =$CJ7 -> Wasatch Front | EY7: =SUM(EY8:EY11) -> 934825 | EZ7: =SUM(EZ8:EZ11) -> 949504 | FA7: =SUM(FA8:FA11) -> 963815 | FB7: =SUM(FB8:FB11) -> 971641 | FC7: =SUM(FC8:FC11) -> 991634 | FD7: =SUM(FD8:FD11) -> 1021606 | FE7: =SUM(FE8:FE11) -> 1051186 | FF7: =SUM(FF8:FF11) -> 1080109 | ... FH7: =SUM(FH8:FH11) -> 1145178 | FJ7: =$CI7 -> 101 | FK7: =$CJ7 -> Wasatch Front | FL7: =SUM(FL8:FL11) -> 43040 | FM7: =SUM(FM8:FM11) -> 44564 | FN7: =SUM(FN8:FN11) -> 44321 | FO7: =SUM(FO8:FO11) -> 46110 | FP7: =SUM(FP8:FP11) -> 48440 | FQ7: =SUM(FQ8:FQ11) -> 52775 | FR7: =SUM(FR8:FR11) -> 55860 | FS7: =SUM(FS8:FS11) -> 61776 | ... FU7: =SUM(FU8:FU11) -> 72331 | FW7: =$CI7 -> 101 | FX7: =$CJ7 -> Wasatch Front | FY7: =SUM(FY8:FY11) -> 6818 | FZ7: =SUM(FZ8:FZ11) -> 6858 | GA7: =SUM(GA8:GA11) -> 6765 | GB7: =SUM(GB8:GB11) -> 6729 | GC7: =SUM(GC8:GC11) -> 7273 | GD7: =SUM(GD8:GD11) -> 8231 | GE7: =SUM(GE8:GE11) -> 8891 | GF7: =SUM(GF8:GF11) -> 10376 | ... GH7: =SUM(GH8:GH11) -> 11780 | GJ7: =$CI7 -> 101 | GK7: =$CJ7 -> Wasatch Front | GL7: =SUM(GL8:GL11) -> 15764 | GM7: =SUM(GM8:GM11) -> 15566 | GN7: =SUM(GN8:GN11) -> 15082 | GO7: =SUM(GO8:GO11) -> 14814 | GP7: =SUM(GP8:GP11) -> 14770 | GQ7: =SUM(GQ8:GQ11) -> 14952 | GR7: =SUM(GR8:GR11) -> 15745 | GS7: =SUM(GS8:GS11) -> 16749 | ... GU7: =SUM(GU8:GU11) -> 18758
AY8: Telecommute | AZ8: =INDEX($CX$7:$DG$13, MATCH(AY5, $CW$7:$CW$13,0), MATCH(AZ$6, $CX$6:$DG$6, 0)) -> 0.02188431 | BA8: =INDEX($CX$7:$DG$13, MATCH(AY5, $CW$7:$CW$13,0), MATCH(BA$6, $CX$6:$DG$6, 0)) -> 0.023317437 | BB8: =INDEX($CX$7:$DG$13, MATCH(AY5, $CW$7:$CW$13,0), MATCH(BB$6, $CX$6:$DG$6, 0)) -> 0.023317753 | BC8: =INDEX($CX$7:$DG$13, MATCH(AY5, $CW$7:$CW$13,0), MATCH(BC$6, $CX$6:$DG$6, 0)) -> 0.02528403 | BD8: =INDEX($CX$7:$DG$13, MATCH(AY5, $CW$7:$CW$13,0), MATCH(BD$6, $CX$6:$DG$6, 0)) -> 0.0266197 | BE8: =INDEX($CX$7:$DG$13, MATCH(AY5, $CW$7:$CW$13,0), MATCH(BE$6, $CX$6:$DG$6, 0)) -> 0.028966157 | BF8: =INDEX($CX$7:$DG$13, MATCH(AY5, $CW$7:$CW$13,0), MATCH(BF$6, $CX$6:$DG$6, 0)) -> 0.029703592 | BG8: =INDEX($CX$7:$DG$13, MATCH(AY5, $CW$7:$CW$13,0), MATCH(BG$6, $CX$6:$DG$6, 0)) -> 0.032081021 | BH8: =INDEX($CX$7:$DG$13, MATCH(AY5, $CW$7:$CW$13,0), MATCH(BH$6, $CX$6:$DG$6, 0)) -> 0.033935668 | BI8: =INDEX($CX$7:$DG$13, MATCH(AY5, $CW$7:$CW$13,0), MATCH(BI$6, $CX$6:$DG$6, 0)) -> 0.036494763 | CI8: 57 | CJ8: =VLOOKUP(CI8, lu_CoName, 2, FALSE) -> Weber | CK8: =CX8 + DK8 -> 0.031489478 | CL8: =CY8 + DL8 -> 0.03423657 | CM8: =CZ8 + DM8 -> 0.032300393 | CN8: =DA8 + DN8 -> 0.033006032 | CO8: =DB8 + DO8 -> 0.035722947 | CP8: =DC8 + DP8 -> 0.041130466 | CQ8: =DD8 + DQ8 -> 0.041244982 | CR8: =DE8 + DR8 -> 0.046252189 | ... CT8: =DG8 + DT8 -> 0.054330715 | CV8: =$CI8 -> 57 | CW8: =$CJ8 -> Weber | CX8: =IFERROR(DX8/EY8, 0) -> 0.014684716 | CY8: =IFERROR(DY8/EZ8, 0) -> 0.016552351 | CZ8: =IFERROR(DZ8/FA8, 0) -> 0.016069374 | DA8: =IFERROR(EA8/FB8, 0) -> 0.017601949 | DB8: =IFERROR(EB8/FC8, 0) -> 0.018449083 | DC8: =IFERROR(EC8/FD8, 0) -> 0.022089778 | DD8: =IFERROR(ED8/FE8, 0) -> 0.022162555 | DE8: =IFERROR(EE8/FF8, 0) -> 0.024474606 | ... DG8: =IFERROR(EG8/FH8, 0) -> 0.031508848 | DI8: =$CI8 -> 57 | DJ8: =$CJ8 -> Weber | DK8: =IFERROR(EK8/EY8, 0) -> 0.016804761 | DL8: =IFERROR(EL8/EZ8, 0) -> 0.017684219 | DM8: =IFERROR(EM8/FA8, 0) -> 0.016231019 | DN8: =IFERROR(EN8/FB8, 0) -> 0.015404084 | DO8: =IFERROR(EO8/FC8, 0) -> 0.017273863 | DP8: =IFERROR(EP8/FD8, 0) -> 0.019040688 | DQ8: =IFERROR(EQ8/FE8, 0) -> 0.019082427 | DR8: =IFERROR(ER8/FF8, 0) -> 0.021777583 | ... DT8: =IFERROR(ET8/FH8, 0) -> 0.022821867 | DV8: =$CI8 -> 57 | DW8: =$CJ8 -> Weber | DX8: =DX45 -> 1510 | DY8: =DY45 -> 1711 | DZ8: =DZ45 -> 1690 | EA8: =EA45 -> 1850 | EB8: =EB45 -> 1978 | EC8: =EC45 -> 2398 | ED8: =ED45 -> 2468 | EE8: =EE45 -> 2795 | ... EG8: =EG45 -> 3823 | EI8: =$CI8 -> 57 | EJ8: =$CJ8 -> Weber | EK8: =EK45 -> 1728 | EL8: =EL45 -> 1828 | EM8: =EM45 -> 1707 | EN8: =EN45 -> 1619 | EO8: =EO45 -> 1852 | EP8: =EP45 -> 2067 | EQ8: =EQ45 -> 2125 | ER8: =ER45 -> 2487 | ... ET8: =ET45 -> 2769 | EW8: =$CI8 -> 57 | EX8: =$CJ8 -> Weber | EY8: =EY45 -> 102828 | EZ8: =EZ45 -> 103369 | FA8: =FA45 -> 105169 | FB8: =FB45 -> 105102 | FC8: =FC45 -> 107214 | FD8: =FD45 -> 108557 | FE8: =FE45 -> 111359 | FF8: =FF45 -> 114200 | ... FH8: =FH45 -> 121331 | FJ8: =$CI8 -> 57 | FK8: =$CJ8 -> Weber | FL8: =FL45 -> 3238 | FM8: =FM45 -> 3539 | FN8: =FN45 -> 3397 | FO8: =FO45 -> 3469 | FP8: =FP45 -> 3830 | FQ8: =FQ45 -> 4465 | FR8: =FR45 -> 4593 | FS8: =FS45 -> 5282 | ... FU8: =FU45 -> 6592 | FW8: =$CI8 -> 57 | FX8: =$CJ8 -> Weber | FY8: =FY45 -> 537 | FZ8: =FZ45 -> 582 | GA8: =GA45 -> 573 | GB8: =GB45 -> 534 | GC8: =GC45 -> 666 | GD8: =GD45 -> 846 | GE8: =GE45 -> 923 | GF8: =GF45 -> 1103 | ... GH8: =GH45 -> 1324 | GJ8: =$CI8 -> 57 | GK8: =$CJ8 -> Weber | GL8: =GL45 -> 1191 | GM8: =GM45 -> 1246 | GN8: =GN45 -> 1134 | GO8: =GO45 -> 1085 | GP8: =GP45 -> 1186 | GQ8: =GQ45 -> 1221 | GR8: =GR45 -> 1202 | GS8: =GS45 -> 1384 | ... GU8: =GU45 -> 1445
AY9: Total Work At Home | AZ9: =SUM(AZ7:AZ8) -> 0.046040703 | BA9: =SUM(BA7:BA8) -> 0.046933978 | BB9: =SUM(BB7:BB8) -> 0.045984966 | BC9: =SUM(BC7:BC8) -> 0.047455799 | BD9: =SUM(BD7:BD8) -> 0.048848668 | BE9: =SUM(BE7:BE8) -> 0.051658859 | BF9: =SUM(BF7:BF8) -> 0.053139977 | BG9: =SUM(BG7:BG8) -> 0.057194228 | ... BI9: =SUM(BI7:BI8) -> 0.06316136 | CI9: 11 | CJ9: =VLOOKUP(CI9, lu_CoName, 2, FALSE) -> Davis | CK9: =CX9 + DK9 -> 0.044575681 | CL9: =CY9 + DL9 -> 0.047153855 | CM9: =CZ9 + DM9 -> 0.045106261 | CN9: =DA9 + DN9 -> 0.047290962 | CO9: =DB9 + DO9 -> 0.049455062 | CP9: =DC9 + DP9 -> 0.052148088 | CQ9: =DD9 + DQ9 -> 0.05199921 | CR9: =DE9 + DR9 -> 0.055483498 | ... CT9: =DG9 + DT9 -> 0.058858596 | CV9: =$CI9 -> 11 | CW9: =$CJ9 -> Davis | CX9: =IFERROR(DX9/EY9, 0) -> 0.020632471 | CY9: =IFERROR(DY9/EZ9, 0) -> 0.025479704 | CZ9: =IFERROR(DZ9/FA9, 0) -> 0.023610364 | DA9: =IFERROR(EA9/FB9, 0) -> 0.025847373 | DB9: =IFERROR(EB9/FC9, 0) -> 0.028318695 | DC9: =IFERROR(EC9/FD9, 0) -> 0.031001316 | DD9: =IFERROR(ED9/FE9, 0) -> 0.03059087 | DE9: =IFERROR(EE9/FF9, 0) -> 0.034743804 | ... DG9: =IFERROR(EG9/FH9, 0) -> 0.036449019 | DI9: =$CI9 -> 11 | DJ9: =$CJ9 -> Davis | DK9: =IFERROR(EK9/EY9, 0) -> 0.02394321 | DL9: =IFERROR(EL9/EZ9, 0) -> 0.021674151 | DM9: =IFERROR(EM9/FA9, 0) -> 0.021495896 | DN9: =IFERROR(EN9/FB9, 0) -> 0.021443589 | DO9: =IFERROR(EO9/FC9, 0) -> 0.021136367 | DP9: =IFERROR(EP9/FD9, 0) -> 0.021146772 | DQ9: =IFERROR(EQ9/FE9, 0) -> 0.021408339 | DR9: =IFERROR(ER9/FF9, 0) -> 0.020739694 | ... DT9: =IFERROR(ET9/FH9, 0) -> 0.022409577 | DV9: =$CI9 -> 11 | DW9: =$CJ9 -> Davis | DX9: =DX22 -> 2767 | DY9: =DY22 -> 3495 | DZ9: =DZ22 -> 3294 | EA9: =EA22 -> 3639 | EB9: =EB22 -> 4069 | EC9: =EC22 -> 4593 | ED9: =ED22 -> 4644 | EE9: =EE22 -> 5411 | ... EG9: =EG22 -> 5992 | EI9: =$CI9 -> 11 | EJ9: =$CJ9 -> Davis | EK9: =EK22 -> 3211 | EL9: =EL22 -> 2973 | EM9: =EM22 -> 2999 | EN9: =EN22 -> 3019 | EO9: =EO22 -> 3037 | EP9: =EP22 -> 3133 | EQ9: =EQ22 -> 3250 | ER9: =ER22 -> 3230 | ... ET9: =ET22 -> 3684 | EW9: =$CI9 -> 11 | EX9: =$CJ9 -> Davis | EY9: =EY22 -> 134109 | EZ9: =EZ22 -> 137168 | FA9: =FA22 -> 139515 | FB9: =FB22 -> 140788 | FC9: =FC22 -> 143686 | FD9: =FD22 -> 148155 | FE9: =FE22 -> 151810 | FF9: =FF22 -> 155740 | ... FH9: =FH22 -> 164394 | FJ9: =$CI9 -> 11 | FK9: =$CJ9 -> Davis | FL9: =FL22 -> 5978 | FM9: =FM22 -> 6468 | FN9: =FN22 -> 6293 | FO9: =FO22 -> 6658 | FP9: =FP22 -> 7106 | FQ9: =FQ22 -> 7726 | FR9: =FR22 -> 7894 | FS9: =FS22 -> 8641 | ... FU9: =FU22 -> 9676 | FW9: =$CI9 -> 11 | FX9: =$CJ9 -> Davis | FY9: =FY22 -> 879 | FZ9: =FZ22 -> 805 | GA9: =GA22 -> 781 | GB9: =GB22 -> 798 | GC9: =GC22 -> 832 | GD9: =GD22 -> 957 | GE9: =GE22 -> 1053 | GF9: =GF22 -> 1218 | ... GH9: =GH22 -> 1626 | GJ9: =$CI9 -> 11 | GK9: =$CJ9 -> Davis | GL9: =GL22 -> 2332 | GM9: =GM22 -> 2168 | GN9: =GN22 -> 2218 | GO9: =GO22 -> 2221 | GP9: =GP22 -> 2205 | GQ9: =GQ22 -> 2176 | GR9: =GR22 -> 2197 | GS9: =GS22 -> 2012 | ... GU9: =GU22 -> 2058
CI10: 35 | CJ10: =VLOOKUP(CI10, lu_CoName, 2, FALSE) -> Salt Lake | CK10: =CX10 + DK10 -> 0.042931884 | CL10: =CY10 + DL10 -> 0.043507812 | CM10: =CZ10 + DM10 -> 0.043455383 | CN10: =DA10 + DN10 -> 0.04479927 | CO10: =DB10 + DO10 -> 0.046272278 | CP10: =DC10 + DP10 -> 0.049433922 | CQ10: =DD10 + DQ10 -> 0.051318901 | CR10: =DE10 + DR10 -> 0.055654606 | ... CT10: =DG10 + DT10 -> 0.06205852 | CV10: =$CI10 -> 35 | CW10: =$CJ10 -> Salt Lake | CX10: =IFERROR(DX10/EY10, 0) -> 0.020160525 | CY10: =IFERROR(DY10/EZ10, 0) -> 0.020714153 | CZ10: =IFERROR(DZ10/FA10, 0) -> 0.021753701 | DA10: =IFERROR(EA10/FB10, 0) -> 0.023663123 | DB10: =IFERROR(EB10/FC10, 0) -> 0.024920935 | DC10: =IFERROR(EC10/FD10, 0) -> 0.027333628 | DD10: =IFERROR(ED10/FE10, 0) -> 0.028398168 | DE10: =IFERROR(EE10/FF10, 0) -> 0.030665065 | ... DG10: =IFERROR(EG10/FH10, 0) -> 0.034882724 | DI10: =$CI10 -> 35 | DJ10: =$CJ10 -> Salt Lake | DK10: =IFERROR(EK10/EY10, 0) -> 0.022771358 | DL10: =IFERROR(EL10/EZ10, 0) -> 0.02279366 | DM10: =IFERROR(EM10/FA10, 0) -> 0.021701682 | DN10: =IFERROR(EN10/FB10, 0) -> 0.021136147 | DO10: =IFERROR(EO10/FC10, 0) -> 0.021351343 | DP10: =IFERROR(EP10/FD10, 0) -> 0.022100294 | DQ10: =IFERROR(EQ10/FE10, 0) -> 0.022920733 | DR10: =IFERROR(ER10/FF10, 0) -> 0.024989541 | ... DT10: =IFERROR(ET10/FH10, 0) -> 0.027175796 | DV10: =$CI10 -> 35 | DW10: =$CJ10 -> Salt Lake | DX10: =DX34 -> 9884 | DY10: =DY34 -> 10240 | DZ10: =DZ34 -> 10873 | EA10: =EA34 -> 11930 | EB10: =EB34 -> 12797 | EC10: =EC34 -> 14452 | ED10: =ED34 -> 15393 | EE10: =EE34 -> 17079 | ... EG10: =EG34 -> 20336 | EI10: =$CI10 -> 35 | EJ10: =$CJ10 -> Salt Lake | EK10: =EK34 -> 11164 | EL10: =EL34 -> 11268 | EM10: =EM34 -> 10847 | EN10: =EN34 -> 10656 | EO10: =EO34 -> 10964 | EP10: =EP34 -> 11685 | EQ10: =EQ34 -> 12424 | ER10: =ER34 -> 13918 | ... ET10: =ET34 -> 15843 | EW10: =$CI10 -> 35 | EX10: =$CJ10 -> Salt Lake | EY10: =EY34 -> 490265 | EZ10: =EZ34 -> 494348 | FA10: =FA34 -> 499823 | FB10: =FB34 -> 504160 | FC10: =FC34 -> 513504 | FD10: =FD34 -> 528726 | FE10: =FE34 -> 542042 | FF10: =FF34 -> 556953 | ... FH10: =FH34 -> 582982 | FJ10: =$CI10 -> 35 | FK10: =$CJ10 -> Salt Lake | FL10: =FL34 -> 21048 | FM10: =FM34 -> 21508 | FN10: =FN34 -> 21720 | FO10: =FO34 -> 22586 | FP10: =FP34 -> 23761 | FQ10: =FQ34 -> 26137 | FR10: =FR34 -> 27817 | FS10: =FS34 -> 30997 | ... FU10: =FU34 -> 36179 | FW10: =$CI10 -> 35 | FX10: =$CJ10 -> Salt Lake | FY10: =FY34 -> 3397 | FZ10: =FZ34 -> 3406 | GA10: =GA34 -> 3293 | GB10: =GB34 -> 3194 | GC10: =GC34 -> 3560 | GD10: =GD34 -> 4111 | GE10: =GE34 -> 4474 | GF10: =GF34 -> 5127 | ... GH10: =GH34 -> 5565 | GJ10: =$CI10 -> 35 | GK10: =$CJ10 -> Salt Lake | GL10: =GL34 -> 7767 | GM10: =GM34 -> 7862 | GN10: =GN34 -> 7554 | GO10: =GO34 -> 7462 | GP10: =GP34 -> 7404 | GQ10: =GQ34 -> 7574 | GR10: =GR34 -> 7950 | GS10: =GS34 -> 8791 | ... GU10: =GU34 -> 10278
AX11: 57 | AY11: =VLOOKUP(AX11, lu_CoName, 2, FALSE) -> Weber | CI11: 49 | CJ11: =VLOOKUP(CI11, lu_CoName, 2, FALSE) -> Utah | CK11: =CX11 + DK11 -> 0.061534608 | CL11: =CY11 + DL11 -> 0.060800768 | CM11: =CZ11 + DM11 -> 0.058871541 | CN11: =DA11 + DN11 -> 0.060458232 | CO11: =DB11 + DO11 -> 0.06048057 | CP11: =DC11 + DP11 -> 0.061172555 | CQ11: =DD11 + DQ11 -> 0.063242199 | CR11: =DE11 + DR11 -> 0.066567673 | ... CT11: =DG11 + DT11 -> 0.071920744 | CV11: =$CI11 -> 49 | CW11: =$CJ11 -> Utah | CX11: =IFERROR(DX11/EY11, 0) -> 0.03032901 | CY11: =IFERROR(DY11/EZ11, 0) -> 0.031190156 | CZ11: =IFERROR(DZ11/FA11, 0) -> 0.030172178 | DA11: =IFERROR(EA11/FB11, 0) -> 0.032257628 | DB11: =IFERROR(EB11/FC11, 0) -> 0.033239449 | DC11: =IFERROR(EC11/FD11, 0) -> 0.034505098 | DD11: =IFERROR(ED11/FE11, 0) -> 0.035446692 | DE11: =IFERROR(EE11/FF11, 0) -> 0.036988184 | ... DG11: =IFERROR(EG11/FH11, 0) -> 0.042109299 | DI11: =$CI11 -> 49 | DJ11: =$CJ11 -> Utah | DK11: =IFERROR(EK11/EY11, 0) -> 0.031205599 | DL11: =IFERROR(EL11/EZ11, 0) -> 0.029610612 | DM11: =IFERROR(EM11/FA11, 0) -> 0.028699363 | DN11: =IFERROR(EN11/FB11, 0) -> 0.028200604 | DO11: =IFERROR(EO11/FC11, 0) -> 0.027241121 | DP11: =IFERROR(EP11/FD11, 0) -> 0.026667457 | DQ11: =IFERROR(EQ11/FE11, 0) -> 0.027795508 | DR11: =IFERROR(ER11/FF11, 0) -> 0.029579489 | ... DT11: =IFERROR(ET11/FH11, 0) -> 0.029811445 | DV11: =$CI11 -> 49 | DW11: =$CJ11 -> Utah | DX11: =DX41 -> 6297 | DY11: =DY41 -> 6694 | DZ11: =DZ41 -> 6617 | EA11: =EA41 -> 7148 | EB11: =EB41 -> 7553 | EC11: =EC41 -> 8149 | ED11: =ED41 -> 8719 | EE11: =EE41 -> 9366 | ... EG11: =EG41 -> 11642 | EI11: =$CI11 -> 49 | EJ11: =$CJ11 -> Utah | EK11: =EK41 -> 6479 | EL11: =EL41 -> 6355 | EM11: =EM41 -> 6294 | EN11: =EN41 -> 6249 | EO11: =EO41 -> 6190 | EP11: =EP41 -> 6298 | EQ11: =EQ41 -> 6837 | ER11: =ER41 -> 7490 | ... ET11: =ET41 -> 8242 | EW11: =$CI11 -> 49 | EX11: =$CJ11 -> Utah | EY11: =EY41 -> 207623 | EZ11: =EZ41 -> 214619 | FA11: =FA41 -> 219308 | FB11: =FB41 -> 221591 | FC11: =FC41 -> 227230 | FD11: =FD41 -> 236168 | FE11: =FE41 -> 245975 | FF11: =FF41 -> 253216 | ... FH11: =FH41 -> 276471 | FJ11: =$CI11 -> 49 | FK11: =$CJ11 -> Utah | FL11: =FL41 -> 12776 | FM11: =FM41 -> 13049 | FN11: =FN41 -> 12911 | FO11: =FO41 -> 13397 | FP11: =FP41 -> 13743 | FQ11: =FQ41 -> 14447 | FR11: =FR41 -> 15556 | FS11: =FS41 -> 16856 | ... FU11: =FU41 -> 19884 | FW11: =$CI11 -> 49 | FX11: =$CJ11 -> Utah | FY11: =FY41 -> 2005 | FZ11: =FZ41 -> 2065 | GA11: =GA41 -> 2118 | GB11: =GB41 -> 2203 | GC11: =GC41 -> 2215 | GD11: =GD41 -> 2317 | GE11: =GE41 -> 2441 | GF11: =GF41 -> 2928 | ... GH11: =GH41 -> 3265 | GJ11: =$CI11 -> 49 | GK11: =$CJ11 -> Utah | GL11: =GL41 -> 4474 | GM11: =GM41 -> 4290 | GN11: =GN41 -> 4176 | GO11: =GO41 -> 4046 | GP11: =GP41 -> 3975 | GQ11: =GQ41 -> 3981 | GR11: =GR41 -> 4396 | GS11: =GS41 -> 4562 | ... GU11: =GU41 -> 4977
AZ12: 2010 | BA12: 2011 | BB12: 2012 | BC12: 2013 | BD12: 2014 | BE12: 2015 | BF12: 2016 | BG12: 2017 | BH12: 2018 | BI12: 2019 | CI12: 1049 | CJ12: =VLOOKUP(CI12, lu_CoName, 2, FALSE) -> State of Utah | CK12: =CX12 + DK12 -> 0.048247967 | CL12: =CY12 + DL12 -> 0.048146251 | CM12: =CZ12 + DM12 -> 0.047170408 | CN12: =DA12 + DN12 -> 0.048242532 | CO12: =DB12 + DO12 -> 0.048818053 | CP12: =DC12 + DP12 -> 0.051301419 | CQ12: =DD12 + DQ12 -> 0.053654326 | CR12: =DE12 + DR12 -> 0.057712073 | ... CT12: =DG12 + DT12 -> 0.065641119 | CV12: =$CI12 -> 1049 | CW12: =$CJ12 -> State of Utah | CX12: =IFERROR(DX12/EY12, 0) -> 0.022286052 | CY12: =IFERROR(DY12/EZ12, 0) -> 0.023168413 | CZ12: =IFERROR(DZ12/FA12, 0) -> 0.02324078 | DA12: =IFERROR(EA12/FB12, 0) -> 0.024825238 | DB12: =IFERROR(EB12/FC12, 0) -> 0.025823246 | DC12: =IFERROR(EC12/FD12, 0) -> 0.02787694 | DD12: =IFERROR(ED12/FE12, 0) -> 0.0291896 | DE12: =IFERROR(EE12/FF12, 0) -> 0.031481466 | ... DG12: =IFERROR(EG12/FH12, 0) -> 0.036790903 | DI12: =$CI12 -> 1049 | DJ12: =$CJ12 -> State of Utah | DK12: =IFERROR(EK12/EY12, 0) -> 0.025961915 | DL12: =IFERROR(EL12/EZ12, 0) -> 0.024977838 | DM12: =IFERROR(EM12/FA12, 0) -> 0.023929627 | DN12: =IFERROR(EN12/FB12, 0) -> 0.023417294 | DO12: =IFERROR(EO12/FC12, 0) -> 0.022994807 | DP12: =IFERROR(EP12/FD12, 0) -> 0.023424479 | DQ12: =IFERROR(EQ12/FE12, 0) -> 0.024464726 | DR12: =IFERROR(ER12/FF12, 0) -> 0.026230607 | ... DT12: =IFERROR(ET12/FH12, 0) -> 0.028850216 | DV12: =$CI12 -> 1049 | DW12: =$CJ12 -> State of Utah | DX12: =DX46 -> 27125 | DY12: =DY46 -> 28592 | DZ12: =DZ46 -> 29049 | EA12: =EA46 -> 31262 | EB12: =EB46 -> 33114 | EC12: =EC46 -> 36796 | ED12: =ED46 -> 39563 | EE12: =EE46 -> 43863 | ... EG12: =EG46 -> 54431 | EI12: =$CI12 -> 1049 | EJ12: =$CJ12 -> State of Utah | EK12: =EK46 -> 31599 | EL12: =EL46 -> 30825 | EM12: =EM46 -> 29910 | EN12: =EN46 -> 29489 | EO12: =EO46 -> 29487 | EP12: =EP46 -> 30919 | EQ12: =EQ46 -> 33159 | ER12: =ER46 -> 36547 | ... ET12: =ET46 -> 42683 | EW12: =$CI12 -> 1049 | EX12: =$CJ12 -> State of Utah | EY12: =EY46 -> 1217129 | EZ12: =EZ46 -> 1234094 | FA12: =FA46 -> 1249915 | FB12: =FB46 -> 1259283 | FC12: =FC46 -> 1282333 | FD12: =FD46 -> 1319944 | FE12: =FE46 -> 1355380 | FF12: =FF46 -> 1393296 | ... FH12: =FH46 -> 1479469 | FJ12: =$CI12 -> 1049 | FK12: =$CJ12 -> State of Utah | FL12: =FL46 -> 58724 | FM12: =FM46 -> 59417 | FN12: =FN46 -> 58959 | FO12: =FO46 -> 60751 | FP12: =FP46 -> 62601 | FQ12: =FQ46 -> 67715 | FR12: =FR46 -> 72722 | FS12: =FS46 -> 80410 | ... FU12: =FU46 -> 97114 | FW12: =$CI12 -> 1049 | FX12: =$CJ12 -> State of Utah | FY12: =FY46 -> 9643 | FZ12: =FZ46 -> 9471 | GA12: =GA46 -> 9504 | GB12: =GB46 -> 9680 | GC12: =GC46 -> 10254 | GD12: =GD46 -> 11439 | GE12: =GE46 -> 12195 | GF12: =GF46 -> 13968 | ... GH12: =GH46 -> 16994 | GJ12: =$CI12 -> 1049 | GK12: =$CJ12 -> State of Utah | GL12: =GL46 -> 21956 | GM12: =GM46 -> 21354 | GN12: =GN46 -> 20406 | GO12: =GO46 -> 19809 | GP12: =GP46 -> 19233 | GQ12: =GQ46 -> 19480 | GR12: =GR46 -> 20964 | GS12: =GS46 -> 22579 | ... GU12: =GU46 -> 25689
AY13: Home-Based-Job | AZ13: =INDEX($DK$7:$DT$13, MATCH(AY11, $DJ$7:$DJ$13,0), MATCH(AZ$6, $DK$6:$DT$6, 0)) -> 0.016804761 | BA13: =INDEX($DK$7:$DT$13, MATCH(AY11, $DJ$7:$DJ$13,0), MATCH(BA$6, $DK$6:$DT$6, 0)) -> 0.017684219 | BB13: =INDEX($DK$7:$DT$13, MATCH(AY11, $DJ$7:$DJ$13,0), MATCH(BB$6, $DK$6:$DT$6, 0)) -> 0.016231019 | BC13: =INDEX($DK$7:$DT$13, MATCH(AY11, $DJ$7:$DJ$13,0), MATCH(BC$6, $DK$6:$DT$6, 0)) -> 0.015404084 | BD13: =INDEX($DK$7:$DT$13, MATCH(AY11, $DJ$7:$DJ$13,0), MATCH(BD$6, $DK$6:$DT$6, 0)) -> 0.017273863 | BE13: =INDEX($DK$7:$DT$13, MATCH(AY11, $DJ$7:$DJ$13,0), MATCH(BE$6, $DK$6:$DT$6, 0)) -> 0.019040688 | BF13: =INDEX($DK$7:$DT$13, MATCH(AY11, $DJ$7:$DJ$13,0), MATCH(BF$6, $DK$6:$DT$6, 0)) -> 0.019082427 | BG13: =INDEX($DK$7:$DT$13, MATCH(AY11, $DJ$7:$DJ$13,0), MATCH(BG$6, $DK$6:$DT$6, 0)) -> 0.021777583 | BH13: =INDEX($DK$7:$DT$13, MATCH(AY11, $DJ$7:$DJ$13,0), MATCH(BH$6, $DK$6:$DT$6, 0)) -> 0.021801721 | BI13: =INDEX($DK$7:$DT$13, MATCH(AY11, $DJ$7:$DJ$13,0), MATCH(BI$6, $DK$6:$DT$6, 0)) -> 0.022821867 | CI13: 1000 | CJ13: =VLOOKUP(CI13, lu_CoName, 2, FALSE) -> United States | CK13: =CX13 + DK13 -> 0.041360975 | CL13: =CY13 + DL13 -> 0.042224129 | CM13: =CZ13 + DM13 -> 0.042729813 | CN13: =DA13 + DN13 -> 0.043254384 | CO13: =DB13 + DO13 -> 0.043665739 | CP13: =DC13 + DP13 -> 0.044232594 | CQ13: =DD13 + DQ13 -> 0.045672811 | CR13: =DE13 + DR13 -> 0.047344292 | ... CT13: =DG13 + DT13 -> 0.051713986 | CV13: =$CI13 -> 1000 | CW13: =$CJ13 -> United States | CX13: =IFERROR(DX13/EY13, 0) -> 0.020312996 | CY13: =IFERROR(DY13/EZ13, 0) -> 0.021408025 | CZ13: =IFERROR(DZ13/FA13, 0) -> 0.022257295 | DA13: =IFERROR(EA13/FB13, 0) -> 0.023061732 | DB13: =IFERROR(EB13/FC13, 0) -> 0.023882179 | DC13: =IFERROR(EC13/FD13, 0) -> 0.024745544 | DD13: =IFERROR(ED13/FE13, 0) -> 0.025975568 | DE13: =IFERROR(EE13/FF13, 0) -> 0.027440342 | ... DG13: =IFERROR(EG13/FH13, 0) -> 0.031329077 | DI13: =$CI13 -> 1000 | DJ13: =$CJ13 -> United States | DK13: =IFERROR(EK13/EY13, 0) -> 0.021047979 | DL13: =IFERROR(EL13/EZ13, 0) -> 0.020816104 | DM13: =IFERROR(EM13/FA13, 0) -> 0.020472518 | DN13: =IFERROR(EN13/FB13, 0) -> 0.020192652 | DO13: =IFERROR(EO13/FC13, 0) -> 0.01978356 | DP13: =IFERROR(EP13/FD13, 0) -> 0.01948705 | DQ13: =IFERROR(EQ13/FE13, 0) -> 0.019697244 | DR13: =IFERROR(ER13/FF13, 0) -> 0.01990395 | ... DT13: =IFERROR(ET13/FH13, 0) -> 0.020384909 | DV13: =$CI13 -> 1000 | DW13: =$CJ13 -> United States | DX13: =DX47 -> 2828687 | DY13: =DY47 -> 2986167 | DZ13: =DZ47 -> 3113654 | EA13: =EA47 -> 3223722 | EB13: =EB47 -> 3375439 | EC13: =EC47 -> 3553984 | ED13: =ED47 -> 3788828 | EE13: =EE47 -> 4073026 | ... EG13: =EG47 -> 4785071 | EI13: =$CI13 -> 1000 | EJ13: =$CJ13 -> United States | EK13: =EK47 -> 2931037 | EL13: =EL47 -> 2903601 | EM13: =EM47 -> 2863975 | EN13: =EN47 -> 2822663 | EO13: =EO47 -> 2796152 | EP13: =EP47 -> 2798753 | EQ13: =EQ47 -> 2873064 | ER13: =ER47 -> 2954384 | ... ET13: =ET47 -> 3113505 | EW13: =$CI13 -> 1000 | EX13: =$CJ13 -> United States | EY13: =EY47 -> 139255035 | EZ13: =EZ47 -> 139488206 | FA13: =FA47 -> 139893639 | FB13: =FB47 -> 139786639 | FC13: =FC47 -> 141337148 | FD13: =FD47 -> 143621171 | FE13: =FE47 -> 145861221 | FF13: =FF47 -> 148432042 | ... FH13: =FH47 -> 152735781 | FJ13: =$CI13 -> 1000 | FK13: =$CJ13 -> United States | FL13: =FL47 -> 5759724 | FM13: =FM47 -> 5889768 | FN13: =FN47 -> 5977629 | FO13: =FO47 -> 6046385 | FP13: =FP47 -> 6171591 | FQ13: =FQ47 -> 6352737 | FR13: =FR47 -> 6661892 | FS13: =FS47 -> 7027410 | ... FU13: =FU47 -> 7898576 | FW13: =$CI13 -> 1000 | FX13: =$CJ13 -> United States | FY13: =FY47 -> 815897 | FZ13: =FZ47 -> 825316 | GA13: =GA47 -> 834222 | GB13: =GB47 -> 831600 | GC13: =GC47 -> 835384 | GD13: =GD47 -> 848753 | GE13: =GE47 -> 895042 | GF13: =GF47 -> 939971 | ... GH13: =GH47 -> 1017531 | GJ13: =$CI13 -> 1000 | GK13: =$CJ13 -> United States | GL13: =GL47 -> 2115140 | GM13: =GM47 -> 2078285 | GN13: =GN47 -> 2029753 | GO13: =GO47 -> 1991063 | GP13: =GP47 -> 1960768 | GQ13: =GQ47 -> 1950000 | GR13: =GR47 -> 1978022 | GS13: =GS47 -> 2014413 | ... GU13: =GU47 -> 2095974
AY14: Telecommute | AZ14: =INDEX($CX$7:$DG$13, MATCH(AY11, $CW$7:$CW$13,0), MATCH(AZ$6, $CX$6:$DG$6, 0)) -> 0.014684716 | BA14: =INDEX($CX$7:$DG$13, MATCH(AY11, $CW$7:$CW$13,0), MATCH(BA$6, $CX$6:$DG$6, 0)) -> 0.016552351 | BB14: =INDEX($CX$7:$DG$13, MATCH(AY11, $CW$7:$CW$13,0), MATCH(BB$6, $CX$6:$DG$6, 0)) -> 0.016069374 | BC14: =INDEX($CX$7:$DG$13, MATCH(AY11, $CW$7:$CW$13,0), MATCH(BC$6, $CX$6:$DG$6, 0)) -> 0.017601949 | BD14: =INDEX($CX$7:$DG$13, MATCH(AY11, $CW$7:$CW$13,0), MATCH(BD$6, $CX$6:$DG$6, 0)) -> 0.018449083 | BE14: =INDEX($CX$7:$DG$13, MATCH(AY11, $CW$7:$CW$13,0), MATCH(BE$6, $CX$6:$DG$6, 0)) -> 0.022089778 | BF14: =INDEX($CX$7:$DG$13, MATCH(AY11, $CW$7:$CW$13,0), MATCH(BF$6, $CX$6:$DG$6, 0)) -> 0.022162555 | BG14: =INDEX($CX$7:$DG$13, MATCH(AY11, $CW$7:$CW$13,0), MATCH(BG$6, $CX$6:$DG$6, 0)) -> 0.024474606 | BH14: =INDEX($CX$7:$DG$13, MATCH(AY11, $CW$7:$CW$13,0), MATCH(BH$6, $CX$6:$DG$6, 0)) -> 0.02716085 | BI14: =INDEX($CX$7:$DG$13, MATCH(AY11, $CW$7:$CW$13,0), MATCH(BI$6, $CX$6:$DG$6, 0)) -> 0.031508848
AY15: Total Work At Home | AZ15: =SUM(AZ13:AZ14) -> 0.031489478 | BA15: =SUM(BA13:BA14) -> 0.03423657 | BB15: =SUM(BB13:BB14) -> 0.032300393 | BC15: =SUM(BC13:BC14) -> 0.033006032 | BD15: =SUM(BD13:BD14) -> 0.035722947 | BE15: =SUM(BE13:BE14) -> 0.041130466 | BF15: =SUM(BF13:BF14) -> 0.041244982 | BG15: =SUM(BG13:BG14) -> 0.046252189 | ... BI15: =SUM(BI13:BI14) -> 0.054330715 | EW15: =EW4 + 0.1 -> 100.1 | EX15: =EX4 -> Total Workers | FD15: Workers | FJ15: =FJ4 + 0.1 -> 700.1 | FK15: =FK4 -> Worked at home | FQ15: Workers | FW15: =FW4 + 0.1 -> 712.1 | FX15: =FX4 -> Self-employed in own incorporated business workers | GD15: Workers | GJ15: =GJ4 + 0.1 -> 760.1 | GK15: =GK4 -> Self-employed in own not incorporated business workers | GQ15: Workers
CJ16: County | CK16: 2010 | CL16: 2011 | CM16: 2012 | CN16: 2013 | CO16: 2014 | CP16: 2015 | CQ16: 2016 | CR16: 2017 | CS16: 2018 | CT16: 2019 | CW16: County | CX16: 2010 | CY16: 2011 | CZ16: 2012 | DA16: 2013 | DB16: 2014 | DC16: 2015 | DD16: 2016 | DE16: 2017 | DF16: 2018 | DG16: 2019 | DJ16: County | DK16: 2010 | DL16: 2011 | DM16: 2012 | DN16: 2013 | DO16: 2014 | DP16: 2015 | DQ16: 2016 | DR16: 2017 | DS16: 2018 | DT16: 2019 | DW16: County | DX16: 2010 | DY16: 2011 | DZ16: 2012 | EA16: 2013 | EB16: 2014 | EC16: 2015 | ED16: 2016 | EE16: 2017 | EF16: 2018 | EG16: 2019 | EJ16: County | EK16: 2010 | EL16: 2011 | EM16: 2012 | EN16: 2013 | EO16: 2014 | EP16: 2015 | EQ16: 2016 | ER16: 2017 | ES16: 2018 | ET16: 2019 | EX16: County | EY16: 2010 | EZ16: 2011 | FA16: 2012 | FB16: 2013 | FC16: 2014 | FD16: 2015 | FE16: 2016 | FF16: 2017 | FG16: 2018 | FH16: 2019 | FK16: County | FL16: 2010 | FM16: 2011 | FN16: 2012 | FO16: 2013 | FP16: 2014 | FQ16: 2015 | FR16: 2016 | FS16: 2017 | FT16: 2018 | FU16: 2019 | FX16: County | FY16: 2010 | FZ16: 2011 | GA16: 2012 | GB16: 2013 | GC16: 2014 | GD16: 2015 | GE16: 2016 | GF16: 2017 | GG16: 2018 | GH16: 2019 | GK16: County | GL16: 2010 | GM16: 2011 | GN16: 2012 | GO16: 2013 | GP16: 2014 | GQ16: 2015 | GR16: 2016 | GS16: 2017 | GT16: 2018 | GU16: 2019
AX17: 11 | AY17: =VLOOKUP(AX17, lu_CoName, 2, FALSE) -> Davis | CI17: 1 | CJ17: =VLOOKUP(CI17, lu_CoName, 2, FALSE) -> Beaver | CK17: =CX17 + DK17 -> 0.069719472 | CL17: =CY17 + DL17 -> 0.053738318 | CM17: =CZ17 + DM17 -> 0.034535687 | CN17: =DA17 + DN17 -> 0.033383346 | CO17: =DB17 + DO17 -> 0.025906736 | CP17: =DC17 + DP17 -> 0.01426087 | CQ17: =DD17 + DQ17 -> 0.020356234 | CR17: =DE17 + DR17 -> 0.034034417 | ... CT17: =DG17 + DT17 -> 0.059796916 | CV17: =$CI17*10 + 0 -> 10 | CW17: =$CJ17 -> Beaver | CX17: =IFERROR(DX17/EY17, 0) -> 0.029290429 | CY17: =IFERROR(DY17/EZ17, 0) -> 0.026869159 | CZ17: =IFERROR(DZ17/FA17, 0) -> 0.013814275 | DA17: =IFERROR(EA17/FB17, 0) -> 0.018379595 | DB17: =IFERROR(EB17/FC17, 0) -> 0.0077720207 | DC17: =IFERROR(EC17/FD17, 0) -> 0.0017391304 | DD17: =IFERROR(ED17/FE17, 0) -> 0.0010905125 | DE17: =IFERROR(EE17/FF17, 0) -> 0.014913958 | ... DG17: =IFERROR(EG17/FH17, 0) -> 0.025197443 | DI17: =$CI17*10 + 0 -> 10 | DJ17: =$CJ17 -> Beaver | DK17: =IFERROR(EK17/EY17, 0) -> 0.040429043 | DL17: =IFERROR(EL17/EZ17, 0) -> 0.026869159 | DM17: =IFERROR(EM17/FA17, 0) -> 0.020721412 | DN17: =IFERROR(EN17/FB17, 0) -> 0.015003751 | DO17: =IFERROR(EO17/FC17, 0) -> 0.018134715 | DP17: =IFERROR(EP17/FD17, 0) -> 0.012521739 | DQ17: =IFERROR(EQ17/FE17, 0) -> 0.019265722 | DR17: =IFERROR(ER17/FF17, 0) -> 0.019120459 | ... DT17: =IFERROR(ET17/FH17, 0) -> 0.034599473 | DV17: =$CI17*10 + 0 -> 10 | DW17: =$CJ17 -> Beaver | DX17: =FL17 - EK17 -> 71 | DY17: =FM17 - EL17 -> 69 | DZ17: =FN17 - EM17 -> 36 | EA17: =FO17 - EN17 -> 49 | EB17: =FP17 - EO17 -> 21 | EC17: =FQ17 - EP17 -> 5 | ED17: =FR17 - EQ17 -> 3 | EE17: =FS17 - ER17 -> 39 | ... EG17: =FU17 - ET17 -> 67 | EI17: =$CI17*10 + 0 -> 10 | EJ17: =$CJ17 -> Beaver | EK17: =FY17 + GL17 -> 98 | EL17: =FZ17 + GM17 -> 69 | EM17: =GA17 + GN17 -> 54 | EN17: =GB17 + GO17 -> 40 | EO17: =GC17 + GP17 -> 49 | EP17: =GD17 + GQ17 -> 36 | EQ17: =GE17 + GR17 -> 53 | ER17: =GF17 + GS17 -> 50 | ... ET17: =GH17 + GU17 -> 92 | EW17: =$CI17 -> 1 | EX17: =$CJ17 -> Beaver | EY17: =INDEX('2010'!$E$7:$EN$37, MATCH(EW17, '2010'!$A$7:$A$37, 0), MATCH(EW15, '2010'!$E$4:$EN$4, 0) ) -> 2424 | EZ17: =INDEX('2011'!$E$7:$EN$37, MATCH(EW17, '2011'!$A$7:$A$37, 0), MATCH(EW15, '2011'!$E$4:$EN$4, 0) ) -> 2568 | FA17: =INDEX('2012'!$E$7:$EN$37, MATCH(EW17, '2012'!$A$7:$A$37, 0), MATCH(EW15, '2012'!$E$4:$EN$4, 0) ) -> 2606 | FB17: =INDEX('2013'!$E$7:$EN$37, MATCH(EW17, '2013'!$A$7:$A$37, 0), MATCH(EW15, '2013'!$E$4:$EN$4, 0) ) -> 2666 | FC17: =INDEX('2014'!$E$7:$EN$37, MATCH(EW17, '2014'!$A$7:$A$37, 0), MATCH(EW15, '2014'!$E$4:$EN$4, 0) ) -> 2702 | FD17: =INDEX('2015'!$E$7:$EN$37, MATCH(EW17, '2015'!$A$7:$A$37, 0), MATCH(EW15, '2015'!$E$4:$EN$4, 0) ) -> 2875 | FE17: =INDEX('2016'!$E$7:$EN$37, MATCH(EW17, '2016'!$A$7:$A$37, 0), MATCH(EW15, '2016'!$E$4:$EN$4, 0) ) -> 2751 | FF17: =INDEX('2017'!$E$7:$EN$37, MATCH(EW17, '2017'!$A$7:$A$37, 0), MATCH(EW15, '2017'!$E$4:$EN$4, 0) ) -> 2615 | FG17: =INDEX('2018'!$E$7:$EN$37, MATCH(EW17, '2018'!$A$7:$A$37, 0), MATCH(EW15, '2018'!$E$4:$EN$4, 0) ) -> 2692 | FH17: =INDEX('2019'!$E$7:$EN$37, MATCH(EW17, '2019'!$A$7:$A$37, 0), MATCH(EW15, '2019'!$E$4:$EN$4, 0) ) -> 2659 | FJ17: =$CI17 -> 1 | FK17: =$CJ17 -> Beaver | FL17: =INDEX('2010'!$E$7:$EN$37, MATCH(FJ17, '2010'!$A$7:$A$37, 0), MATCH(FJ15, '2010'!$E$4:$EN$4, 0) ) -> 169 | FM17: =INDEX('2011'!$E$7:$EN$37, MATCH(FJ17, '2011'!$A$7:$A$37, 0), MATCH(FJ15, '2011'!$E$4:$EN$4, 0) ) -> 138 | FN17: =INDEX('2012'!$E$7:$EN$37, MATCH(FJ17, '2012'!$A$7:$A$37, 0), MATCH(FJ15, '2012'!$E$4:$EN$4, 0) ) -> 90 | FO17: =INDEX('2013'!$E$7:$EN$37, MATCH(FJ17, '2013'!$A$7:$A$37, 0), MATCH(FJ15, '2013'!$E$4:$EN$4, 0) ) -> 89 | FP17: =INDEX('2014'!$E$7:$EN$37, MATCH(FJ17, '2014'!$A$7:$A$37, 0), MATCH(FJ15, '2014'!$E$4:$EN$4, 0) ) -> 70 | FQ17: =INDEX('2015'!$E$7:$EN$37, MATCH(FJ17, '2015'!$A$7:$A$37, 0), MATCH(FJ15, '2015'!$E$4:$EN$4, 0) ) -> 41 | FR17: =INDEX('2016'!$E$7:$EN$37, MATCH(FJ17, '2016'!$A$7:$A$37, 0), MATCH(FJ15, '2016'!$E$4:$EN$4, 0) ) -> 56 | FS17: =INDEX('2017'!$E$7:$EN$37, MATCH(FJ17, '2017'!$A$7:$A$37, 0), MATCH(FJ15, '2017'!$E$4:$EN$4, 0) ) -> 89 | FT17: =INDEX('2018'!$E$7:$EN$37, MATCH(FJ17, '2018'!$A$7:$A$37, 0), MATCH(FJ15, '2018'!$E$4:$EN$4, 0) ) -> 108 | FU17: =INDEX('2019'!$E$7:$EN$37, MATCH(FJ17, '2019'!$A$7:$A$37, 0), MATCH(FJ15, '2019'!$E$4:$EN$4, 0) ) -> 159 | FW17: =$CI17 -> 1 | FX17: =$CJ17 -> Beaver | FY17: =INDEX('2010'!$E$7:$EN$37, MATCH(FW17, '2010'!$A$7:$A$37, 0), MATCH(FW15, '2010'!$E$4:$EN$4, 0) ) -> 39 | FZ17: =INDEX('2011'!$E$7:$EN$37, MATCH(FW17, '2011'!$A$7:$A$37, 0), MATCH(FW15, '2011'!$E$4:$EN$4, 0) ) -> 13 | GA17: =INDEX('2012'!$E$7:$EN$37, MATCH(FW17, '2012'!$A$7:$A$37, 0), MATCH(FW15, '2012'!$E$4:$EN$4, 0) ) -> 12 | GB17: =INDEX('2013'!$E$7:$EN$37, MATCH(FW17, '2013'!$A$7:$A$37, 0), MATCH(FW15, '2013'!$E$4:$EN$4, 0) ) -> 0 | GC17: =INDEX('2014'!$E$7:$EN$37, MATCH(FW17, '2014'!$A$7:$A$37, 0), MATCH(FW15, '2014'!$E$4:$EN$4, 0) ) -> 12 | GD17: =INDEX('2015'!$E$7:$EN$37, MATCH(FW17, '2015'!$A$7:$A$37, 0), MATCH(FW15, '2015'!$E$4:$EN$4, 0) ) -> 12 | GE17: =INDEX('2016'!$E$7:$EN$37, MATCH(FW17, '2016'!$A$7:$A$37, 0), MATCH(FW15, '2016'!$E$4:$EN$4, 0) ) -> 14 | GF17: =INDEX('2017'!$E$7:$EN$37, MATCH(FW17, '2017'!$A$7:$A$37, 0), MATCH(FW15, '2017'!$E$4:$EN$4, 0) ) -> 15 | GG17: =INDEX('2018'!$E$7:$EN$37, MATCH(FW17, '2018'!$A$7:$A$37, 0), MATCH(FW15, '2018'!$E$4:$EN$4, 0) ) -> 35 | GH17: =INDEX('2019'!$E$7:$EN$37, MATCH(FW17, '2019'!$A$7:$A$37, 0), MATCH(FW15, '2019'!$E$4:$EN$4, 0) ) -> 22 | GJ17: =$CI17 -> 1 | GK17: =$CJ17 -> Beaver | GL17: =INDEX('2010'!$E$7:$EN$37, MATCH(GJ17, '2010'!$A$7:$A$37, 0), MATCH(GJ15, '2010'!$E$4:$EN$4, 0) ) -> 59 | GM17: =INDEX('2011'!$E$7:$EN$37, MATCH(GJ17, '2011'!$A$7:$A$37, 0), MATCH(GJ15, '2011'!$E$4:$EN$4, 0) ) -> 56 | GN17: =INDEX('2012'!$E$7:$EN$37, MATCH(GJ17, '2012'!$A$7:$A$37, 0), MATCH(GJ15, '2012'!$E$4:$EN$4, 0) ) -> 42 | GO17: =INDEX('2013'!$E$7:$EN$37, MATCH(GJ17, '2013'!$A$7:$A$37, 0), MATCH(GJ15, '2013'!$E$4:$EN$4, 0) ) -> 40 | GP17: =INDEX('2014'!$E$7:$EN$37, MATCH(GJ17, '2014'!$A$7:$A$37, 0), MATCH(GJ15, '2014'!$E$4:$EN$4, 0) ) -> 37 | GQ17: =INDEX('2015'!$E$7:$EN$37, MATCH(GJ17, '2015'!$A$7:$A$37, 0), MATCH(GJ15, '2015'!$E$4:$EN$4, 0) ) -> 24 | GR17: =INDEX('2016'!$E$7:$EN$37, MATCH(GJ17, '2016'!$A$7:$A$37, 0), MATCH(GJ15, '2016'!$E$4:$EN$4, 0) ) -> 39 | GS17: =INDEX('2017'!$E$7:$EN$37, MATCH(GJ17, '2017'!$A$7:$A$37, 0), MATCH(GJ15, '2017'!$E$4:$EN$4, 0) ) -> 35 | GT17: =INDEX('2018'!$E$7:$EN$37, MATCH(GJ17, '2018'!$A$7:$A$37, 0), MATCH(GJ15, '2018'!$E$4:$EN$4, 0) ) -> 20 | GU17: =INDEX('2019'!$E$7:$EN$37, MATCH(GJ17, '2019'!$A$7:$A$37, 0), MATCH(GJ15, '2019'!$E$4:$EN$4, 0) ) -> 70
AZ18: 2010 | BA18: 2011 | BB18: 2012 | BC18: 2013 | BD18: 2014 | BE18: 2015 | BF18: 2016 | BG18: 2017 | BH18: 2018 | BI18: 2019 | CI18: 3 | CJ18: =VLOOKUP(CI18, lu_CoName, 2, FALSE) -> Box Elder | CK18: =CX18 + DK18 -> 0.050635961 | CL18: =CY18 + DL18 -> 0.049246374 | CM18: =CZ18 + DM18 -> 0.043755654 | CN18: =DA18 + DN18 -> 0.039484174 | CO18: =DB18 + DO18 -> 0.034524987 | CP18: =DC18 + DP18 -> 0.033645035 | CQ18: =DD18 + DQ18 -> 0.039750221 | CR18: =DE18 + DR18 -> 0.040007249 | ... CT18: =DG18 + DT18 -> 0.052917861 | CV18: =$CI18*10 + 0 -> 30 | CW18: =$CJ18 -> Box Elder | CX18: =IFERROR(DX18/EY18, 0) -> 0.014839083 | CY18: =IFERROR(DY18/EZ18, 0) -> 0.015119917 | CZ18: =IFERROR(DZ18/FA18, 0) -> 0.013331429 | DA18: =IFERROR(EA18/FB18, 0) -> 0.011395076 | DB18: =IFERROR(EB18/FC18, 0) -> 0.011257124 | DC18: =IFERROR(EC18/FD18, 0) -> 0.014473004 | DD18: =IFERROR(ED18/FE18, 0) -> 0.01700918 | DE18: =IFERROR(EE18/FF18, 0) -> 0.018032713 | ... DG18: =IFERROR(EG18/FH18, 0) -> 0.02863046 | DI18: =$CI18*10 + 0 -> 30 | DJ18: =$CJ18 -> Box Elder | DK18: =IFERROR(EK18/EY18, 0) -> 0.035796878 | DL18: =IFERROR(EL18/EZ18, 0) -> 0.034126457 | DM18: =IFERROR(EM18/FA18, 0) -> 0.030424225 | DN18: =IFERROR(EN18/FB18, 0) -> 0.028089097 | DO18: =IFERROR(EO18/FC18, 0) -> 0.023267863 | DP18: =IFERROR(EP18/FD18, 0) -> 0.019172031 | DQ18: =IFERROR(EQ18/FE18, 0) -> 0.022741041 | DR18: =IFERROR(ER18/FF18, 0) -> 0.021974537 | ... DT18: =IFERROR(ET18/FH18, 0) -> 0.024287401 | DV18: =$CI18*10 + 0 -> 30 | DW18: =$CJ18 -> Box Elder | DX18: =FL18 - EK18 -> 308 | DY18: =FM18 - EL18 -> 319 | DZ18: =FN18 - EM18 -> 280 | EA18: =FO18 - EN18 -> 243 | EB18: =FP18 - EO18 -> 239 | EC18: =FQ18 - EP18 -> 308 | ED18: =FR18 - EQ18 -> 365 | EE18: =FS18 - ER18 -> 398 | ... EG18: =FU18 - ET18 -> 679 | EI18: =$CI18*10 + 0 -> 30 | EJ18: =$CJ18 -> Box Elder | EK18: =FY18 + GL18 -> 743 | EL18: =FZ18 + GM18 -> 720 | EM18: =GA18 + GN18 -> 639 | EN18: =GB18 + GO18 -> 599 | EO18: =GC18 + GP18 -> 494 | EP18: =GD18 + GQ18 -> 408 | EQ18: =GE18 + GR18 -> 488 | ER18: =GF18 + GS18 -> 485 | ... ET18: =GH18 + GU18 -> 576 | EW18: =$CI18 -> 3 | EX18: =$CJ18 -> Box Elder | EY18: =INDEX('2010'!$E$7:$EN$37, MATCH(EW18, '2010'!$A$7:$A$37, 0), MATCH(EW15, '2010'!$E$4:$EN$4, 0) ) -> 20756 | EZ18: =INDEX('2011'!$E$7:$EN$37, MATCH(EW18, '2011'!$A$7:$A$37, 0), MATCH(EW15, '2011'!$E$4:$EN$4, 0) ) -> 21098 | FA18: =INDEX('2012'!$E$7:$EN$37, MATCH(EW18, '2012'!$A$7:$A$37, 0), MATCH(EW15, '2012'!$E$4:$EN$4, 0) ) -> 21003 | FB18: =INDEX('2013'!$E$7:$EN$37, MATCH(EW18, '2013'!$A$7:$A$37, 0), MATCH(EW15, '2013'!$E$4:$EN$4, 0) ) -> 21325 | FC18: =INDEX('2014'!$E$7:$EN$37, MATCH(EW18, '2014'!$A$7:$A$37, 0), MATCH(EW15, '2014'!$E$4:$EN$4, 0) ) -> 21231 | FD18: =INDEX('2015'!$E$7:$EN$37, MATCH(EW18, '2015'!$A$7:$A$37, 0), MATCH(EW15, '2015'!$E$4:$EN$4, 0) ) -> 21281 | FE18: =INDEX('2016'!$E$7:$EN$37, MATCH(EW18, '2016'!$A$7:$A$37, 0), MATCH(EW15, '2016'!$E$4:$EN$4, 0) ) -> 21459 | FF18: =INDEX('2017'!$E$7:$EN$37, MATCH(EW18, '2017'!$A$7:$A$37, 0), MATCH(EW15, '2017'!$E$4:$EN$4, 0) ) -> 22071 | FG18: =INDEX('2018'!$E$7:$EN$37, MATCH(EW18, '2018'!$A$7:$A$37, 0), MATCH(EW15, '2018'!$E$4:$EN$4, 0) ) -> 22814 | FH18: =INDEX('2019'!$E$7:$EN$37, MATCH(EW18, '2019'!$A$7:$A$37, 0), MATCH(EW15, '2019'!$E$4:$EN$4, 0) ) -> 23716 | FJ18: =$CI18 -> 3 | FK18: =$CJ18 -> Box Elder | FL18: =INDEX('2010'!$E$7:$EN$37, MATCH(FJ18, '2010'!$A$7:$A$37, 0), MATCH(FJ15, '2010'!$E$4:$EN$4, 0) ) -> 1051 | FM18: =INDEX('2011'!$E$7:$EN$37, MATCH(FJ18, '2011'!$A$7:$A$37, 0), MATCH(FJ15, '2011'!$E$4:$EN$4, 0) ) -> 1039 | FN18: =INDEX('2012'!$E$7:$EN$37, MATCH(FJ18, '2012'!$A$7:$A$37, 0), MATCH(FJ15, '2012'!$E$4:$EN$4, 0) ) -> 919 | FO18: =INDEX('2013'!$E$7:$EN$37, MATCH(FJ18, '2013'!$A$7:$A$37, 0), MATCH(FJ15, '2013'!$E$4:$EN$4, 0) ) -> 842 | FP18: =INDEX('2014'!$E$7:$EN$37, MATCH(FJ18, '2014'!$A$7:$A$37, 0), MATCH(FJ15, '2014'!$E$4:$EN$4, 0) ) -> 733 | FQ18: =INDEX('2015'!$E$7:$EN$37, MATCH(FJ18, '2015'!$A$7:$A$37, 0), MATCH(FJ15, '2015'!$E$4:$EN$4, 0) ) -> 716 | FR18: =INDEX('2016'!$E$7:$EN$37, MATCH(FJ18, '2016'!$A$7:$A$37, 0), MATCH(FJ15, '2016'!$E$4:$EN$4, 0) ) -> 853 | FS18: =INDEX('2017'!$E$7:$EN$37, MATCH(FJ18, '2017'!$A$7:$A$37, 0), MATCH(FJ15, '2017'!$E$4:$EN$4, 0) ) -> 883 | FT18: =INDEX('2018'!$E$7:$EN$37, MATCH(FJ18, '2018'!$A$7:$A$37, 0), MATCH(FJ15, '2018'!$E$4:$EN$4, 0) ) -> 1142 | FU18: =INDEX('2019'!$E$7:$EN$37, MATCH(FJ18, '2019'!$A$7:$A$37, 0), MATCH(FJ15, '2019'!$E$4:$EN$4, 0) ) -> 1255 | FW18: =$CI18 -> 3 | FX18: =$CJ18 -> Box Elder | FY18: =INDEX('2010'!$E$7:$EN$37, MATCH(FW18, '2010'!$A$7:$A$37, 0), MATCH(FW15, '2010'!$E$4:$EN$4, 0) ) -> 165 | FZ18: =INDEX('2011'!$E$7:$EN$37, MATCH(FW18, '2011'!$A$7:$A$37, 0), MATCH(FW15, '2011'!$E$4:$EN$4, 0) ) -> 170 | GA18: =INDEX('2012'!$E$7:$EN$37, MATCH(FW18, '2012'!$A$7:$A$37, 0), MATCH(FW15, '2012'!$E$4:$EN$4, 0) ) -> 151 | GB18: =INDEX('2013'!$E$7:$EN$37, MATCH(FW18, '2013'!$A$7:$A$37, 0), MATCH(FW15, '2013'!$E$4:$EN$4, 0) ) -> 151 | GC18: =INDEX('2014'!$E$7:$EN$37, MATCH(FW18, '2014'!$A$7:$A$37, 0), MATCH(FW15, '2014'!$E$4:$EN$4, 0) ) -> 165 | GD18: =INDEX('2015'!$E$7:$EN$37, MATCH(FW18, '2015'!$A$7:$A$37, 0), MATCH(FW15, '2015'!$E$4:$EN$4, 0) ) -> 146 | GE18: =INDEX('2016'!$E$7:$EN$37, MATCH(FW18, '2016'!$A$7:$A$37, 0), MATCH(FW15, '2016'!$E$4:$EN$4, 0) ) -> 111 | GF18: =INDEX('2017'!$E$7:$EN$37, MATCH(FW18, '2017'!$A$7:$A$37, 0), MATCH(FW15, '2017'!$E$4:$EN$4, 0) ) -> 131 | GG18: =INDEX('2018'!$E$7:$EN$37, MATCH(FW18, '2018'!$A$7:$A$37, 0), MATCH(FW15, '2018'!$E$4:$EN$4, 0) ) -> 166 | GH18: =INDEX('2019'!$E$7:$EN$37, MATCH(FW18, '2019'!$A$7:$A$37, 0), MATCH(FW15, '2019'!$E$4:$EN$4, 0) ) -> 120 | GJ18: =$CI18 -> 3 | GK18: =$CJ18 -> Box Elder | GL18: =INDEX('2010'!$E$7:$EN$37, MATCH(GJ18, '2010'!$A$7:$A$37, 0), MATCH(GJ15, '2010'!$E$4:$EN$4, 0) ) -> 578 | GM18: =INDEX('2011'!$E$7:$EN$37, MATCH(GJ18, '2011'!$A$7:$A$37, 0), MATCH(GJ15, '2011'!$E$4:$EN$4, 0) ) -> 550 | GN18: =INDEX('2012'!$E$7:$EN$37, MATCH(GJ18, '2012'!$A$7:$A$37, 0), MATCH(GJ15, '2012'!$E$4:$EN$4, 0) ) -> 488 | GO18: =INDEX('2013'!$E$7:$EN$37, MATCH(GJ18, '2013'!$A$7:$A$37, 0), MATCH(GJ15, '2013'!$E$4:$EN$4, 0) ) -> 448 | GP18: =INDEX('2014'!$E$7:$EN$37, MATCH(GJ18, '2014'!$A$7:$A$37, 0), MATCH(GJ15, '2014'!$E$4:$EN$4, 0) ) -> 329 | GQ18: =INDEX('2015'!$E$7:$EN$37, MATCH(GJ18, '2015'!$A$7:$A$37, 0), MATCH(GJ15, '2015'!$E$4:$EN$4, 0) ) -> 262 | GR18: =INDEX('2016'!$E$7:$EN$37, MATCH(GJ18, '2016'!$A$7:$A$37, 0), MATCH(GJ15, '2016'!$E$4:$EN$4, 0) ) -> 377 | GS18: =INDEX('2017'!$E$7:$EN$37, MATCH(GJ18, '2017'!$A$7:$A$37, 0), MATCH(GJ15, '2017'!$E$4:$EN$4, 0) ) -> 354 | GT18: =INDEX('2018'!$E$7:$EN$37, MATCH(GJ18, '2018'!$A$7:$A$37, 0), MATCH(GJ15, '2018'!$E$4:$EN$4, 0) ) -> 436 | GU18: =INDEX('2019'!$E$7:$EN$37, MATCH(GJ18, '2019'!$A$7:$A$37, 0), MATCH(GJ15, '2019'!$E$4:$EN$4, 0) ) -> 456
AY19: Home-Based-Job | AZ19: =INDEX($DK$7:$DT$13, MATCH(AY17, $DJ$7:$DJ$13,0), MATCH(AZ$6, $DK$6:$DT$6, 0)) -> 0.02394321 | BA19: =INDEX($DK$7:$DT$13, MATCH(AY17, $DJ$7:$DJ$13,0), MATCH(BA$6, $DK$6:$DT$6, 0)) -> 0.021674151 | BB19: =INDEX($DK$7:$DT$13, MATCH(AY17, $DJ$7:$DJ$13,0), MATCH(BB$6, $DK$6:$DT$6, 0)) -> 0.021495896 | BC19: =INDEX($DK$7:$DT$13, MATCH(AY17, $DJ$7:$DJ$13,0), MATCH(BC$6, $DK$6:$DT$6, 0)) -> 0.021443589 | BD19: =INDEX($DK$7:$DT$13, MATCH(AY17, $DJ$7:$DJ$13,0), MATCH(BD$6, $DK$6:$DT$6, 0)) -> 0.021136367 | BE19: =INDEX($DK$7:$DT$13, MATCH(AY17, $DJ$7:$DJ$13,0), MATCH(BE$6, $DK$6:$DT$6, 0)) -> 0.021146772 | BF19: =INDEX($DK$7:$DT$13, MATCH(AY17, $DJ$7:$DJ$13,0), MATCH(BF$6, $DK$6:$DT$6, 0)) -> 0.021408339 | BG19: =INDEX($DK$7:$DT$13, MATCH(AY17, $DJ$7:$DJ$13,0), MATCH(BG$6, $DK$6:$DT$6, 0)) -> 0.020739694 | BH19: =INDEX($DK$7:$DT$13, MATCH(AY17, $DJ$7:$DJ$13,0), MATCH(BH$6, $DK$6:$DT$6, 0)) -> 0.0227936 | BI19: =INDEX($DK$7:$DT$13, MATCH(AY17, $DJ$7:$DJ$13,0), MATCH(BI$6, $DK$6:$DT$6, 0)) -> 0.022409577 | CI19: 5 | CJ19: =VLOOKUP(CI19, lu_CoName, 2, FALSE) -> Cache | CK19: =CX19 + DK19 -> 0.053870467 | CL19: =CY19 + DL19 -> 0.045694404 | CM19: =CZ19 + DM19 -> 0.043328221 | CN19: =DA19 + DN19 -> 0.044274955 | CO19: =DB19 + DO19 -> 0.041536687 | CP19: =DC19 + DP19 -> 0.045870032 | CQ19: =DD19 + DQ19 -> 0.050949051 | CR19: =DE19 + DR19 -> 0.051726899 | ... CT19: =DG19 + DT19 -> 0.062955688 | CV19: =$CI19*10 + 0 -> 50 | CW19: =$CJ19 -> Cache | CX19: =IFERROR(DX19/EY19, 0) -> 0.027151187 | CY19: =IFERROR(DY19/EZ19, 0) -> 0.023059824 | CZ19: =IFERROR(DZ19/FA19, 0) -> 0.021587423 | DA19: =IFERROR(EA19/FB19, 0) -> 0.022175613 | DB19: =IFERROR(EB19/FC19, 0) -> 0.021269355 | DC19: =IFERROR(EC19/FD19, 0) -> 0.023036785 | DD19: =IFERROR(ED19/FE19, 0) -> 0.025211152 | DE19: =IFERROR(EE19/FF19, 0) -> 0.026157049 | ... DG19: =IFERROR(EG19/FH19, 0) -> 0.034557379 | DI19: =$CI19*10 + 0 -> 50 | DJ19: =$CJ19 -> Cache | DK19: =IFERROR(EK19/EY19, 0) -> 0.026719281 | DL19: =IFERROR(EL19/EZ19, 0) -> 0.02263458 | DM19: =IFERROR(EM19/FA19, 0) -> 0.021740798 | DN19: =IFERROR(EN19/FB19, 0) -> 0.022099342 | DO19: =IFERROR(EO19/FC19, 0) -> 0.020267332 | DP19: =IFERROR(EP19/FD19, 0) -> 0.022833247 | DQ19: =IFERROR(EQ19/FE19, 0) -> 0.025737898 | DR19: =IFERROR(ER19/FF19, 0) -> 0.02556985 | ... DT19: =IFERROR(ET19/FH19, 0) -> 0.028398309 | DV19: =$CI19*10 + 0 -> 50 | DW19: =$CJ19 -> Cache | DX19: =FL19 - EK19 -> 1383 | DY19: =FM19 - EL19 -> 1193 | DZ19: =FN19 - EM19 -> 1126 | EA19: =FO19 - EN19 -> 1163 | EB19: =FP19 - EO19 -> 1125 | EC19: =FQ19 - EP19 -> 1245 | ED19: =FR19 - EQ19 -> 1388 | EE19: =FS19 - ER19 -> 1470 | ... EG19: =FU19 - ET19 -> 2076 | EI19: =$CI19*10 + 0 -> 50 | EJ19: =$CJ19 -> Cache | EK19: =FY19 + GL19 -> 1361 | EL19: =FZ19 + GM19 -> 1171 | EM19: =GA19 + GN19 -> 1134 | EN19: =GB19 + GO19 -> 1159 | EO19: =GC19 + GP19 -> 1072 | EP19: =GD19 + GQ19 -> 1234 | EQ19: =GE19 + GR19 -> 1417 | ER19: =GF19 + GS19 -> 1437 | ... ET19: =GH19 + GU19 -> 1706 | EW19: =$CI19 -> 5 | EX19: =$CJ19 -> Cache | EY19: =INDEX('2010'!$E$7:$EN$37, MATCH(EW19, '2010'!$A$7:$A$37, 0), MATCH(EW15, '2010'!$E$4:$EN$4, 0) ) -> 50937 | EZ19: =INDEX('2011'!$E$7:$EN$37, MATCH(EW19, '2011'!$A$7:$A$37, 0), MATCH(EW15, '2011'!$E$4:$EN$4, 0) ) -> 51735 | FA19: =INDEX('2012'!$E$7:$EN$37, MATCH(EW19, '2012'!$A$7:$A$37, 0), MATCH(EW15, '2012'!$E$4:$EN$4, 0) ) -> 52160 | FB19: =INDEX('2013'!$E$7:$EN$37, MATCH(EW19, '2013'!$A$7:$A$37, 0), MATCH(EW15, '2013'!$E$4:$EN$4, 0) ) -> 52445 | FC19: =INDEX('2014'!$E$7:$EN$37, MATCH(EW19, '2014'!$A$7:$A$37, 0), MATCH(EW15, '2014'!$E$4:$EN$4, 0) ) -> 52893 | FD19: =INDEX('2015'!$E$7:$EN$37, MATCH(EW19, '2015'!$A$7:$A$37, 0), MATCH(EW15, '2015'!$E$4:$EN$4, 0) ) -> 54044 | FE19: =INDEX('2016'!$E$7:$EN$37, MATCH(EW19, '2016'!$A$7:$A$37, 0), MATCH(EW15, '2016'!$E$4:$EN$4, 0) ) -> 55055 | FF19: =INDEX('2017'!$E$7:$EN$37, MATCH(EW19, '2017'!$A$7:$A$37, 0), MATCH(EW15, '2017'!$E$4:$EN$4, 0) ) -> 56199 | FG19: =INDEX('2018'!$E$7:$EN$37, MATCH(EW19, '2018'!$A$7:$A$37, 0), MATCH(EW15, '2018'!$E$4:$EN$4, 0) ) -> 58265 | FH19: =INDEX('2019'!$E$7:$EN$37, MATCH(EW19, '2019'!$A$7:$A$37, 0), MATCH(EW15, '2019'!$E$4:$EN$4, 0) ) -> 60074 | FJ19: =$CI19 -> 5 | FK19: =$CJ19 -> Cache | FL19: =INDEX('2010'!$E$7:$EN$37, MATCH(FJ19, '2010'!$A$7:$A$37, 0), MATCH(FJ15, '2010'!$E$4:$EN$4, 0) ) -> 2744 | FM19: =INDEX('2011'!$E$7:$EN$37, MATCH(FJ19, '2011'!$A$7:$A$37, 0), MATCH(FJ15, '2011'!$E$4:$EN$4, 0) ) -> 2364 | FN19: =INDEX('2012'!$E$7:$EN$37, MATCH(FJ19, '2012'!$A$7:$A$37, 0), MATCH(FJ15, '2012'!$E$4:$EN$4, 0) ) -> 2260 | FO19: =INDEX('2013'!$E$7:$EN$37, MATCH(FJ19, '2013'!$A$7:$A$37, 0), MATCH(FJ15, '2013'!$E$4:$EN$4, 0) ) -> 2322 | FP19: =INDEX('2014'!$E$7:$EN$37, MATCH(FJ19, '2014'!$A$7:$A$37, 0), MATCH(FJ15, '2014'!$E$4:$EN$4, 0) ) -> 2197 | FQ19: =INDEX('2015'!$E$7:$EN$37, MATCH(FJ19, '2015'!$A$7:$A$37, 0), MATCH(FJ15, '2015'!$E$4:$EN$4, 0) ) -> 2479 | FR19: =INDEX('2016'!$E$7:$EN$37, MATCH(FJ19, '2016'!$A$7:$A$37, 0), MATCH(FJ15, '2016'!$E$4:$EN$4, 0) ) -> 2805 | FS19: =INDEX('2017'!$E$7:$EN$37, MATCH(FJ19, '2017'!$A$7:$A$37, 0), MATCH(FJ15, '2017'!$E$4:$EN$4, 0) ) -> 2907 | FT19: =INDEX('2018'!$E$7:$EN$37, MATCH(FJ19, '2018'!$A$7:$A$37, 0), MATCH(FJ15, '2018'!$E$4:$EN$4, 0) ) -> 3232 | FU19: =INDEX('2019'!$E$7:$EN$37, MATCH(FJ19, '2019'!$A$7:$A$37, 0), MATCH(FJ15, '2019'!$E$4:$EN$4, 0) ) -> 3782 | FW19: =$CI19 -> 5 | FX19: =$CJ19 -> Cache | FY19: =INDEX('2010'!$E$7:$EN$37, MATCH(FW19, '2010'!$A$7:$A$37, 0), MATCH(FW15, '2010'!$E$4:$EN$4, 0) ) -> 375 | FZ19: =INDEX('2011'!$E$7:$EN$37, MATCH(FW19, '2011'!$A$7:$A$37, 0), MATCH(FW15, '2011'!$E$4:$EN$4, 0) ) -> 334 | GA19: =INDEX('2012'!$E$7:$EN$37, MATCH(FW19, '2012'!$A$7:$A$37, 0), MATCH(FW15, '2012'!$E$4:$EN$4, 0) ) -> 327 | GB19: =INDEX('2013'!$E$7:$EN$37, MATCH(FW19, '2013'!$A$7:$A$37, 0), MATCH(FW15, '2013'!$E$4:$EN$4, 0) ) -> 331 | GC19: =INDEX('2014'!$E$7:$EN$37, MATCH(FW19, '2014'!$A$7:$A$37, 0), MATCH(FW15, '2014'!$E$4:$EN$4, 0) ) -> 312 | GD19: =INDEX('2015'!$E$7:$EN$37, MATCH(FW19, '2015'!$A$7:$A$37, 0), MATCH(FW15, '2015'!$E$4:$EN$4, 0) ) -> 456 | GE19: =INDEX('2016'!$E$7:$EN$37, MATCH(FW19, '2016'!$A$7:$A$37, 0), MATCH(FW15, '2016'!$E$4:$EN$4, 0) ) -> 565 | GF19: =INDEX('2017'!$E$7:$EN$37, MATCH(FW19, '2017'!$A$7:$A$37, 0), MATCH(FW15, '2017'!$E$4:$EN$4, 0) ) -> 662 | GG19: =INDEX('2018'!$E$7:$EN$37, MATCH(FW19, '2018'!$A$7:$A$37, 0), MATCH(FW15, '2018'!$E$4:$EN$4, 0) ) -> 798 | GH19: =INDEX('2019'!$E$7:$EN$37, MATCH(FW19, '2019'!$A$7:$A$37, 0), MATCH(FW15, '2019'!$E$4:$EN$4, 0) ) -> 893 | GJ19: =$CI19 -> 5 | GK19: =$CJ19 -> Cache | GL19: =INDEX('2010'!$E$7:$EN$37, MATCH(GJ19, '2010'!$A$7:$A$37, 0), MATCH(GJ15, '2010'!$E$4:$EN$4, 0) ) -> 986 | GM19: =INDEX('2011'!$E$7:$EN$37, MATCH(GJ19, '2011'!$A$7:$A$37, 0), MATCH(GJ15, '2011'!$E$4:$EN$4, 0) ) -> 837 | GN19: =INDEX('2012'!$E$7:$EN$37, MATCH(GJ19, '2012'!$A$7:$A$37, 0), MATCH(GJ15, '2012'!$E$4:$EN$4, 0) ) -> 807 | GO19: =INDEX('2013'!$E$7:$EN$37, MATCH(GJ19, '2013'!$A$7:$A$37, 0), MATCH(GJ15, '2013'!$E$4:$EN$4, 0) ) -> 828 | GP19: =INDEX('2014'!$E$7:$EN$37, MATCH(GJ19, '2014'!$A$7:$A$37, 0), MATCH(GJ15, '2014'!$E$4:$EN$4, 0) ) -> 760 | GQ19: =INDEX('2015'!$E$7:$EN$37, MATCH(GJ19, '2015'!$A$7:$A$37, 0), MATCH(GJ15, '2015'!$E$4:$EN$4, 0) ) -> 778 | GR19: =INDEX('2016'!$E$7:$EN$37, MATCH(GJ19, '2016'!$A$7:$A$37, 0), MATCH(GJ15, '2016'!$E$4:$EN$4, 0) ) -> 852 | GS19: =INDEX('2017'!$E$7:$EN$37, MATCH(GJ19, '2017'!$A$7:$A$37, 0), MATCH(GJ15, '2017'!$E$4:$EN$4, 0) ) -> 775 | GT19: =INDEX('2018'!$E$7:$EN$37, MATCH(GJ19, '2018'!$A$7:$A$37, 0), MATCH(GJ15, '2018'!$E$4:$EN$4, 0) ) -> 753 | GU19: =INDEX('2019'!$E$7:$EN$37, MATCH(GJ19, '2019'!$A$7:$A$37, 0), MATCH(GJ15, '2019'!$E$4:$EN$4, 0) ) -> 813
AY20: Telecommute | AZ20: =INDEX($CX$7:$DG$13, MATCH(AY17, $CW$7:$CW$13,0), MATCH(AZ$6, $CX$6:$DG$6, 0)) -> 0.020632471 | BA20: =INDEX($CX$7:$DG$13, MATCH(AY17, $CW$7:$CW$13,0), MATCH(BA$6, $CX$6:$DG$6, 0)) -> 0.025479704 | BB20: =INDEX($CX$7:$DG$13, MATCH(AY17, $CW$7:$CW$13,0), MATCH(BB$6, $CX$6:$DG$6, 0)) -> 0.023610364 | BC20: =INDEX($CX$7:$DG$13, MATCH(AY17, $CW$7:$CW$13,0), MATCH(BC$6, $CX$6:$DG$6, 0)) -> 0.025847373 | BD20: =INDEX($CX$7:$DG$13, MATCH(AY17, $CW$7:$CW$13,0), MATCH(BD$6, $CX$6:$DG$6, 0)) -> 0.028318695 | BE20: =INDEX($CX$7:$DG$13, MATCH(AY17, $CW$7:$CW$13,0), MATCH(BE$6, $CX$6:$DG$6, 0)) -> 0.031001316 | BF20: =INDEX($CX$7:$DG$13, MATCH(AY17, $CW$7:$CW$13,0), MATCH(BF$6, $CX$6:$DG$6, 0)) -> 0.03059087 | BG20: =INDEX($CX$7:$DG$13, MATCH(AY17, $CW$7:$CW$13,0), MATCH(BG$6, $CX$6:$DG$6, 0)) -> 0.034743804 | BH20: =INDEX($CX$7:$DG$13, MATCH(AY17, $CW$7:$CW$13,0), MATCH(BH$6, $CX$6:$DG$6, 0)) -> 0.035479773 | BI20: =INDEX($CX$7:$DG$13, MATCH(AY17, $CW$7:$CW$13,0), MATCH(BI$6, $CX$6:$DG$6, 0)) -> 0.036449019 | CI20: 7 | CJ20: =VLOOKUP(CI20, lu_CoName, 2, FALSE) -> Carbon | CK20: =CX20 + DK20 -> 0.034883721 | CL20: =CY20 + DL20 -> 0.026702115 | CM20: =CZ20 + DM20 -> 0.029777524 | CN20: =DA20 + DN20 -> 0.030474041 | CO20: =DB20 + DO20 -> 0.02980576 | CP20: =DC20 + DP20 -> 0.02583435 | CQ20: =DD20 + DQ20 -> 0.031452254 | CR20: =DE20 + DR20 -> 0.033025404 | ... CT20: =DG20 + DT20 -> 0.041319362 | CV20: =$CI20*10 + 0 -> 70 | CW20: =$CJ20 -> Carbon | CX20: =IFERROR(DX20/EY20, 0) -> 0.02 | CY20: =IFERROR(DY20/EZ20, 0) -> 0.014218009 | CZ20: =IFERROR(DZ20/FA20, 0) -> 0.014489447 | DA20: =IFERROR(EA20/FB20, 0) -> 0.017268623 | DB20: =IFERROR(EB20/FC20, 0) -> 0.014512168 | DC20: =IFERROR(EC20/FD20, 0) -> 0.013970507 | DD20: =IFERROR(ED20/FE20, 0) -> 0.019984104 | DE20: =IFERROR(EE20/FF20, 0) -> 0.019399538 | ... DG20: =IFERROR(EG20/FH20, 0) -> 0.015598952 | DI20: =$CI20*10 + 0 -> 70 | DJ20: =$CJ20 -> Carbon | DK20: =IFERROR(EK20/EY20, 0) -> 0.014883721 | DL20: =IFERROR(EL20/EZ20, 0) -> 0.012484106 | DM20: =IFERROR(EM20/FA20, 0) -> 0.015288078 | DN20: =IFERROR(EN20/FB20, 0) -> 0.013205418 | DO20: =IFERROR(EO20/FC20, 0) -> 0.015293592 | DP20: =IFERROR(EP20/FD20, 0) -> 0.011863843 | DQ20: =IFERROR(EQ20/FE20, 0) -> 0.01146815 | DR20: =IFERROR(ER20/FF20, 0) -> 0.013625866 | ... DT20: =IFERROR(ET20/FH20, 0) -> 0.02572041 | DV20: =$CI20*10 + 0 -> 70 | DW20: =$CJ20 -> Carbon | DX20: =FL20 - EK20 -> 172 | DY20: =FM20 - EL20 -> 123 | DZ20: =FN20 - EM20 -> 127 | EA20: =FO20 - EN20 -> 153 | EB20: =FP20 - EO20 -> 130 | EC20: =FQ20 - EP20 -> 126 | ED20: =FR20 - EQ20 -> 176 | EE20: =FS20 - ER20 -> 168 | ... EG20: =FU20 - ET20 -> 131 | EI20: =$CI20*10 + 0 -> 70 | EJ20: =$CJ20 -> Carbon | EK20: =FY20 + GL20 -> 128 | EL20: =FZ20 + GM20 -> 108 | EM20: =GA20 + GN20 -> 134 | EN20: =GB20 + GO20 -> 117 | EO20: =GC20 + GP20 -> 137 | EP20: =GD20 + GQ20 -> 107 | EQ20: =GE20 + GR20 -> 101 | ER20: =GF20 + GS20 -> 118 | ... ET20: =GH20 + GU20 -> 216 | EW20: =$CI20 -> 7 | EX20: =$CJ20 -> Carbon | EY20: =INDEX('2010'!$E$7:$EN$37, MATCH(EW20, '2010'!$A$7:$A$37, 0), MATCH(EW15, '2010'!$E$4:$EN$4, 0) ) -> 8600 | EZ20: =INDEX('2011'!$E$7:$EN$37, MATCH(EW20, '2011'!$A$7:$A$37, 0), MATCH(EW15, '2011'!$E$4:$EN$4, 0) ) -> 8651 | FA20: =INDEX('2012'!$E$7:$EN$37, MATCH(EW20, '2012'!$A$7:$A$37, 0), MATCH(EW15, '2012'!$E$4:$EN$4, 0) ) -> 8765 | FB20: =INDEX('2013'!$E$7:$EN$37, MATCH(EW20, '2013'!$A$7:$A$37, 0), MATCH(EW15, '2013'!$E$4:$EN$4, 0) ) -> 8860 | FC20: =INDEX('2014'!$E$7:$EN$37, MATCH(EW20, '2014'!$A$7:$A$37, 0), MATCH(EW15, '2014'!$E$4:$EN$4, 0) ) -> 8958 | FD20: =INDEX('2015'!$E$7:$EN$37, MATCH(EW20, '2015'!$A$7:$A$37, 0), MATCH(EW15, '2015'!$E$4:$EN$4, 0) ) -> 9019 | FE20: =INDEX('2016'!$E$7:$EN$37, MATCH(EW20, '2016'!$A$7:$A$37, 0), MATCH(EW15, '2016'!$E$4:$EN$4, 0) ) -> 8807 | FF20: =INDEX('2017'!$E$7:$EN$37, MATCH(EW20, '2017'!$A$7:$A$37, 0), MATCH(EW15, '2017'!$E$4:$EN$4, 0) ) -> 8660 | FG20: =INDEX('2018'!$E$7:$EN$37, MATCH(EW20, '2018'!$A$7:$A$37, 0), MATCH(EW15, '2018'!$E$4:$EN$4, 0) ) -> 8581 | FH20: =INDEX('2019'!$E$7:$EN$37, MATCH(EW20, '2019'!$A$7:$A$37, 0), MATCH(EW15, '2019'!$E$4:$EN$4, 0) ) -> 8398 | FJ20: =$CI20 -> 7 | FK20: =$CJ20 -> Carbon | FL20: =INDEX('2010'!$E$7:$EN$37, MATCH(FJ20, '2010'!$A$7:$A$37, 0), MATCH(FJ15, '2010'!$E$4:$EN$4, 0) ) -> 300 | FM20: =INDEX('2011'!$E$7:$EN$37, MATCH(FJ20, '2011'!$A$7:$A$37, 0), MATCH(FJ15, '2011'!$E$4:$EN$4, 0) ) -> 231 | FN20: =INDEX('2012'!$E$7:$EN$37, MATCH(FJ20, '2012'!$A$7:$A$37, 0), MATCH(FJ15, '2012'!$E$4:$EN$4, 0) ) -> 261 | FO20: =INDEX('2013'!$E$7:$EN$37, MATCH(FJ20, '2013'!$A$7:$A$37, 0), MATCH(FJ15, '2013'!$E$4:$EN$4, 0) ) -> 270 | FP20: =INDEX('2014'!$E$7:$EN$37, MATCH(FJ20, '2014'!$A$7:$A$37, 0), MATCH(FJ15, '2014'!$E$4:$EN$4, 0) ) -> 267 | FQ20: =INDEX('2015'!$E$7:$EN$37, MATCH(FJ20, '2015'!$A$7:$A$37, 0), MATCH(FJ15, '2015'!$E$4:$EN$4, 0) ) -> 233 | FR20: =INDEX('2016'!$E$7:$EN$37, MATCH(FJ20, '2016'!$A$7:$A$37, 0), MATCH(FJ15, '2016'!$E$4:$EN$4, 0) ) -> 277 | FS20: =INDEX('2017'!$E$7:$EN$37, MATCH(FJ20, '2017'!$A$7:$A$37, 0), MATCH(FJ15, '2017'!$E$4:$EN$4, 0) ) -> 286 | FT20: =INDEX('2018'!$E$7:$EN$37, MATCH(FJ20, '2018'!$A$7:$A$37, 0), MATCH(FJ15, '2018'!$E$4:$EN$4, 0) ) -> 376 | FU20: =INDEX('2019'!$E$7:$EN$37, MATCH(FJ20, '2019'!$A$7:$A$37, 0), MATCH(FJ15, '2019'!$E$4:$EN$4, 0) ) -> 347 | FW20: =$CI20 -> 7 | FX20: =$CJ20 -> Carbon | FY20: =INDEX('2010'!$E$7:$EN$37, MATCH(FW20, '2010'!$A$7:$A$37, 0), MATCH(FW15, '2010'!$E$4:$EN$4, 0) ) -> 15 | FZ20: =INDEX('2011'!$E$7:$EN$37, MATCH(FW20, '2011'!$A$7:$A$37, 0), MATCH(FW15, '2011'!$E$4:$EN$4, 0) ) -> 2 | GA20: =INDEX('2012'!$E$7:$EN$37, MATCH(FW20, '2012'!$A$7:$A$37, 0), MATCH(FW15, '2012'!$E$4:$EN$4, 0) ) -> 10 | GB20: =INDEX('2013'!$E$7:$EN$37, MATCH(FW20, '2013'!$A$7:$A$37, 0), MATCH(FW15, '2013'!$E$4:$EN$4, 0) ) -> 6 | GC20: =INDEX('2014'!$E$7:$EN$37, MATCH(FW20, '2014'!$A$7:$A$37, 0), MATCH(FW15, '2014'!$E$4:$EN$4, 0) ) -> 21 | GD20: =INDEX('2015'!$E$7:$EN$37, MATCH(FW20, '2015'!$A$7:$A$37, 0), MATCH(FW15, '2015'!$E$4:$EN$4, 0) ) -> 21 | GE20: =INDEX('2016'!$E$7:$EN$37, MATCH(FW20, '2016'!$A$7:$A$37, 0), MATCH(FW15, '2016'!$E$4:$EN$4, 0) ) -> 25 | GF20: =INDEX('2017'!$E$7:$EN$37, MATCH(FW20, '2017'!$A$7:$A$37, 0), MATCH(FW15, '2017'!$E$4:$EN$4, 0) ) -> 41 | GG20: =INDEX('2018'!$E$7:$EN$37, MATCH(FW20, '2018'!$A$7:$A$37, 0), MATCH(FW15, '2018'!$E$4:$EN$4, 0) ) -> 109 | GH20: =INDEX('2019'!$E$7:$EN$37, MATCH(FW20, '2019'!$A$7:$A$37, 0), MATCH(FW15, '2019'!$E$4:$EN$4, 0) ) -> 92 | GJ20: =$CI20 -> 7 | GK20: =$CJ20 -> Carbon | GL20: =INDEX('2010'!$E$7:$EN$37, MATCH(GJ20, '2010'!$A$7:$A$37, 0), MATCH(GJ15, '2010'!$E$4:$EN$4, 0) ) -> 113 | GM20: =INDEX('2011'!$E$7:$EN$37, MATCH(GJ20, '2011'!$A$7:$A$37, 0), MATCH(GJ15, '2011'!$E$4:$EN$4, 0) ) -> 106 | GN20: =INDEX('2012'!$E$7:$EN$37, MATCH(GJ20, '2012'!$A$7:$A$37, 0), MATCH(GJ15, '2012'!$E$4:$EN$4, 0) ) -> 124 | GO20: =INDEX('2013'!$E$7:$EN$37, MATCH(GJ20, '2013'!$A$7:$A$37, 0), MATCH(GJ15, '2013'!$E$4:$EN$4, 0) ) -> 111 | GP20: =INDEX('2014'!$E$7:$EN$37, MATCH(GJ20, '2014'!$A$7:$A$37, 0), MATCH(GJ15, '2014'!$E$4:$EN$4, 0) ) -> 116 | GQ20: =INDEX('2015'!$E$7:$EN$37, MATCH(GJ20, '2015'!$A$7:$A$37, 0), MATCH(GJ15, '2015'!$E$4:$EN$4, 0) ) -> 86 | GR20: =INDEX('2016'!$E$7:$EN$37, MATCH(GJ20, '2016'!$A$7:$A$37, 0), MATCH(GJ15, '2016'!$E$4:$EN$4, 0) ) -> 76 | GS20: =INDEX('2017'!$E$7:$EN$37, MATCH(GJ20, '2017'!$A$7:$A$37, 0), MATCH(GJ15, '2017'!$E$4:$EN$4, 0) ) -> 77 | GT20: =INDEX('2018'!$E$7:$EN$37, MATCH(GJ20, '2018'!$A$7:$A$37, 0), MATCH(GJ15, '2018'!$E$4:$EN$4, 0) ) -> 106 | GU20: =INDEX('2019'!$E$7:$EN$37, MATCH(GJ20, '2019'!$A$7:$A$37, 0), MATCH(GJ15, '2019'!$E$4:$EN$4, 0) ) -> 124
AY21: Total Work At Home | AZ21: =SUM(AZ19:AZ20) -> 0.044575681 | BA21: =SUM(BA19:BA20) -> 0.047153855 | BB21: =SUM(BB19:BB20) -> 0.045106261 | BC21: =SUM(BC19:BC20) -> 0.047290962 | BD21: =SUM(BD19:BD20) -> 0.049455062 | BE21: =SUM(BE19:BE20) -> 0.052148088 | BF21: =SUM(BF19:BF20) -> 0.05199921 | BG21: =SUM(BG19:BG20) -> 0.055483498 | ... BI21: =SUM(BI19:BI20) -> 0.058858596 | CI21: 9 | CJ21: =VLOOKUP(CI21, lu_CoName, 2, FALSE) -> Daggett | CK21: =CX21 + DK21 -> 0.092261905 | CL21: =CY21 + DL21 -> 0.10755814 | CM21: =CZ21 + DM21 -> 0.078066914 | CN21: =DA21 + DN21 -> 0.11864407 | CO21: =DB21 + DO21 -> 0.155 | CP21: =DC21 + DP21 -> 0.055813953 | CQ21: =DD21 + DQ21 -> 0.078853047 | CR21: =DE21 + DR21 -> 0.081272085 | ... CT21: =DG21 + DT21 -> 0.04290429 | CV21: =$CI21*10 + 0 -> 90 | CW21: =$CJ21 -> Daggett | CX21: =IFERROR(DX21/EY21, 0) -> 0 | CY21: =IFERROR(DY21/EZ21, 0) -> 0.014534884 | CZ21: =IFERROR(DZ21/FA21, 0) -> 0.011152416 | DA21: =IFERROR(EA21/FB21, 0) -> 0.0084745763 | DB21: =IFERROR(EB21/FC21, 0) -> 0.015 | DC21: =IFERROR(EC21/FD21, 0) -> 0.018604651 | DD21: =IFERROR(ED21/FE21, 0) -> 0.010752688 | DE21: =IFERROR(EE21/FF21, 0) -> 0.010600707 | ... DG21: =IFERROR(EG21/FH21, 0) -> 0 | DI21: =$CI21*10 + 0 -> 90 | DJ21: =$CJ21 -> Daggett | DK21: =IFERROR(EK21/EY21, 0) -> 0.092261905 | DL21: =IFERROR(EL21/EZ21, 0) -> 0.093023256 | DM21: =IFERROR(EM21/FA21, 0) -> 0.066914498 | DN21: =IFERROR(EN21/FB21, 0) -> 0.11016949 | DO21: =IFERROR(EO21/FC21, 0) -> 0.14 | DP21: =IFERROR(EP21/FD21, 0) -> 0.037209302 | DQ21: =IFERROR(EQ21/FE21, 0) -> 0.068100358 | DR21: =IFERROR(ER21/FF21, 0) -> 0.070671378 | ... DT21: =IFERROR(ET21/FH21, 0) -> 0.04290429 | DV21: =$CI21*10 + 0 -> 90 | DW21: =$CJ21 -> Daggett | DX21: =FL21 - EK21 -> 0 | DY21: =FM21 - EL21 -> 5 | DZ21: =FN21 - EM21 -> 3 | EA21: =FO21 - EN21 -> 2 | EB21: =FP21 - EO21 -> 3 | EC21: =FQ21 - EP21 -> 4 | ED21: =FR21 - EQ21 -> 3 | EE21: =FS21 - ER21 -> 3 | ... EG21: =FU21 - ET21 -> 0 | EI21: =$CI21*10 + 0 -> 90 | EJ21: =$CJ21 -> Daggett | EK21: =FY21 + GL21 -> 31 | EL21: =FZ21 + GM21 -> 32 | EM21: =GA21 + GN21 -> 18 | EN21: =GB21 + GO21 -> 26 | EO21: =GC21 + GP21 -> 28 | EP21: =GD21 + GQ21 -> 8 | EQ21: =GE21 + GR21 -> 19 | ER21: =GF21 + GS21 -> 20 | ... ET21: =GH21 + GU21 -> 13 | EW21: =$CI21 -> 9 | EX21: =$CJ21 -> Daggett | EY21: =INDEX('2010'!$E$7:$EN$37, MATCH(EW21, '2010'!$A$7:$A$37, 0), MATCH(EW15, '2010'!$E$4:$EN$4, 0) ) -> 336 | EZ21: =INDEX('2011'!$E$7:$EN$37, MATCH(EW21, '2011'!$A$7:$A$37, 0), MATCH(EW15, '2011'!$E$4:$EN$4, 0) ) -> 344 | FA21: =INDEX('2012'!$E$7:$EN$37, MATCH(EW21, '2012'!$A$7:$A$37, 0), MATCH(EW15, '2012'!$E$4:$EN$4, 0) ) -> 269 | FB21: =INDEX('2013'!$E$7:$EN$37, MATCH(EW21, '2013'!$A$7:$A$37, 0), MATCH(EW15, '2013'!$E$4:$EN$4, 0) ) -> 236 | FC21: =INDEX('2014'!$E$7:$EN$37, MATCH(EW21, '2014'!$A$7:$A$37, 0), MATCH(EW15, '2014'!$E$4:$EN$4, 0) ) -> 200 | FD21: =INDEX('2015'!$E$7:$EN$37, MATCH(EW21, '2015'!$A$7:$A$37, 0), MATCH(EW15, '2015'!$E$4:$EN$4, 0) ) -> 215 | FE21: =INDEX('2016'!$E$7:$EN$37, MATCH(EW21, '2016'!$A$7:$A$37, 0), MATCH(EW15, '2016'!$E$4:$EN$4, 0) ) -> 279 | FF21: =INDEX('2017'!$E$7:$EN$37, MATCH(EW21, '2017'!$A$7:$A$37, 0), MATCH(EW15, '2017'!$E$4:$EN$4, 0) ) -> 283 | FG21: =INDEX('2018'!$E$7:$EN$37, MATCH(EW21, '2018'!$A$7:$A$37, 0), MATCH(EW15, '2018'!$E$4:$EN$4, 0) ) -> 250 | FH21: =INDEX('2019'!$E$7:$EN$37, MATCH(EW21, '2019'!$A$7:$A$37, 0), MATCH(EW15, '2019'!$E$4:$EN$4, 0) ) -> 303 | FJ21: =$CI21 -> 9 | FK21: =$CJ21 -> Daggett | FL21: =INDEX('2010'!$E$7:$EN$37, MATCH(FJ21, '2010'!$A$7:$A$37, 0), MATCH(FJ15, '2010'!$E$4:$EN$4, 0) ) -> 31 | FM21: =INDEX('2011'!$E$7:$EN$37, MATCH(FJ21, '2011'!$A$7:$A$37, 0), MATCH(FJ15, '2011'!$E$4:$EN$4, 0) ) -> 37 | FN21: =INDEX('2012'!$E$7:$EN$37, MATCH(FJ21, '2012'!$A$7:$A$37, 0), MATCH(FJ15, '2012'!$E$4:$EN$4, 0) ) -> 21 | FO21: =INDEX('2013'!$E$7:$EN$37, MATCH(FJ21, '2013'!$A$7:$A$37, 0), MATCH(FJ15, '2013'!$E$4:$EN$4, 0) ) -> 28 | FP21: =INDEX('2014'!$E$7:$EN$37, MATCH(FJ21, '2014'!$A$7:$A$37, 0), MATCH(FJ15, '2014'!$E$4:$EN$4, 0) ) -> 31 | FQ21: =INDEX('2015'!$E$7:$EN$37, MATCH(FJ21, '2015'!$A$7:$A$37, 0), MATCH(FJ15, '2015'!$E$4:$EN$4, 0) ) -> 12 | FR21: =INDEX('2016'!$E$7:$EN$37, MATCH(FJ21, '2016'!$A$7:$A$37, 0), MATCH(FJ15, '2016'!$E$4:$EN$4, 0) ) -> 22 | FS21: =INDEX('2017'!$E$7:$EN$37, MATCH(FJ21, '2017'!$A$7:$A$37, 0), MATCH(FJ15, '2017'!$E$4:$EN$4, 0) ) -> 23 | FT21: =INDEX('2018'!$E$7:$EN$37, MATCH(FJ21, '2018'!$A$7:$A$37, 0), MATCH(FJ15, '2018'!$E$4:$EN$4, 0) ) -> 12 | FU21: =INDEX('2019'!$E$7:$EN$37, MATCH(FJ21, '2019'!$A$7:$A$37, 0), MATCH(FJ15, '2019'!$E$4:$EN$4, 0) ) -> 13 | FW21: =$CI21 -> 9 | FX21: =$CJ21 -> Daggett | FY21: =INDEX('2010'!$E$7:$EN$37, MATCH(FW21, '2010'!$A$7:$A$37, 0), MATCH(FW15, '2010'!$E$4:$EN$4, 0) ) -> 31 | FZ21: =INDEX('2011'!$E$7:$EN$37, MATCH(FW21, '2011'!$A$7:$A$37, 0), MATCH(FW15, '2011'!$E$4:$EN$4, 0) ) -> 32 | GA21: =INDEX('2012'!$E$7:$EN$37, MATCH(FW21, '2012'!$A$7:$A$37, 0), MATCH(FW15, '2012'!$E$4:$EN$4, 0) ) -> 18 | GB21: =INDEX('2013'!$E$7:$EN$37, MATCH(FW21, '2013'!$A$7:$A$37, 0), MATCH(FW15, '2013'!$E$4:$EN$4, 0) ) -> 20 | GC21: =INDEX('2014'!$E$7:$EN$37, MATCH(FW21, '2014'!$A$7:$A$37, 0), MATCH(FW15, '2014'!$E$4:$EN$4, 0) ) -> 22 | GD21: =INDEX('2015'!$E$7:$EN$37, MATCH(FW21, '2015'!$A$7:$A$37, 0), MATCH(FW15, '2015'!$E$4:$EN$4, 0) ) -> 0 | GE21: =INDEX('2016'!$E$7:$EN$37, MATCH(FW21, '2016'!$A$7:$A$37, 0), MATCH(FW15, '2016'!$E$4:$EN$4, 0) ) -> 10 | GF21: =INDEX('2017'!$E$7:$EN$37, MATCH(FW21, '2017'!$A$7:$A$37, 0), MATCH(FW15, '2017'!$E$4:$EN$4, 0) ) -> 11 | GG21: =INDEX('2018'!$E$7:$EN$37, MATCH(FW21, '2018'!$A$7:$A$37, 0), MATCH(FW15, '2018'!$E$4:$EN$4, 0) ) -> 9 | GH21: =INDEX('2019'!$E$7:$EN$37, MATCH(FW21, '2019'!$A$7:$A$37, 0), MATCH(FW15, '2019'!$E$4:$EN$4, 0) ) -> 13 | GJ21: =$CI21 -> 9 | GK21: =$CJ21 -> Daggett | GL21: =INDEX('2010'!$E$7:$EN$37, MATCH(GJ21, '2010'!$A$7:$A$37, 0), MATCH(GJ15, '2010'!$E$4:$EN$4, 0) ) -> 0 | GM21: =INDEX('2011'!$E$7:$EN$37, MATCH(GJ21, '2011'!$A$7:$A$37, 0), MATCH(GJ15, '2011'!$E$4:$EN$4, 0) ) -> 0 | GN21: =INDEX('2012'!$E$7:$EN$37, MATCH(GJ21, '2012'!$A$7:$A$37, 0), MATCH(GJ15, '2012'!$E$4:$EN$4, 0) ) -> 0 | GO21: =INDEX('2013'!$E$7:$EN$37, MATCH(GJ21, '2013'!$A$7:$A$37, 0), MATCH(GJ15, '2013'!$E$4:$EN$4, 0) ) -> 6 | GP21: =INDEX('2014'!$E$7:$EN$37, MATCH(GJ21, '2014'!$A$7:$A$37, 0), MATCH(GJ15, '2014'!$E$4:$EN$4, 0) ) -> 6 | GQ21: =INDEX('2015'!$E$7:$EN$37, MATCH(GJ21, '2015'!$A$7:$A$37, 0), MATCH(GJ15, '2015'!$E$4:$EN$4, 0) ) -> 8 | GR21: =INDEX('2016'!$E$7:$EN$37, MATCH(GJ21, '2016'!$A$7:$A$37, 0), MATCH(GJ15, '2016'!$E$4:$EN$4, 0) ) -> 9 | GS21: =INDEX('2017'!$E$7:$EN$37, MATCH(GJ21, '2017'!$A$7:$A$37, 0), MATCH(GJ15, '2017'!$E$4:$EN$4, 0) ) -> 9 | GT21: =INDEX('2018'!$E$7:$EN$37, MATCH(GJ21, '2018'!$A$7:$A$37, 0), MATCH(GJ15, '2018'!$E$4:$EN$4, 0) ) -> 0 | GU21: =INDEX('2019'!$E$7:$EN$37, MATCH(GJ21, '2019'!$A$7:$A$37, 0), MATCH(GJ15, '2019'!$E$4:$EN$4, 0) ) -> 0
CI22: 11 | CJ22: =VLOOKUP(CI22, lu_CoName, 2, FALSE) -> Davis | CK22: =CX22 + DK22 -> 0.044575681 | CL22: =CY22 + DL22 -> 0.047153855 | CM22: =CZ22 + DM22 -> 0.045106261 | CN22: =DA22 + DN22 -> 0.047290962 | CO22: =DB22 + DO22 -> 0.049455062 | CP22: =DC22 + DP22 -> 0.052148088 | CQ22: =DD22 + DQ22 -> 0.05199921 | CR22: =DE22 + DR22 -> 0.055483498 | ... CT22: =DG22 + DT22 -> 0.058858596 | CV22: =$CI22*10 + 0 -> 110 | CW22: =$CJ22 -> Davis | CX22: =IFERROR(DX22/EY22, 0) -> 0.020632471 | CY22: =IFERROR(DY22/EZ22, 0) -> 0.025479704 | CZ22: =IFERROR(DZ22/FA22, 0) -> 0.023610364 | DA22: =IFERROR(EA22/FB22, 0) -> 0.025847373 | DB22: =IFERROR(EB22/FC22, 0) -> 0.028318695 | DC22: =IFERROR(EC22/FD22, 0) -> 0.031001316 | DD22: =IFERROR(ED22/FE22, 0) -> 0.03059087 | DE22: =IFERROR(EE22/FF22, 0) -> 0.034743804 | ... DG22: =IFERROR(EG22/FH22, 0) -> 0.036449019 | DI22: =$CI22*10 + 0 -> 110 | DJ22: =$CJ22 -> Davis | DK22: =IFERROR(EK22/EY22, 0) -> 0.02394321 | DL22: =IFERROR(EL22/EZ22, 0) -> 0.021674151 | DM22: =IFERROR(EM22/FA22, 0) -> 0.021495896 | DN22: =IFERROR(EN22/FB22, 0) -> 0.021443589 | DO22: =IFERROR(EO22/FC22, 0) -> 0.021136367 | DP22: =IFERROR(EP22/FD22, 0) -> 0.021146772 | DQ22: =IFERROR(EQ22/FE22, 0) -> 0.021408339 | DR22: =IFERROR(ER22/FF22, 0) -> 0.020739694 | ... DT22: =IFERROR(ET22/FH22, 0) -> 0.022409577 | DV22: =$CI22*10 + 0 -> 110 | DW22: =$CJ22 -> Davis | DX22: =FL22 - EK22 -> 2767 | DY22: =FM22 - EL22 -> 3495 | DZ22: =FN22 - EM22 -> 3294 | EA22: =FO22 - EN22 -> 3639 | EB22: =FP22 - EO22 -> 4069 | EC22: =FQ22 - EP22 -> 4593 | ED22: =FR22 - EQ22 -> 4644 | EE22: =FS22 - ER22 -> 5411 | ... EG22: =FU22 - ET22 -> 5992 | EI22: =$CI22*10 + 0 -> 110 | EJ22: =$CJ22 -> Davis | EK22: =FY22 + GL22 -> 3211 | EL22: =FZ22 + GM22 -> 2973 | EM22: =GA22 + GN22 -> 2999 | EN22: =GB22 + GO22 -> 3019 | EO22: =GC22 + GP22 -> 3037 | EP22: =GD22 + GQ22 -> 3133 | EQ22: =GE22 + GR22 -> 3250 | ER22: =GF22 + GS22 -> 3230 | ... ET22: =GH22 + GU22 -> 3684 | EW22: =$CI22 -> 11 | EX22: =$CJ22 -> Davis | EY22: =INDEX('2010'!$E$7:$EN$37, MATCH(EW22, '2010'!$A$7:$A$37, 0), MATCH(EW15, '2010'!$E$4:$EN$4, 0) ) -> 134109 | EZ22: =INDEX('2011'!$E$7:$EN$37, MATCH(EW22, '2011'!$A$7:$A$37, 0), MATCH(EW15, '2011'!$E$4:$EN$4, 0) ) -> 137168 | FA22: =INDEX('2012'!$E$7:$EN$37, MATCH(EW22, '2012'!$A$7:$A$37, 0), MATCH(EW15, '2012'!$E$4:$EN$4, 0) ) -> 139515 | FB22: =INDEX('2013'!$E$7:$EN$37, MATCH(EW22, '2013'!$A$7:$A$37, 0), MATCH(EW15, '2013'!$E$4:$EN$4, 0) ) -> 140788 | FC22: =INDEX('2014'!$E$7:$EN$37, MATCH(EW22, '2014'!$A$7:$A$37, 0), MATCH(EW15, '2014'!$E$4:$EN$4, 0) ) -> 143686 | FD22: =INDEX('2015'!$E$7:$EN$37, MATCH(EW22, '2015'!$A$7:$A$37, 0), MATCH(EW15, '2015'!$E$4:$EN$4, 0) ) -> 148155 | FE22: =INDEX('2016'!$E$7:$EN$37, MATCH(EW22, '2016'!$A$7:$A$37, 0), MATCH(EW15, '2016'!$E$4:$EN$4, 0) ) -> 151810 | FF22: =INDEX('2017'!$E$7:$EN$37, MATCH(EW22, '2017'!$A$7:$A$37, 0), MATCH(EW15, '2017'!$E$4:$EN$4, 0) ) -> 155740 | FG22: =INDEX('2018'!$E$7:$EN$37, MATCH(EW22, '2018'!$A$7:$A$37, 0), MATCH(EW15, '2018'!$E$4:$EN$4, 0) ) -> 158992 | FH22: =INDEX('2019'!$E$7:$EN$37, MATCH(EW22, '2019'!$A$7:$A$37, 0), MATCH(EW15, '2019'!$E$4:$EN$4, 0) ) -> 164394 | FJ22: =$CI22 -> 11 | FK22: =$CJ22 -> Davis | FL22: =INDEX('2010'!$E$7:$EN$37, MATCH(FJ22, '2010'!$A$7:$A$37, 0), MATCH(FJ15, '2010'!$E$4:$EN$4, 0) ) -> 5978 | FM22: =INDEX('2011'!$E$7:$EN$37, MATCH(FJ22, '2011'!$A$7:$A$37, 0), MATCH(FJ15, '2011'!$E$4:$EN$4, 0) ) -> 6468 | FN22: =INDEX('2012'!$E$7:$EN$37, MATCH(FJ22, '2012'!$A$7:$A$37, 0), MATCH(FJ15, '2012'!$E$4:$EN$4, 0) ) -> 6293 | FO22: =INDEX('2013'!$E$7:$EN$37, MATCH(FJ22, '2013'!$A$7:$A$37, 0), MATCH(FJ15, '2013'!$E$4:$EN$4, 0) ) -> 6658 | FP22: =INDEX('2014'!$E$7:$EN$37, MATCH(FJ22, '2014'!$A$7:$A$37, 0), MATCH(FJ15, '2014'!$E$4:$EN$4, 0) ) -> 7106 | FQ22: =INDEX('2015'!$E$7:$EN$37, MATCH(FJ22, '2015'!$A$7:$A$37, 0), MATCH(FJ15, '2015'!$E$4:$EN$4, 0) ) -> 7726 | FR22: =INDEX('2016'!$E$7:$EN$37, MATCH(FJ22, '2016'!$A$7:$A$37, 0), MATCH(FJ15, '2016'!$E$4:$EN$4, 0) ) -> 7894 | FS22: =INDEX('2017'!$E$7:$EN$37, MATCH(FJ22, '2017'!$A$7:$A$37, 0), MATCH(FJ15, '2017'!$E$4:$EN$4, 0) ) -> 8641 | FT22: =INDEX('2018'!$E$7:$EN$37, MATCH(FJ22, '2018'!$A$7:$A$37, 0), MATCH(FJ15, '2018'!$E$4:$EN$4, 0) ) -> 9265 | FU22: =INDEX('2019'!$E$7:$EN$37, MATCH(FJ22, '2019'!$A$7:$A$37, 0), MATCH(FJ15, '2019'!$E$4:$EN$4, 0) ) -> 9676 | FW22: =$CI22 -> 11 | FX22: =$CJ22 -> Davis | FY22: =INDEX('2010'!$E$7:$EN$37, MATCH(FW22, '2010'!$A$7:$A$37, 0), MATCH(FW15, '2010'!$E$4:$EN$4, 0) ) -> 879 | FZ22: =INDEX('2011'!$E$7:$EN$37, MATCH(FW22, '2011'!$A$7:$A$37, 0), MATCH(FW15, '2011'!$E$4:$EN$4, 0) ) -> 805 | GA22: =INDEX('2012'!$E$7:$EN$37, MATCH(FW22, '2012'!$A$7:$A$37, 0), MATCH(FW15, '2012'!$E$4:$EN$4, 0) ) -> 781 | GB22: =INDEX('2013'!$E$7:$EN$37, MATCH(FW22, '2013'!$A$7:$A$37, 0), MATCH(FW15, '2013'!$E$4:$EN$4, 0) ) -> 798 | GC22: =INDEX('2014'!$E$7:$EN$37, MATCH(FW22, '2014'!$A$7:$A$37, 0), MATCH(FW15, '2014'!$E$4:$EN$4, 0) ) -> 832 | GD22: =INDEX('2015'!$E$7:$EN$37, MATCH(FW22, '2015'!$A$7:$A$37, 0), MATCH(FW15, '2015'!$E$4:$EN$4, 0) ) -> 957 | GE22: =INDEX('2016'!$E$7:$EN$37, MATCH(FW22, '2016'!$A$7:$A$37, 0), MATCH(FW15, '2016'!$E$4:$EN$4, 0) ) -> 1053 | GF22: =INDEX('2017'!$E$7:$EN$37, MATCH(FW22, '2017'!$A$7:$A$37, 0), MATCH(FW15, '2017'!$E$4:$EN$4, 0) ) -> 1218 | GG22: =INDEX('2018'!$E$7:$EN$37, MATCH(FW22, '2018'!$A$7:$A$37, 0), MATCH(FW15, '2018'!$E$4:$EN$4, 0) ) -> 1423 | GH22: =INDEX('2019'!$E$7:$EN$37, MATCH(FW22, '2019'!$A$7:$A$37, 0), MATCH(FW15, '2019'!$E$4:$EN$4, 0) ) -> 1626 | GJ22: =$CI22 -> 11 | GK22: =$CJ22 -> Davis | GL22: =INDEX('2010'!$E$7:$EN$37, MATCH(GJ22, '2010'!$A$7:$A$37, 0), MATCH(GJ15, '2010'!$E$4:$EN$4, 0) ) -> 2332 | GM22: =INDEX('2011'!$E$7:$EN$37, MATCH(GJ22, '2011'!$A$7:$A$37, 0), MATCH(GJ15, '2011'!$E$4:$EN$4, 0) ) -> 2168 | GN22: =INDEX('2012'!$E$7:$EN$37, MATCH(GJ22, '2012'!$A$7:$A$37, 0), MATCH(GJ15, '2012'!$E$4:$EN$4, 0) ) -> 2218 | GO22: =INDEX('2013'!$E$7:$EN$37, MATCH(GJ22, '2013'!$A$7:$A$37, 0), MATCH(GJ15, '2013'!$E$4:$EN$4, 0) ) -> 2221 | GP22: =INDEX('2014'!$E$7:$EN$37, MATCH(GJ22, '2014'!$A$7:$A$37, 0), MATCH(GJ15, '2014'!$E$4:$EN$4, 0) ) -> 2205 | GQ22: =INDEX('2015'!$E$7:$EN$37, MATCH(GJ22, '2015'!$A$7:$A$37, 0), MATCH(GJ15, '2015'!$E$4:$EN$4, 0) ) -> 2176 | GR22: =INDEX('2016'!$E$7:$EN$37, MATCH(GJ22, '2016'!$A$7:$A$37, 0), MATCH(GJ15, '2016'!$E$4:$EN$4, 0) ) -> 2197 | GS22: =INDEX('2017'!$E$7:$EN$37, MATCH(GJ22, '2017'!$A$7:$A$37, 0), MATCH(GJ15, '2017'!$E$4:$EN$4, 0) ) -> 2012 | GT22: =INDEX('2018'!$E$7:$EN$37, MATCH(GJ22, '2018'!$A$7:$A$37, 0), MATCH(GJ15, '2018'!$E$4:$EN$4, 0) ) -> 2201 | GU22: =INDEX('2019'!$E$7:$EN$37, MATCH(GJ22, '2019'!$A$7:$A$37, 0), MATCH(GJ15, '2019'!$E$4:$EN$4, 0) ) -> 2058
AX23: 35 | AY23: =VLOOKUP(AX23, lu_CoName, 2, FALSE) -> Salt Lake | CI23: 13 | CJ23: =VLOOKUP(CI23, lu_CoName, 2, FALSE) -> Duchesne | CK23: =CX23 + DK23 -> 0.050149594 | CL23: =CY23 + DL23 -> 0.046601406 | CM23: =CZ23 + DM23 -> 0.035044825 | CN23: =DA23 + DN23 -> 0.03659348 | CO23: =DB23 + DO23 -> 0.029887758 | CP23: =DC23 + DP23 -> 0.030806909 | CQ23: =DD23 + DQ23 -> 0.046913262 | CR23: =DE23 + DR23 -> 0.066683732 | ... CT23: =DG23 + DT23 -> 0.098852604 | CV23: =$CI23*10 + 0 -> 130 | CW23: =$CJ23 -> Duchesne | CX23: =IFERROR(DX23/EY23, 0) -> 0.02293774 | CY23: =IFERROR(DY23/EZ23, 0) -> 0.02040535 | CZ23: =IFERROR(DZ23/FA23, 0) -> 0.018065743 | DA23: =IFERROR(EA23/FB23, 0) -> 0.018895542 | DB23: =IFERROR(EB23/FC23, 0) -> 0.014748108 | DC23: =IFERROR(EC23/FD23, 0) -> 0.013663315 | DD23: =IFERROR(ED23/FE23, 0) -> 0.020621214 | DE23: =IFERROR(EE23/FF23, 0) -> 0.027902214 | ... DG23: =IFERROR(EG23/FH23, 0) -> 0.037952339 | DI23: =$CI23*10 + 0 -> 130 | DJ23: =$CJ23 -> Duchesne | DK23: =IFERROR(EK23/EY23, 0) -> 0.027211854 | DL23: =IFERROR(EL23/EZ23, 0) -> 0.026196057 | DM23: =IFERROR(EM23/FA23, 0) -> 0.016979082 | DN23: =IFERROR(EN23/FB23, 0) -> 0.017697937 | DO23: =IFERROR(EO23/FC23, 0) -> 0.01513965 | DP23: =IFERROR(EP23/FD23, 0) -> 0.017143594 | DQ23: =IFERROR(EQ23/FE23, 0) -> 0.026292048 | DR23: =IFERROR(ER23/FF23, 0) -> 0.038781518 | ... DT23: =IFERROR(ET23/FH23, 0) -> 0.060900265 | DV23: =$CI23*10 + 0 -> 130 | DW23: =$CJ23 -> Duchesne | DX23: =FL23 - EK23 -> 161 | DY23: =FM23 - EL23 -> 148 | DZ23: =FN23 - EM23 -> 133 | EA23: =FO23 - EN23 -> 142 | EB23: =FP23 - EO23 -> 113 | EC23: =FQ23 - EP23 -> 106 | ED23: =FR23 - EQ23 -> 160 | EE23: =FS23 - ER23 -> 218 | ... EG23: =FU23 - ET23 -> 301 | EI23: =$CI23*10 + 0 -> 130 | EJ23: =$CJ23 -> Duchesne | EK23: =FY23 + GL23 -> 191 | EL23: =FZ23 + GM23 -> 190 | EM23: =GA23 + GN23 -> 125 | EN23: =GB23 + GO23 -> 133 | EO23: =GC23 + GP23 -> 116 | EP23: =GD23 + GQ23 -> 133 | EQ23: =GE23 + GR23 -> 204 | ER23: =GF23 + GS23 -> 303 | ... ET23: =GH23 + GU23 -> 483 | EW23: =$CI23 -> 13 | EX23: =$CJ23 -> Duchesne | EY23: =INDEX('2010'!$E$7:$EN$37, MATCH(EW23, '2010'!$A$7:$A$37, 0), MATCH(EW15, '2010'!$E$4:$EN$4, 0) ) -> 7019 | EZ23: =INDEX('2011'!$E$7:$EN$37, MATCH(EW23, '2011'!$A$7:$A$37, 0), MATCH(EW15, '2011'!$E$4:$EN$4, 0) ) -> 7253 | FA23: =INDEX('2012'!$E$7:$EN$37, MATCH(EW23, '2012'!$A$7:$A$37, 0), MATCH(EW15, '2012'!$E$4:$EN$4, 0) ) -> 7362 | FB23: =INDEX('2013'!$E$7:$EN$37, MATCH(EW23, '2013'!$A$7:$A$37, 0), MATCH(EW15, '2013'!$E$4:$EN$4, 0) ) -> 7515 | FC23: =INDEX('2014'!$E$7:$EN$37, MATCH(EW23, '2014'!$A$7:$A$37, 0), MATCH(EW15, '2014'!$E$4:$EN$4, 0) ) -> 7662 | FD23: =INDEX('2015'!$E$7:$EN$37, MATCH(EW23, '2015'!$A$7:$A$37, 0), MATCH(EW15, '2015'!$E$4:$EN$4, 0) ) -> 7758 | FE23: =INDEX('2016'!$E$7:$EN$37, MATCH(EW23, '2016'!$A$7:$A$37, 0), MATCH(EW15, '2016'!$E$4:$EN$4, 0) ) -> 7759 | FF23: =INDEX('2017'!$E$7:$EN$37, MATCH(EW23, '2017'!$A$7:$A$37, 0), MATCH(EW15, '2017'!$E$4:$EN$4, 0) ) -> 7813 | FG23: =INDEX('2018'!$E$7:$EN$37, MATCH(EW23, '2018'!$A$7:$A$37, 0), MATCH(EW15, '2018'!$E$4:$EN$4, 0) ) -> 7928 | FH23: =INDEX('2019'!$E$7:$EN$37, MATCH(EW23, '2019'!$A$7:$A$37, 0), MATCH(EW15, '2019'!$E$4:$EN$4, 0) ) -> 7931 | FJ23: =$CI23 -> 13 | FK23: =$CJ23 -> Duchesne | FL23: =INDEX('2010'!$E$7:$EN$37, MATCH(FJ23, '2010'!$A$7:$A$37, 0), MATCH(FJ15, '2010'!$E$4:$EN$4, 0) ) -> 352 | FM23: =INDEX('2011'!$E$7:$EN$37, MATCH(FJ23, '2011'!$A$7:$A$37, 0), MATCH(FJ15, '2011'!$E$4:$EN$4, 0) ) -> 338 | FN23: =INDEX('2012'!$E$7:$EN$37, MATCH(FJ23, '2012'!$A$7:$A$37, 0), MATCH(FJ15, '2012'!$E$4:$EN$4, 0) ) -> 258 | FO23: =INDEX('2013'!$E$7:$EN$37, MATCH(FJ23, '2013'!$A$7:$A$37, 0), MATCH(FJ15, '2013'!$E$4:$EN$4, 0) ) -> 275 | FP23: =INDEX('2014'!$E$7:$EN$37, MATCH(FJ23, '2014'!$A$7:$A$37, 0), MATCH(FJ15, '2014'!$E$4:$EN$4, 0) ) -> 229 | FQ23: =INDEX('2015'!$E$7:$EN$37, MATCH(FJ23, '2015'!$A$7:$A$37, 0), MATCH(FJ15, '2015'!$E$4:$EN$4, 0) ) -> 239 | FR23: =INDEX('2016'!$E$7:$EN$37, MATCH(FJ23, '2016'!$A$7:$A$37, 0), MATCH(FJ15, '2016'!$E$4:$EN$4, 0) ) -> 364 | FS23: =INDEX('2017'!$E$7:$EN$37, MATCH(FJ23, '2017'!$A$7:$A$37, 0), MATCH(FJ15, '2017'!$E$4:$EN$4, 0) ) -> 521 | FT23: =INDEX('2018'!$E$7:$EN$37, MATCH(FJ23, '2018'!$A$7:$A$37, 0), MATCH(FJ15, '2018'!$E$4:$EN$4, 0) ) -> 675 | FU23: =INDEX('2019'!$E$7:$EN$37, MATCH(FJ23, '2019'!$A$7:$A$37, 0), MATCH(FJ15, '2019'!$E$4:$EN$4, 0) ) -> 784 | FW23: =$CI23 -> 13 | FX23: =$CJ23 -> Duchesne | FY23: =INDEX('2010'!$E$7:$EN$37, MATCH(FW23, '2010'!$A$7:$A$37, 0), MATCH(FW15, '2010'!$E$4:$EN$4, 0) ) -> 37 | FZ23: =INDEX('2011'!$E$7:$EN$37, MATCH(FW23, '2011'!$A$7:$A$37, 0), MATCH(FW15, '2011'!$E$4:$EN$4, 0) ) -> 19 | GA23: =INDEX('2012'!$E$7:$EN$37, MATCH(FW23, '2012'!$A$7:$A$37, 0), MATCH(FW15, '2012'!$E$4:$EN$4, 0) ) -> 28 | GB23: =INDEX('2013'!$E$7:$EN$37, MATCH(FW23, '2013'!$A$7:$A$37, 0), MATCH(FW15, '2013'!$E$4:$EN$4, 0) ) -> 35 | GC23: =INDEX('2014'!$E$7:$EN$37, MATCH(FW23, '2014'!$A$7:$A$37, 0), MATCH(FW15, '2014'!$E$4:$EN$4, 0) ) -> 45 | GD23: =INDEX('2015'!$E$7:$EN$37, MATCH(FW23, '2015'!$A$7:$A$37, 0), MATCH(FW15, '2015'!$E$4:$EN$4, 0) ) -> 71 | GE23: =INDEX('2016'!$E$7:$EN$37, MATCH(FW23, '2016'!$A$7:$A$37, 0), MATCH(FW15, '2016'!$E$4:$EN$4, 0) ) -> 99 | GF23: =INDEX('2017'!$E$7:$EN$37, MATCH(FW23, '2017'!$A$7:$A$37, 0), MATCH(FW15, '2017'!$E$4:$EN$4, 0) ) -> 133 | GG23: =INDEX('2018'!$E$7:$EN$37, MATCH(FW23, '2018'!$A$7:$A$37, 0), MATCH(FW15, '2018'!$E$4:$EN$4, 0) ) -> 156 | GH23: =INDEX('2019'!$E$7:$EN$37, MATCH(FW23, '2019'!$A$7:$A$37, 0), MATCH(FW15, '2019'!$E$4:$EN$4, 0) ) -> 196 | GJ23: =$CI23 -> 13 | GK23: =$CJ23 -> Duchesne | GL23: =INDEX('2010'!$E$7:$EN$37, MATCH(GJ23, '2010'!$A$7:$A$37, 0), MATCH(GJ15, '2010'!$E$4:$EN$4, 0) ) -> 154 | GM23: =INDEX('2011'!$E$7:$EN$37, MATCH(GJ23, '2011'!$A$7:$A$37, 0), MATCH(GJ15, '2011'!$E$4:$EN$4, 0) ) -> 171 | GN23: =INDEX('2012'!$E$7:$EN$37, MATCH(GJ23, '2012'!$A$7:$A$37, 0), MATCH(GJ15, '2012'!$E$4:$EN$4, 0) ) -> 97 | GO23: =INDEX('2013'!$E$7:$EN$37, MATCH(GJ23, '2013'!$A$7:$A$37, 0), MATCH(GJ15, '2013'!$E$4:$EN$4, 0) ) -> 98 | GP23: =INDEX('2014'!$E$7:$EN$37, MATCH(GJ23, '2014'!$A$7:$A$37, 0), MATCH(GJ15, '2014'!$E$4:$EN$4, 0) ) -> 71 | GQ23: =INDEX('2015'!$E$7:$EN$37, MATCH(GJ23, '2015'!$A$7:$A$37, 0), MATCH(GJ15, '2015'!$E$4:$EN$4, 0) ) -> 62 | GR23: =INDEX('2016'!$E$7:$EN$37, MATCH(GJ23, '2016'!$A$7:$A$37, 0), MATCH(GJ15, '2016'!$E$4:$EN$4, 0) ) -> 105 | GS23: =INDEX('2017'!$E$7:$EN$37, MATCH(GJ23, '2017'!$A$7:$A$37, 0), MATCH(GJ15, '2017'!$E$4:$EN$4, 0) ) -> 170 | GT23: =INDEX('2018'!$E$7:$EN$37, MATCH(GJ23, '2018'!$A$7:$A$37, 0), MATCH(GJ15, '2018'!$E$4:$EN$4, 0) ) -> 235 | GU23: =INDEX('2019'!$E$7:$EN$37, MATCH(GJ23, '2019'!$A$7:$A$37, 0), MATCH(GJ15, '2019'!$E$4:$EN$4, 0) ) -> 287
AZ24: 2010 | BA24: 2011 | BB24: 2012 | BC24: 2013 | BD24: 2014 | BE24: 2015 | BF24: 2016 | BG24: 2017 | BH24: 2018 | BI24: 2019 | CI24: 15 | CJ24: =VLOOKUP(CI24, lu_CoName, 2, FALSE) -> Emery | CK24: =CX24 + DK24 -> 0.056530214 | CL24: =CY24 + DL24 -> 0.060639964 | CM24: =CZ24 + DM24 -> 0.060759494 | CN24: =DA24 + DN24 -> 0.060698383 | CO24: =DB24 + DO24 -> 0.045751634 | CP24: =DC24 + DP24 -> 0.057916977 | CQ24: =DD24 + DQ24 -> 0.065846785 | CR24: =DE24 + DR24 -> 0.068076328 | ... CT24: =DG24 + DT24 -> 0.080545548 | CV24: =$CI24*10 + 0 -> 150 | CW24: =$CJ24 -> Emery | CX24: =IFERROR(DX24/EY24, 0) -> 0.02014295 | CY24: =IFERROR(DY24/EZ24, 0) -> 0.024837771 | CZ24: =IFERROR(DZ24/FA24, 0) -> 0.025776755 | DA24: =IFERROR(EA24/FB24, 0) -> 0.025076166 | DB24: =IFERROR(EB24/FC24, 0) -> 0.022754781 | DC24: =IFERROR(EC24/FD24, 0) -> 0.016902809 | DD24: =IFERROR(ED24/FE24, 0) -> 0.015116577 | DE24: =IFERROR(EE24/FF24, 0) -> 0.016503352 | ... DG24: =IFERROR(EG24/FH24, 0) -> 0.025476068 | DI24: =$CI24*10 + 0 -> 150 | DJ24: =$CJ24 -> Emery | DK24: =IFERROR(EK24/EY24, 0) -> 0.036387264 | DL24: =IFERROR(EL24/EZ24, 0) -> 0.035802193 | DM24: =IFERROR(EM24/FA24, 0) -> 0.034982739 | DN24: =IFERROR(EN24/FB24, 0) -> 0.035622217 | DO24: =IFERROR(EO24/FC24, 0) -> 0.022996853 | DP24: =IFERROR(EP24/FD24, 0) -> 0.041014169 | DQ24: =IFERROR(EQ24/FE24, 0) -> 0.050730208 | DR24: =IFERROR(ER24/FF24, 0) -> 0.051572976 | ... DT24: =IFERROR(ET24/FH24, 0) -> 0.05506948 | DV24: =$CI24*10 + 0 -> 150 | DW24: =$CJ24 -> Emery | DX24: =FL24 - EK24 -> 93 | DY24: =FM24 - EL24 -> 111 | DZ24: =FN24 - EM24 -> 112 | EA24: =FO24 - EN24 -> 107 | EB24: =FP24 - EO24 -> 94 | EC24: =FQ24 - EP24 -> 68 | ED24: =FR24 - EQ24 -> 59 | EE24: =FS24 - ER24 -> 64 | ... EG24: =FU24 - ET24 -> 99 | EI24: =$CI24*10 + 0 -> 150 | EJ24: =$CJ24 -> Emery | EK24: =FY24 + GL24 -> 168 | EL24: =FZ24 + GM24 -> 160 | EM24: =GA24 + GN24 -> 152 | EN24: =GB24 + GO24 -> 152 | EO24: =GC24 + GP24 -> 95 | EP24: =GD24 + GQ24 -> 165 | EQ24: =GE24 + GR24 -> 198 | ER24: =GF24 + GS24 -> 200 | ... ET24: =GH24 + GU24 -> 214 | EW24: =$CI24 -> 15 | EX24: =$CJ24 -> Emery | EY24: =INDEX('2010'!$E$7:$EN$37, MATCH(EW24, '2010'!$A$7:$A$37, 0), MATCH(EW15, '2010'!$E$4:$EN$4, 0) ) -> 4617 | EZ24: =INDEX('2011'!$E$7:$EN$37, MATCH(EW24, '2011'!$A$7:$A$37, 0), MATCH(EW15, '2011'!$E$4:$EN$4, 0) ) -> 4469 | FA24: =INDEX('2012'!$E$7:$EN$37, MATCH(EW24, '2012'!$A$7:$A$37, 0), MATCH(EW15, '2012'!$E$4:$EN$4, 0) ) -> 4345 | FB24: =INDEX('2013'!$E$7:$EN$37, MATCH(EW24, '2013'!$A$7:$A$37, 0), MATCH(EW15, '2013'!$E$4:$EN$4, 0) ) -> 4267 | FC24: =INDEX('2014'!$E$7:$EN$37, MATCH(EW24, '2014'!$A$7:$A$37, 0), MATCH(EW15, '2014'!$E$4:$EN$4, 0) ) -> 4131 | FD24: =INDEX('2015'!$E$7:$EN$37, MATCH(EW24, '2015'!$A$7:$A$37, 0), MATCH(EW15, '2015'!$E$4:$EN$4, 0) ) -> 4023 | FE24: =INDEX('2016'!$E$7:$EN$37, MATCH(EW24, '2016'!$A$7:$A$37, 0), MATCH(EW15, '2016'!$E$4:$EN$4, 0) ) -> 3903 | FF24: =INDEX('2017'!$E$7:$EN$37, MATCH(EW24, '2017'!$A$7:$A$37, 0), MATCH(EW15, '2017'!$E$4:$EN$4, 0) ) -> 3878 | FG24: =INDEX('2018'!$E$7:$EN$37, MATCH(EW24, '2018'!$A$7:$A$37, 0), MATCH(EW15, '2018'!$E$4:$EN$4, 0) ) -> 3861 | FH24: =INDEX('2019'!$E$7:$EN$37, MATCH(EW24, '2019'!$A$7:$A$37, 0), MATCH(EW15, '2019'!$E$4:$EN$4, 0) ) -> 3886 | FJ24: =$CI24 -> 15 | FK24: =$CJ24 -> Emery | FL24: =INDEX('2010'!$E$7:$EN$37, MATCH(FJ24, '2010'!$A$7:$A$37, 0), MATCH(FJ15, '2010'!$E$4:$EN$4, 0) ) -> 261 | FM24: =INDEX('2011'!$E$7:$EN$37, MATCH(FJ24, '2011'!$A$7:$A$37, 0), MATCH(FJ15, '2011'!$E$4:$EN$4, 0) ) -> 271 | FN24: =INDEX('2012'!$E$7:$EN$37, MATCH(FJ24, '2012'!$A$7:$A$37, 0), MATCH(FJ15, '2012'!$E$4:$EN$4, 0) ) -> 264 | FO24: =INDEX('2013'!$E$7:$EN$37, MATCH(FJ24, '2013'!$A$7:$A$37, 0), MATCH(FJ15, '2013'!$E$4:$EN$4, 0) ) -> 259 | FP24: =INDEX('2014'!$E$7:$EN$37, MATCH(FJ24, '2014'!$A$7:$A$37, 0), MATCH(FJ15, '2014'!$E$4:$EN$4, 0) ) -> 189 | FQ24: =INDEX('2015'!$E$7:$EN$37, MATCH(FJ24, '2015'!$A$7:$A$37, 0), MATCH(FJ15, '2015'!$E$4:$EN$4, 0) ) -> 233 | FR24: =INDEX('2016'!$E$7:$EN$37, MATCH(FJ24, '2016'!$A$7:$A$37, 0), MATCH(FJ15, '2016'!$E$4:$EN$4, 0) ) -> 257 | FS24: =INDEX('2017'!$E$7:$EN$37, MATCH(FJ24, '2017'!$A$7:$A$37, 0), MATCH(FJ15, '2017'!$E$4:$EN$4, 0) ) -> 264 | FT24: =INDEX('2018'!$E$7:$EN$37, MATCH(FJ24, '2018'!$A$7:$A$37, 0), MATCH(FJ15, '2018'!$E$4:$EN$4, 0) ) -> 297 | FU24: =INDEX('2019'!$E$7:$EN$37, MATCH(FJ24, '2019'!$A$7:$A$37, 0), MATCH(FJ15, '2019'!$E$4:$EN$4, 0) ) -> 313 | FW24: =$CI24 -> 15 | FX24: =$CJ24 -> Emery | FY24: =INDEX('2010'!$E$7:$EN$37, MATCH(FW24, '2010'!$A$7:$A$37, 0), MATCH(FW15, '2010'!$E$4:$EN$4, 0) ) -> 79 | FZ24: =INDEX('2011'!$E$7:$EN$37, MATCH(FW24, '2011'!$A$7:$A$37, 0), MATCH(FW15, '2011'!$E$4:$EN$4, 0) ) -> 77 | GA24: =INDEX('2012'!$E$7:$EN$37, MATCH(FW24, '2012'!$A$7:$A$37, 0), MATCH(FW15, '2012'!$E$4:$EN$4, 0) ) -> 89 | GB24: =INDEX('2013'!$E$7:$EN$37, MATCH(FW24, '2013'!$A$7:$A$37, 0), MATCH(FW15, '2013'!$E$4:$EN$4, 0) ) -> 87 | GC24: =INDEX('2014'!$E$7:$EN$37, MATCH(FW24, '2014'!$A$7:$A$37, 0), MATCH(FW15, '2014'!$E$4:$EN$4, 0) ) -> 31 | GD24: =INDEX('2015'!$E$7:$EN$37, MATCH(FW24, '2015'!$A$7:$A$37, 0), MATCH(FW15, '2015'!$E$4:$EN$4, 0) ) -> 28 | GE24: =INDEX('2016'!$E$7:$EN$37, MATCH(FW24, '2016'!$A$7:$A$37, 0), MATCH(FW15, '2016'!$E$4:$EN$4, 0) ) -> 29 | GF24: =INDEX('2017'!$E$7:$EN$37, MATCH(FW24, '2017'!$A$7:$A$37, 0), MATCH(FW15, '2017'!$E$4:$EN$4, 0) ) -> 13 | GG24: =INDEX('2018'!$E$7:$EN$37, MATCH(FW24, '2018'!$A$7:$A$37, 0), MATCH(FW15, '2018'!$E$4:$EN$4, 0) ) -> 42 | GH24: =INDEX('2019'!$E$7:$EN$37, MATCH(FW24, '2019'!$A$7:$A$37, 0), MATCH(FW15, '2019'!$E$4:$EN$4, 0) ) -> 41 | GJ24: =$CI24 -> 15 | GK24: =$CJ24 -> Emery | GL24: =INDEX('2010'!$E$7:$EN$37, MATCH(GJ24, '2010'!$A$7:$A$37, 0), MATCH(GJ15, '2010'!$E$4:$EN$4, 0) ) -> 89 | GM24: =INDEX('2011'!$E$7:$EN$37, MATCH(GJ24, '2011'!$A$7:$A$37, 0), MATCH(GJ15, '2011'!$E$4:$EN$4, 0) ) -> 83 | GN24: =INDEX('2012'!$E$7:$EN$37, MATCH(GJ24, '2012'!$A$7:$A$37, 0), MATCH(GJ15, '2012'!$E$4:$EN$4, 0) ) -> 63 | GO24: =INDEX('2013'!$E$7:$EN$37, MATCH(GJ24, '2013'!$A$7:$A$37, 0), MATCH(GJ15, '2013'!$E$4:$EN$4, 0) ) -> 65 | GP24: =INDEX('2014'!$E$7:$EN$37, MATCH(GJ24, '2014'!$A$7:$A$37, 0), MATCH(GJ15, '2014'!$E$4:$EN$4, 0) ) -> 64 | GQ24: =INDEX('2015'!$E$7:$EN$37, MATCH(GJ24, '2015'!$A$7:$A$37, 0), MATCH(GJ15, '2015'!$E$4:$EN$4, 0) ) -> 137 | GR24: =INDEX('2016'!$E$7:$EN$37, MATCH(GJ24, '2016'!$A$7:$A$37, 0), MATCH(GJ15, '2016'!$E$4:$EN$4, 0) ) -> 169 | GS24: =INDEX('2017'!$E$7:$EN$37, MATCH(GJ24, '2017'!$A$7:$A$37, 0), MATCH(GJ15, '2017'!$E$4:$EN$4, 0) ) -> 187 | GT24: =INDEX('2018'!$E$7:$EN$37, MATCH(GJ24, '2018'!$A$7:$A$37, 0), MATCH(GJ15, '2018'!$E$4:$EN$4, 0) ) -> 186 | GU24: =INDEX('2019'!$E$7:$EN$37, MATCH(GJ24, '2019'!$A$7:$A$37, 0), MATCH(GJ15, '2019'!$E$4:$EN$4, 0) ) -> 173
